Workbook

Sheet Painel
A1: VALVIC MARCENARIA
A2: Vargas Decor Ltda · CNPJ 17.269.304/0001-51 · Belo Horizonte / MG
A3: PAINEL DE PAGAMENTOS
A4: Tudo aqui é calculado a partir das abas de ano — não digite nada nesta aba
A6: VENDIDO EM 2026 | D6: RECEBIDO | G6: A RECEBER | J6: % RECEBIDO | M6: PROJETOS | P6: TICKET MÉDIO
A7: ='2026'!$A$7 | D7: ='2026'!$D$7 | G7: ='2026'!$F$7 | J7: ='2026'!$H$7 | M7: =COUNT('2026'!$X$10:$X$107) | P7: =IF(COUNT('2026'!$X$10:$X$107)=0,"",'2026'!$A$7/COUNT('2026'!$X$10:$X$107))
A9: ANO A ANO vendido, recebido e o que ficou em aberto
A10: Ano | B10: Projetos | C10: Vendido | D10: Recebido | E10: A receber | F10: % recebido | G10: Ticket médio
A11: 2026 | B11: =COUNT('2026'!$X$10:$X$107) | C11: ='2026'!$A$7 | D11: ='2026'!$D$7 | E11: ='2026'!$F$7 | F11: ='2026'!$H$7 | G11: =IF(COUNT('2026'!$X$10:$X$107)=0,"",'2026'!$A$7/COUNT('2026'!$X$10:$X$107))
A12: 2025 | B12: =COUNT('2025'!$X$10:$X$112) | C12: ='2025'!$A$7 | D12: ='2025'!$D$7 | E12: ='2025'!$F$7 | F12: ='2025'!$H$7 | G12: =IF(COUNT('2025'!$X$10:$X$112)=0,"",'2025'!$A$7/COUNT('2025'!$X$10:$X$112))
A13: 2024 | B13: =COUNT('2024'!$X$10:$X$108) | C13: ='2024'!$A$7 | D13: ='2024'!$D$7 | E13: ='2024'!$F$7 | F13: ='2024'!$H$7 | G13: =IF(COUNT('2024'!$X$10:$X$108)=0,"",'2024'!$A$7/COUNT('2024'!$X$10:$X$108))
A14: 2023 | B14: =COUNT('2023'!$X$26:$X$127) | C14: ='2023'!$A$7 | D14: ='2023'!$D$7 | E14: ='2023'!$F$7 | F14: ='2023'!$H$7 | G14: =IF(COUNT('2023'!$X$26:$X$127)=0,"",'2023'!$A$7/COUNT('2023'!$X$26:$X$127))
A16: 2026 MÊS A MÊS vendas pela data do contrato · acumulado comparado à meta
A17: Mês | B17: Projetos | C17: Vendido | D17: Recebido | E17: A receber | F17: % recebido | G17: Acum. vendido | H17: Meta acum.
A18: Janeiro | B18: =COUNT('2026'!$X$11:$X$19) | C18: ='2026'!$C$10 | D18: ='2026'!$E$10 | E18: ='2026'!$F$10 | F18: ='2026'!$G$10 | G18: =IF(DATE(2026,1,1)>TODAY(),"",IF(SUM($C$18:$C18)=0,"",SUM($C$18:$C18))) | H18: =ROUND('2026'!$I$7/12*1,0)
A19: Fevereiro | B19: =COUNT('2026'!$X$18:$X$26) | C19: ='2026'!$C$17 | D19: ='2026'!$E$17 | E19: ='2026'!$F$17 | F19: ='2026'!$G$17 | G19: =IF(DATE(2026,2,1)>TODAY(),"",IF(SUM($C$18:$C19)=0,"",SUM($C$18:$C19))) | H19: =ROUND('2026'!$I$7/12*2,0)
A20: Março | B20: =COUNT('2026'!$X$28:$X$36) | C20: ='2026'!$C$27 | D20: ='2026'!$E$27 | E20: ='2026'!$F$27 | F20: ='2026'!$G$27 | G20: =IF(DATE(2026,3,1)>TODAY(),"",IF(SUM($C$18:$C20)=0,"",SUM($C$18:$C20))) | H20: =ROUND('2026'!$I$7/12*3,0)
A21: Abril | B21: =COUNT('2026'!$X$39:$X$47) | C21: ='2026'!$C$38 | D21: ='2026'!$E$38 | E21: ='2026'!$F$38 | F21: ='2026'!$G$38 | G21: =IF(DATE(2026,4,1)>TODAY(),"",IF(SUM($C$18:$C21)=0,"",SUM($C$18:$C21))) | H21: =ROUND('2026'!$I$7/12*4,0)
A22: Maio | B22: =COUNT('2026'!$X$50:$X$58) | C22: ='2026'!$C$49 | D22: ='2026'!$E$49 | E22: ='2026'!$F$49 | F22: ='2026'!$G$49 | G22: =IF(DATE(2026,5,1)>TODAY(),"",IF(SUM($C$18:$C22)=0,"",SUM($C$18:$C22))) | H22: =ROUND('2026'!$I$7/12*5,0)
A23: Junho | B23: =COUNT('2026'!$X$59:$X$67) | C23: ='2026'!$C$58 | D23: ='2026'!$E$58 | E23: ='2026'!$F$58 | F23: ='2026'!$G$58 | G23: =IF(DATE(2026,6,1)>TODAY(),"",IF(SUM($C$18:$C23)=0,"",SUM($C$18:$C23))) | H23: =ROUND('2026'!$I$7/12*6,0)
A24: Julho | B24: =COUNT('2026'!$X$70:$X$78) | C24: ='2026'!$C$69 | D24: ='2026'!$E$69 | E24: ='2026'!$F$69 | F24: ='2026'!$G$69 | G24: =IF(DATE(2026,7,1)>TODAY(),"",IF(SUM($C$18:$C24)=0,"",SUM($C$18:$C24))) | H24: =ROUND('2026'!$I$7/12*7,0)
A25: Agosto | B25: =COUNT('2026'!$X$81:$X$89) | C25: ='2026'!$C$80 | D25: ='2026'!$E$80 | E25: ='2026'!$F$80 | F25: ='2026'!$G$80 | G25: =IF(DATE(2026,8,1)>TODAY(),"",IF(SUM($C$18:$C25)=0,"",SUM($C$18:$C25))) | H25: =ROUND('2026'!$I$7/12*8,0)
A26: Setembro | B26: =COUNT('2026'!$X$89:$X$97) | C26: ='2026'!$C$88 | D26: ='2026'!$E$88 | E26: ='2026'!$F$88 | F26: ='2026'!$G$88 | G26: =IF(DATE(2026,9,1)>TODAY(),"",IF(SUM($C$18:$C26)=0,"",SUM($C$18:$C26))) | H26: =ROUND('2026'!$I$7/12*9,0)
A27: Outubro | B27: =COUNT('2026'!$X$94:$X$102) | C27: ='2026'!$C$93 | D27: ='2026'!$E$93 | E27: ='2026'!$F$93 | F27: ='2026'!$G$93 | G27: =IF(DATE(2026,10,1)>TODAY(),"",IF(SUM($C$18:$C27)=0,"",SUM($C$18:$C27))) | H27: =ROUND('2026'!$I$7/12*10,0)
A28: Novembro | B28: =COUNT('2026'!$X$99:$X$107) | C28: ='2026'!$C$98 | D28: ='2026'!$E$98 | E28: ='2026'!$F$98 | F28: ='2026'!$G$98 | G28: =IF(DATE(2026,11,1)>TODAY(),"",IF(SUM($C$18:$C28)=0,"",SUM($C$18:$C28))) | H28: =ROUND('2026'!$I$7/12*11,0)
A29: Dezembro | B29: =COUNT('2026'!$X$104:$X$112) | C29: ='2026'!$C$103 | D29: ='2026'!$E$103 | E29: ='2026'!$F$103 | F29: ='2026'!$G$103 | G29: =IF(DATE(2026,12,1)>TODAY(),"",IF(SUM($C$18:$C29)=0,"",SUM($C$18:$C29))) | H29: =ROUND('2026'!$I$7/12*12,0)
A31: MAIORES SALDOS EM ABERTO DE 2026 ordenado pelo saldo · empate exato mostra o primeiro da lista
A32: # | B32: Cliente | C32: Projeto | D32: Investimento | E32: Recebido | F32: Saldo a receber | G32: % recebido | H32: % do total em aberto
A33: 1 | B33: =IF(COUNT('2026'!$X$10:$X$106)<1,"",IF(LARGE('2026'!$X$10:$X$106,1)<=0,"",INDEX('2026'!$A$10:$A$106,MATCH(LARGE('2026'!$X$10:$X$106,1),'2026'!$X$10:$X$106,0)))) | C33: =IF(COUNT('2026'!$X$10:$X$106)<1,"",IF(LARGE('2026'!$X$10:$X$106,1)<=0,"",INDEX('2026'!$B$10:$B$106,MATCH(LARGE('2026'!$X$10:$X$106,1),'2026'!$X$10:$X$106,0)))) | D33: =IF(COUNT('2026'!$X$10:$X$106)<1,"",IF(LARGE('2026'!$X$10:$X$106,1)<=0,"",INDEX('2026'!$C$10:$C$106,MATCH(LARGE('2026'!$X$10:$X$106,1),'2026'!$X$10:$X$106,0)))) | E33: =IF(COUNT('2026'!$X$10:$X$106)<1,"",IF(LARGE('2026'!$X$10:$X$106,1)<=0,"",INDEX('2026'!$E$10:$E$106,MATCH(LARGE('2026'!$X$10:$X$106,1),'2026'!$X$10:$X$106,0)))) | F33: =IF(COUNT('2026'!$X$10:$X$106)<1,"",IF(LARGE('2026'!$X$10:$X$106,1)<=0,"",LARGE('2026'!$X$10:$X$106,1))) | G33: =IF(COUNT('2026'!$X$10:$X$106)<1,"",IF(LARGE('2026'!$X$10:$X$106,1)<=0,"",INDEX('2026'!$G$10:$G$106,MATCH(LARGE('2026'!$X$10:$X$106,1),'2026'!$X$10:$X$106,0)))) | H33: =IF($F33="","",$F33/'2026'!$F$7)
A34: 2 | B34: =IF(COUNT('2026'!$X$10:$X$106)<2,"",IF(LARGE('2026'!$X$10:$X$106,2)<=0,"",INDEX('2026'!$A$10:$A$106,MATCH(LARGE('2026'!$X$10:$X$106,2),'2026'!$X$10:$X$106,0)))) | C34: =IF(COUNT('2026'!$X$10:$X$106)<2,"",IF(LARGE('2026'!$X$10:$X$106,2)<=0,"",INDEX('2026'!$B$10:$B$106,MATCH(LARGE('2026'!$X$10:$X$106,2),'2026'!$X$10:$X$106,0)))) | D34: =IF(COUNT('2026'!$X$10:$X$106)<2,"",IF(LARGE('2026'!$X$10:$X$106,2)<=0,"",INDEX('2026'!$C$10:$C$106,MATCH(LARGE('2026'!$X$10:$X$106,2),'2026'!$X$10:$X$106,0)))) | E34: =IF(COUNT('2026'!$X$10:$X$106)<2,"",IF(LARGE('2026'!$X$10:$X$106,2)<=0,"",INDEX('2026'!$E$10:$E$106,MATCH(LARGE('2026'!$X$10:$X$106,2),'2026'!$X$10:$X$106,0)))) | F34: =IF(COUNT('2026'!$X$10:$X$106)<2,"",IF(LARGE('2026'!$X$10:$X$106,2)<=0,"",LARGE('2026'!$X$10:$X$106,2))) | G34: =IF(COUNT('2026'!$X$10:$X$106)<2,"",IF(LARGE('2026'!$X$10:$X$106,2)<=0,"",INDEX('2026'!$G$10:$G$106,MATCH(LARGE('2026'!$X$10:$X$106,2),'2026'!$X$10:$X$106,0)))) | H34: =IF($F34="","",$F34/'2026'!$F$7)
A35: 3 | B35: =IF(COUNT('2026'!$X$10:$X$106)<3,"",IF(LARGE('2026'!$X$10:$X$106,3)<=0,"",INDEX('2026'!$A$10:$A$106,MATCH(LARGE('2026'!$X$10:$X$106,3),'2026'!$X$10:$X$106,0)))) | C35: =IF(COUNT('2026'!$X$10:$X$106)<3,"",IF(LARGE('2026'!$X$10:$X$106,3)<=0,"",INDEX('2026'!$B$10:$B$106,MATCH(LARGE('2026'!$X$10:$X$106,3),'2026'!$X$10:$X$106,0)))) | D35: =IF(COUNT('2026'!$X$10:$X$106)<3,"",IF(LARGE('2026'!$X$10:$X$106,3)<=0,"",INDEX('2026'!$C$10:$C$106,MATCH(LARGE('2026'!$X$10:$X$106,3),'2026'!$X$10:$X$106,0)))) | E35: =IF(COUNT('2026'!$X$10:$X$106)<3,"",IF(LARGE('2026'!$X$10:$X$106,3)<=0,"",INDEX('2026'!$E$10:$E$106,MATCH(LARGE('2026'!$X$10:$X$106,3),'2026'!$X$10:$X$106,0)))) | F35: =IF(COUNT('2026'!$X$10:$X$106)<3,"",IF(LARGE('2026'!$X$10:$X$106,3)<=0,"",LARGE('2026'!$X$10:$X$106,3))) | G35: =IF(COUNT('2026'!$X$10:$X$106)<3,"",IF(LARGE('2026'!$X$10:$X$106,3)<=0,"",INDEX('2026'!$G$10:$G$106,MATCH(LARGE('2026'!$X$10:$X$106,3),'2026'!$X$10:$X$106,0)))) | H35: =IF($F35="","",$F35/'2026'!$F$7)
A36: 4 | B36: =IF(COUNT('2026'!$X$10:$X$106)<4,"",IF(LARGE('2026'!$X$10:$X$106,4)<=0,"",INDEX('2026'!$A$10:$A$106,MATCH(LARGE('2026'!$X$10:$X$106,4),'2026'!$X$10:$X$106,0)))) | C36: =IF(COUNT('2026'!$X$10:$X$106)<4,"",IF(LARGE('2026'!$X$10:$X$106,4)<=0,"",INDEX('2026'!$B$10:$B$106,MATCH(LARGE('2026'!$X$10:$X$106,4),'2026'!$X$10:$X$106,0)))) | D36: =IF(COUNT('2026'!$X$10:$X$106)<4,"",IF(LARGE('2026'!$X$10:$X$106,4)<=0,"",INDEX('2026'!$C$10:$C$106,MATCH(LARGE('2026'!$X$10:$X$106,4),'2026'!$X$10:$X$106,0)))) | E36: =IF(COUNT('2026'!$X$10:$X$106)<4,"",IF(LARGE('2026'!$X$10:$X$106,4)<=0,"",INDEX('2026'!$E$10:$E$106,MATCH(LARGE('2026'!$X$10:$X$106,4),'2026'!$X$10:$X$106,0)))) | F36: =IF(COUNT('2026'!$X$10:$X$106)<4,"",IF(LARGE('2026'!$X$10:$X$106,4)<=0,"",LARGE('2026'!$X$10:$X$106,4))) | G36: =IF(COUNT('2026'!$X$10:$X$106)<4,"",IF(LARGE('2026'!$X$10:$X$106,4)<=0,"",INDEX('2026'!$G$10:$G$106,MATCH(LARGE('2026'!$X$10:$X$106,4),'2026'!$X$10:$X$106,0)))) | H36: =IF($F36="","",$F36/'2026'!$F$7)
A37: 5 | B37: =IF(COUNT('2026'!$X$10:$X$106)<5,"",IF(LARGE('2026'!$X$10:$X$106,5)<=0,"",INDEX('2026'!$A$10:$A$106,MATCH(LARGE('2026'!$X$10:$X$106,5),'2026'!$X$10:$X$106,0)))) | C37: =IF(COUNT('2026'!$X$10:$X$106)<5,"",IF(LARGE('2026'!$X$10:$X$106,5)<=0,"",INDEX('2026'!$B$10:$B$106,MATCH(LARGE('2026'!$X$10:$X$106,5),'2026'!$X$10:$X$106,0)))) | D37: =IF(COUNT('2026'!$X$10:$X$106)<5,"",IF(LARGE('2026'!$X$10:$X$106,5)<=0,"",INDEX('2026'!$C$10:$C$106,MATCH(LARGE('2026'!$X$10:$X$106,5),'2026'!$X$10:$X$106,0)))) | E37: =IF(COUNT('2026'!$X$10:$X$106)<5,"",IF(LARGE('2026'!$X$10:$X$106,5)<=0,"",INDEX('2026'!$E$10:$E$106,MATCH(LARGE('2026'!$X$10:$X$106,5),'2026'!$X$10:$X$106,0)))) | F37: =IF(COUNT('2026'!$X$10:$X$106)<5,"",IF(LARGE('2026'!$X$10:$X$106,5)<=0,"",LARGE('2026'!$X$10:$X$106,5))) | G37: =IF(COUNT('2026'!$X$10:$X$106)<5,"",IF(LARGE('2026'!$X$10:$X$106,5)<=0,"",INDEX('2026'!$G$10:$G$106,MATCH(LARGE('2026'!$X$10:$X$106,5),'2026'!$X$10:$X$106,0)))) | H37: =IF($F37="","",$F37/'2026'!$F$7)
A38: 6 | B38: =IF(COUNT('2026'!$X$10:$X$106)<6,"",IF(LARGE('2026'!$X$10:$X$106,6)<=0,"",INDEX('2026'!$A$10:$A$106,MATCH(LARGE('2026'!$X$10:$X$106,6),'2026'!$X$10:$X$106,0)))) | C38: =IF(COUNT('2026'!$X$10:$X$106)<6,"",IF(LARGE('2026'!$X$10:$X$106,6)<=0,"",INDEX('2026'!$B$10:$B$106,MATCH(LARGE('2026'!$X$10:$X$106,6),'2026'!$X$10:$X$106,0)))) | D38: =IF(COUNT('2026'!$X$10:$X$106)<6,"",IF(LARGE('2026'!$X$10:$X$106,6)<=0,"",INDEX('2026'!$C$10:$C$106,MATCH(LARGE('2026'!$X$10:$X$106,6),'2026'!$X$10:$X$106,0)))) | E38: =IF(COUNT('2026'!$X$10:$X$106)<6,"",IF(LARGE('2026'!$X$10:$X$106,6)<=0,"",INDEX('2026'!$E$10:$E$106,MATCH(LARGE('2026'!$X$10:$X$106,6),'2026'!$X$10:$X$106,0)))) | F38: =IF(COUNT('2026'!$X$10:$X$106)<6,"",IF(LARGE('2026'!$X$10:$X$106,6)<=0,"",LARGE('2026'!$X$10:$X$106,6))) | G38: =IF(COUNT('2026'!$X$10:$X$106)<6,"",IF(LARGE('2026'!$X$10:$X$106,6)<=0,"",INDEX('2026'!$G$10:$G$106,MATCH(LARGE('2026'!$X$10:$X$106,6),'2026'!$X$10:$X$106,0)))) | H38: =IF($F38="","",$F38/'2026'!$F$7)
A39: 7 | B39: =IF(COUNT('2026'!$X$10:$X$106)<7,"",IF(LARGE('2026'!$X$10:$X$106,7)<=0,"",INDEX('2026'!$A$10:$A$106,MATCH(LARGE('2026'!$X$10:$X$106,7),'2026'!$X$10:$X$106,0)))) | C39: =IF(COUNT('2026'!$X$10:$X$106)<7,"",IF(LARGE('2026'!$X$10:$X$106,7)<=0,"",INDEX('2026'!$B$10:$B$106,MATCH(LARGE('2026'!$X$10:$X$106,7),'2026'!$X$10:$X$106,0)))) | D39: =IF(COUNT('2026'!$X$10:$X$106)<7,"",IF(LARGE('2026'!$X$10:$X$106,7)<=0,"",INDEX('2026'!$C$10:$C$106,MATCH(LARGE('2026'!$X$10:$X$106,7),'2026'!$X$10:$X$106,0)))) | E39: =IF(COUNT('2026'!$X$10:$X$106)<7,"",IF(LARGE('2026'!$X$10:$X$106,7)<=0,"",INDEX('2026'!$E$10:$E$106,MATCH(LARGE('2026'!$X$10:$X$106,7),'2026'!$X$10:$X$106,0)))) | F39: =IF(COUNT('2026'!$X$10:$X$106)<7,"",IF(LARGE('2026'!$X$10:$X$106,7)<=0,"",LARGE('2026'!$X$10:$X$106,7))) | G39: =IF(COUNT('2026'!$X$10:$X$106)<7,"",IF(LARGE('2026'!$X$10:$X$106,7)<=0,"",INDEX('2026'!$G$10:$G$106,MATCH(LARGE('2026'!$X$10:$X$106,7),'2026'!$X$10:$X$106,0)))) | H39: =IF($F39="","",$F39/'2026'!$F$7)
A40: 8 | B40: =IF(COUNT('2026'!$X$10:$X$106)<8,"",IF(LARGE('2026'!$X$10:$X$106,8)<=0,"",INDEX('2026'!$A$10:$A$106,MATCH(LARGE('2026'!$X$10:$X$106,8),'2026'!$X$10:$X$106,0)))) | C40: =IF(COUNT('2026'!$X$10:$X$106)<8,"",IF(LARGE('2026'!$X$10:$X$106,8)<=0,"",INDEX('2026'!$B$10:$B$106,MATCH(LARGE('2026'!$X$10:$X$106,8),'2026'!$X$10:$X$106,0)))) | D40: =IF(COUNT('2026'!$X$10:$X$106)<8,"",IF(LARGE('2026'!$X$10:$X$106,8)<=0,"",INDEX('2026'!$C$10:$C$106,MATCH(LARGE('2026'!$X$10:$X$106,8),'2026'!$X$10:$X$106,0)))) | E40: =IF(COUNT('2026'!$X$10:$X$106)<8,"",IF(LARGE('2026'!$X$10:$X$106,8)<=0,"",INDEX('2026'!$E$10:$E$106,MATCH(LARGE('2026'!$X$10:$X$106,8),'2026'!$X$10:$X$106,0)))) | F40: =IF(COUNT('2026'!$X$10:$X$106)<8,"",IF(LARGE('2026'!$X$10:$X$106,8)<=0,"",LARGE('2026'!$X$10:$X$106,8))) | G40: =IF(COUNT('2026'!$X$10:$X$106)<8,"",IF(LARGE('2026'!$X$10:$X$106,8)<=0,"",INDEX('2026'!$G$10:$G$106,MATCH(LARGE('2026'!$X$10:$X$106,8),'2026'!$X$10:$X$106,0)))) | H40: =IF($F40="","",$F40/'2026'!$F$7)
A41: 9 | B41: =IF(COUNT('2026'!$X$10:$X$106)<9,"",IF(LARGE('2026'!$X$10:$X$106,9)<=0,"",INDEX('2026'!$A$10:$A$106,MATCH(LARGE('2026'!$X$10:$X$106,9),'2026'!$X$10:$X$106,0)))) | C41: =IF(COUNT('2026'!$X$10:$X$106)<9,"",IF(LARGE('2026'!$X$10:$X$106,9)<=0,"",INDEX('2026'!$B$10:$B$106,MATCH(LARGE('2026'!$X$10:$X$106,9),'2026'!$X$10:$X$106,0)))) | D41: =IF(COUNT('2026'!$X$10:$X$106)<9,"",IF(LARGE('2026'!$X$10:$X$106,9)<=0,"",INDEX('2026'!$C$10:$C$106,MATCH(LARGE('2026'!$X$10:$X$106,9),'2026'!$X$10:$X$106,0)))) | E41: =IF(COUNT('2026'!$X$10:$X$106)<9,"",IF(LARGE('2026'!$X$10:$X$106,9)<=0,"",INDEX('2026'!$E$10:$E$106,MATCH(LARGE('2026'!$X$10:$X$106,9),'2026'!$X$10:$X$106,0)))) | F41: =IF(COUNT('2026'!$X$10:$X$106)<9,"",IF(LARGE('2026'!$X$10:$X$106,9)<=0,"",LARGE('2026'!$X$10:$X$106,9))) | G41: =IF(COUNT('2026'!$X$10:$X$106)<9,"",IF(LARGE('2026'!$X$10:$X$106,9)<=0,"",INDEX('2026'!$G$10:$G$106,MATCH(LARGE('2026'!$X$10:$X$106,9),'2026'!$X$10:$X$106,0)))) | H41: =IF($F41="","",$F41/'2026'!$F$7)
A42: 10 | B42: =IF(COUNT('2026'!$X$10:$X$106)<10,"",IF(LARGE('2026'!$X$10:$X$106,10)<=0,"",INDEX('2026'!$A$10:$A$106,MATCH(LARGE('2026'!$X$10:$X$106,10),'2026'!$X$10:$X$106,0)))) | C42: =IF(COUNT('2026'!$X$10:$X$106)<10,"",IF(LARGE('2026'!$X$10:$X$106,10)<=0,"",INDEX('2026'!$B$10:$B$106,MATCH(LARGE('2026'!$X$10:$X$106,10),'2026'!$X$10:$X$106,0)))) | D42: =IF(COUNT('2026'!$X$10:$X$106)<10,"",IF(LARGE('2026'!$X$10:$X$106,10)<=0,"",INDEX('2026'!$C$10:$C$106,MATCH(LARGE('2026'!$X$10:$X$106,10),'2026'!$X$10:$X$106,0)))) | E42: =IF(COUNT('2026'!$X$10:$X$106)<10,"",IF(LARGE('2026'!$X$10:$X$106,10)<=0,"",INDEX('2026'!$E$10:$E$106,MATCH(LARGE('2026'!$X$10:$X$106,10),'2026'!$X$10:$X$106,0)))) | F42: =IF(COUNT('2026'!$X$10:$X$106)<10,"",IF(LARGE('2026'!$X$10:$X$106,10)<=0,"",LARGE('2026'!$X$10:$X$106,10))) | G42: =IF(COUNT('2026'!$X$10:$X$106)<10,"",IF(LARGE('2026'!$X$10:$X$106,10)<=0,"",INDEX('2026'!$G$10:$G$106,MATCH(LARGE('2026'!$X$10:$X$106,10),'2026'!$X$10:$X$106,0)))) | H42: =IF($F42="","",$F42/'2026'!$F$7)
A43: 11 | B43: =IF(COUNT('2026'!$X$10:$X$106)<11,"",IF(LARGE('2026'!$X$10:$X$106,11)<=0,"",INDEX('2026'!$A$10:$A$106,MATCH(LARGE('2026'!$X$10:$X$106,11),'2026'!$X$10:$X$106,0)))) | C43: =IF(COUNT('2026'!$X$10:$X$106)<11,"",IF(LARGE('2026'!$X$10:$X$106,11)<=0,"",INDEX('2026'!$B$10:$B$106,MATCH(LARGE('2026'!$X$10:$X$106,11),'2026'!$X$10:$X$106,0)))) | D43: =IF(COUNT('2026'!$X$10:$X$106)<11,"",IF(LARGE('2026'!$X$10:$X$106,11)<=0,"",INDEX('2026'!$C$10:$C$106,MATCH(LARGE('2026'!$X$10:$X$106,11),'2026'!$X$10:$X$106,0)))) | E43: =IF(COUNT('2026'!$X$10:$X$106)<11,"",IF(LARGE('2026'!$X$10:$X$106,11)<=0,"",INDEX('2026'!$E$10:$E$106,MATCH(LARGE('2026'!$X$10:$X$106,11),'2026'!$X$10:$X$106,0)))) | F43: =IF(COUNT('2026'!$X$10:$X$106)<11,"",IF(LARGE('2026'!$X$10:$X$106,11)<=0,"",LARGE('2026'!$X$10:$X$106,11))) | G43: =IF(COUNT('2026'!$X$10:$X$106)<11,"",IF(LARGE('2026'!$X$10:$X$106,11)<=0,"",INDEX('2026'!$G$10:$G$106,MATCH(LARGE('2026'!$X$10:$X$106,11),'2026'!$X$10:$X$106,0)))) | H43: =IF($F43="","",$F43/'2026'!$F$7)
A44: 12 | B44: =IF(COUNT('2026'!$X$10:$X$106)<12,"",IF(LARGE('2026'!$X$10:$X$106,12)<=0,"",INDEX('2026'!$A$10:$A$106,MATCH(LARGE('2026'!$X$10:$X$106,12),'2026'!$X$10:$X$106,0)))) | C44: =IF(COUNT('2026'!$X$10:$X$106)<12,"",IF(LARGE('2026'!$X$10:$X$106,12)<=0,"",INDEX('2026'!$B$10:$B$106,MATCH(LARGE('2026'!$X$10:$X$106,12),'2026'!$X$10:$X$106,0)))) | D44: =IF(COUNT('2026'!$X$10:$X$106)<12,"",IF(LARGE('2026'!$X$10:$X$106,12)<=0,"",INDEX('2026'!$C$10:$C$106,MATCH(LARGE('2026'!$X$10:$X$106,12),'2026'!$X$10:$X$106,0)))) | E44: =IF(COUNT('2026'!$X$10:$X$106)<12,"",IF(LARGE('2026'!$X$10:$X$106,12)<=0,"",INDEX('2026'!$E$10:$E$106,MATCH(LARGE('2026'!$X$10:$X$106,12),'2026'!$X$10:$X$106,0)))) | F44: =IF(COUNT('2026'!$X$10:$X$106)<12,"",IF(LARGE('2026'!$X$10:$X$106,12)<=0,"",LARGE('2026'!$X$10:$X$106,12))) | G44: =IF(COUNT('2026'!$X$10:$X$106)<12,"",IF(LARGE('2026'!$X$10:$X$106,12)<=0,"",INDEX('2026'!$G$10:$G$106,MATCH(LARGE('2026'!$X$10:$X$106,12),'2026'!$X$10:$X$106,0)))) | H44: =IF($F44="","",$F44/'2026'!$F$7)
A46: LEITURA DO QUADRO frases montadas a partir dos números acima
A47: ="Concentração da carteira em aberto: os 3 maiores saldos somam "&TEXT(SUM($F$33:$F$35),"R$ #,##0")&" de "&TEXT('2026'!$F$7,"R$ #,##0")&" — "&TEXT(SUM($F$33:$F$35)/'2026'!$F$7,"0%")&" do total a receber."
A48: ="Ritmo do ano até "&INDEX($A$18:$A$29,MONTH(TODAY()))&": vendido "&TEXT('2026'!$A$7,"R$ #,##0")&" contra meta acumulada de "&TEXT(INDEX($H$18:$H$29,MONTH(TODAY())),"R$ #,##0")&" — "&IF('2026'!$A$7>=INDEX($H$18:$H$29,MONTH(TODAY())),"acima do ritmo necessário.","faltam "&TEXT(INDEX($H$18:$H$29,MONTH(TODAY()))-'2026'!$A$7,"R$ #,##0")&" para o ritmo da meta.")
A49: ="Projetos sem nenhum recebimento em 2026: "&COUNTIF('2026'!$H$10:$H$106,"A receber")&" de "&COUNT('2026'!$X$10:$X$107)&" — somam "&TEXT(SUMIF('2026'!$H$10:$H$106,"A receber",'2026'!$C$10:$C$106),"R$ #,##0")&" de contrato."
A50: ="Veja a aba Análise & Sazonalidade para o fluxo de caixa mês a mês e o padrão sazonal de vendas."

Sheet Análise & Sazonalidade
A1: VALVIC MARCENARIA
A2: Vargas Decor Ltda · CNPJ 17.269.304/0001-51 · Belo Horizonte / MG
A3: ANÁLISE & SAZONALIDADE
A4: Fluxo de caixa pela data do pagamento · padrão sazonal de vendas · concentração da carteira
A6: FLUXO DE CAIXA REALIZADO quanto entrou em cada mês, pela DATA DO PAGAMENTO — não pela data do contrato
A7: Mês | B7: 2023 | C7: 2024 | D7: 2025 | E7: 2026 | F7: Média 23–25 | G7: Peso no ano
A8: Janeiro | B8: =ROUND(SUMIFS('2026'!$I$10:$I$107,'2026'!$J$10:$J$107,">="&DATE(2023,1,1),'2026'!$J$10:$J$107,"<"&DATE(2023,2,1))+SUMIFS('2026'!$L$10:$L$107,'2026'!$M$10:$M$107,">="&DATE(2023,1,1),'2026'!$M$10:$M$107,"<"&DATE(2023,2,1))+SUMIFS('2026'!$O$10:$O$107,'2026'!$P$10:$P$107,">="&DATE(2023,1,1),'2026'!$P$10:$P$107,"<"&DATE(2023,2,1))+SUMIFS('2026'!$R$10:$R$107,'2026'!$S$10:$S$107,">="&DATE(2023,1,1),'2026'!$S$10:$S$107,"<"&DATE(2023,2,1))+SUMIFS('2026'!$U$10:$U$107,'2026'!$V$10:$V$107,">="&DATE(2023,1,1),'2026'!$V$10:$V$107,"<"&DATE(2023,2,1))+SUMIFS('2025'!$I$10:$I$112,'2025'!$J$10:$J$112,">="&DATE(2023,1,1),'2025'!$J$10:$J$112,"<"&DATE(2023,2,1))+SUMIFS('2025'!$L$10:$L$112,'2025'!$M$10:$M$112,">="&DATE(2023,1,1),'2025'!$M$10:$M$112,"<"&DATE(2023,2,1))+SUMIFS('2025'!$O$10:$O$112,'2025'!$P$10:$P$112,">="&DATE(2023,1,1),'2025'!$P$10:$P$112,"<"&DATE(2023,2,1))+SUMIFS('2025'!$R$10:$R$112,'2025'!$S$10:$S$112,">="&DATE(2023,1,1),'2025'!$S$10:$S$112,"<"&DATE(2023,2,1))+SUMIFS('2025'!$U$10:$U$112,'2025'!$V$10:$V$112,">="&DATE(2023,1,1),'2025'!$V$10:$V$112,"<"&DATE(2023,2,1))+SUMIFS('2024'!$I$10:$I$108,'2024'!$J$10:$J$108,">="&DATE(2023,1,1),'2024'!$J$10:$J$108,"<"&DATE(2023,2,1))+SUMIFS('2024'!$L$10:$L$108,'2024'!$M$10:$M$108,">="&DATE(2023,1,1),'2024'!$M$10:$M$108,"<"&DATE(2023,2,1))+SUMIFS('2024'!$O$10:$O$108,'2024'!$P$10:$P$108,">="&DATE(2023,1,1),'2024'!$P$10:$P$108,"<"&DATE(2023,2,1))+SUMIFS('2024'!$R$10:$R$108,'2024'!$S$10:$S$108,">="&DATE(2023,1,1),'2024'!$S$10:$S$108,"<"&DATE(2023,2,1))+SUMIFS('2024'!$U$10:$U$108,'2024'!$V$10:$V$108,">="&DATE(2023,1,1),'2024'!$V$10:$V$108,"<"&DATE(2023,2,1))+SUMIFS('2023'!$I$10:$I$127,'2023'!$J$10:$J$127,">="&DATE(2023,1,1),'2023'!$J$10:$J$127,"<"&DATE(2023,2,1))+SUMIFS('2023'!$L$10:$L$127,'2023'!$M$10:$M$127,">="&DATE(2023,1,1),'2023'!$M$10:$M$127,"<"&DATE(2023,2,1))+SUMIFS('2023'!$O$10:$O$127,'2023'!$P$10:$P$127,">="&DATE(2023,1,1),'2023'!$P$10:$P$127,"<"&DATE(2023,2,1))+SUMIFS('2023'!$R$10:$R$127,'2023'!$S$10:$S$127,">="&DATE(2023,1,1),'2023'!$S$10:$S$127,"<"&DATE(2023,2,1))+SUMIFS('2023'!$U$10:$U$127,'2023'!$V$10:$V$127,">="&DATE(2023,1,1),'2023'!$V$10:$V$127,"<"&DATE(2023,2,1)),2) | C8: =ROUND(SUMIFS('2026'!$I$10:$I$107,'2026'!$J$10:$J$107,">="&DATE(2024,1,1),'2026'!$J$10:$J$107,"<"&DATE(2024,2,1))+SUMIFS('2026'!$L$10:$L$107,'2026'!$M$10:$M$107,">="&DATE(2024,1,1),'2026'!$M$10:$M$107,"<"&DATE(2024,2,1))+SUMIFS('2026'!$O$10:$O$107,'2026'!$P$10:$P$107,">="&DATE(2024,1,1),'2026'!$P$10:$P$107,"<"&DATE(2024,2,1))+SUMIFS('2026'!$R$10:$R$107,'2026'!$S$10:$S$107,">="&DATE(2024,1,1),'2026'!$S$10:$S$107,"<"&DATE(2024,2,1))+SUMIFS('2026'!$U$10:$U$107,'2026'!$V$10:$V$107,">="&DATE(2024,1,1),'2026'!$V$10:$V$107,"<"&DATE(2024,2,1))+SUMIFS('2025'!$I$10:$I$112,'2025'!$J$10:$J$112,">="&DATE(2024,1,1),'2025'!$J$10:$J$112,"<"&DATE(2024,2,1))+SUMIFS('2025'!$L$10:$L$112,'2025'!$M$10:$M$112,">="&DATE(2024,1,1),'2025'!$M$10:$M$112,"<"&DATE(2024,2,1))+SUMIFS('2025'!$O$10:$O$112,'2025'!$P$10:$P$112,">="&DATE(2024,1,1),'2025'!$P$10:$P$112,"<"&DATE(2024,2,1))+SUMIFS('2025'!$R$10:$R$112,'2025'!$S$10:$S$112,">="&DATE(2024,1,1),'2025'!$S$10:$S$112,"<"&DATE(2024,2,1))+SUMIFS('2025'!$U$10:$U$112,'2025'!$V$10:$V$112,">="&DATE(2024,1,1),'2025'!$V$10:$V$112,"<"&DATE(2024,2,1))+SUMIFS('2024'!$I$10:$I$108,'2024'!$J$10:$J$108,">="&DATE(2024,1,1),'2024'!$J$10:$J$108,"<"&DATE(2024,2,1))+SUMIFS('2024'!$L$10:$L$108,'2024'!$M$10:$M$108,">="&DATE(2024,1,1),'2024'!$M$10:$M$108,"<"&DATE(2024,2,1))+SUMIFS('2024'!$O$10:$O$108,'2024'!$P$10:$P$108,">="&DATE(2024,1,1),'2024'!$P$10:$P$108,"<"&DATE(2024,2,1))+SUMIFS('2024'!$R$10:$R$108,'2024'!$S$10:$S$108,">="&DATE(2024,1,1),'2024'!$S$10:$S$108,"<"&DATE(2024,2,1))+SUMIFS('2024'!$U$10:$U$108,'2024'!$V$10:$V$108,">="&DATE(2024,1,1),'2024'!$V$10:$V$108,"<"&DATE(2024,2,1))+SUMIFS('2023'!$I$10:$I$127,'2023'!$J$10:$J$127,">="&DATE(2024,1,1),'2023'!$J$10:$J$127,"<"&DATE(2024,2,1))+SUMIFS('2023'!$L$10:$L$127,'2023'!$M$10:$M$127,">="&DATE(2024,1,1),'2023'!$M$10:$M$127,"<"&DATE(2024,2,1))+SUMIFS('2023'!$O$10:$O$127,'2023'!$P$10:$P$127,">="&DATE(2024,1,1),'2023'!$P$10:$P$127,"<"&DATE(2024,2,1))+SUMIFS('2023'!$R$10:$R$127,'2023'!$S$10:$S$127,">="&DATE(2024,1,1),'2023'!$S$10:$S$127,"<"&DATE(2024,2,1))+SUMIFS('2023'!$U$10:$U$127,'2023'!$V$10:$V$127,">="&DATE(2024,1,1),'2023'!$V$10:$V$127,"<"&DATE(2024,2,1)),2) | D8: =ROUND(SUMIFS('2026'!$I$10:$I$107,'2026'!$J$10:$J$107,">="&DATE(2025,1,1),'2026'!$J$10:$J$107,"<"&DATE(2025,2,1))+SUMIFS('2026'!$L$10:$L$107,'2026'!$M$10:$M$107,">="&DATE(2025,1,1),'2026'!$M$10:$M$107,"<"&DATE(2025,2,1))+SUMIFS('2026'!$O$10:$O$107,'2026'!$P$10:$P$107,">="&DATE(2025,1,1),'2026'!$P$10:$P$107,"<"&DATE(2025,2,1))+SUMIFS('2026'!$R$10:$R$107,'2026'!$S$10:$S$107,">="&DATE(2025,1,1),'2026'!$S$10:$S$107,"<"&DATE(2025,2,1))+SUMIFS('2026'!$U$10:$U$107,'2026'!$V$10:$V$107,">="&DATE(2025,1,1),'2026'!$V$10:$V$107,"<"&DATE(2025,2,1))+SUMIFS('2025'!$I$10:$I$112,'2025'!$J$10:$J$112,">="&DATE(2025,1,1),'2025'!$J$10:$J$112,"<"&DATE(2025,2,1))+SUMIFS('2025'!$L$10:$L$112,'2025'!$M$10:$M$112,">="&DATE(2025,1,1),'2025'!$M$10:$M$112,"<"&DATE(2025,2,1))+SUMIFS('2025'!$O$10:$O$112,'2025'!$P$10:$P$112,">="&DATE(2025,1,1),'2025'!$P$10:$P$112,"<"&DATE(2025,2,1))+SUMIFS('2025'!$R$10:$R$112,'2025'!$S$10:$S$112,">="&DATE(2025,1,1),'2025'!$S$10:$S$112,"<"&DATE(2025,2,1))+SUMIFS('2025'!$U$10:$U$112,'2025'!$V$10:$V$112,">="&DATE(2025,1,1),'2025'!$V$10:$V$112,"<"&DATE(2025,2,1))+SUMIFS('2024'!$I$10:$I$108,'2024'!$J$10:$J$108,">="&DATE(2025,1,1),'2024'!$J$10:$J$108,"<"&DATE(2025,2,1))+SUMIFS('2024'!$L$10:$L$108,'2024'!$M$10:$M$108,">="&DATE(2025,1,1),'2024'!$M$10:$M$108,"<"&DATE(2025,2,1))+SUMIFS('2024'!$O$10:$O$108,'2024'!$P$10:$P$108,">="&DATE(2025,1,1),'2024'!$P$10:$P$108,"<"&DATE(2025,2,1))+SUMIFS('2024'!$R$10:$R$108,'2024'!$S$10:$S$108,">="&DATE(2025,1,1),'2024'!$S$10:$S$108,"<"&DATE(2025,2,1))+SUMIFS('2024'!$U$10:$U$108,'2024'!$V$10:$V$108,">="&DATE(2025,1,1),'2024'!$V$10:$V$108,"<"&DATE(2025,2,1))+SUMIFS('2023'!$I$10:$I$127,'2023'!$J$10:$J$127,">="&DATE(2025,1,1),'2023'!$J$10:$J$127,"<"&DATE(2025,2,1))+SUMIFS('2023'!$L$10:$L$127,'2023'!$M$10:$M$127,">="&DATE(2025,1,1),'2023'!$M$10:$M$127,"<"&DATE(2025,2,1))+SUMIFS('2023'!$O$10:$O$127,'2023'!$P$10:$P$127,">="&DATE(2025,1,1),'2023'!$P$10:$P$127,"<"&DATE(2025,2,1))+SUMIFS('2023'!$R$10:$R$127,'2023'!$S$10:$S$127,">="&DATE(2025,1,1),'2023'!$S$10:$S$127,"<"&DATE(2025,2,1))+SUMIFS('2023'!$U$10:$U$127,'2023'!$V$10:$V$127,">="&DATE(2025,1,1),'2023'!$V$10:$V$127,"<"&DATE(2025,2,1)),2) | E8: =ROUND(SUMIFS('2026'!$I$10:$I$107,'2026'!$J$10:$J$107,">="&DATE(2026,1,1),'2026'!$J$10:$J$107,"<"&DATE(2026,2,1))+SUMIFS('2026'!$L$10:$L$107,'2026'!$M$10:$M$107,">="&DATE(2026,1,1),'2026'!$M$10:$M$107,"<"&DATE(2026,2,1))+SUMIFS('2026'!$O$10:$O$107,'2026'!$P$10:$P$107,">="&DATE(2026,1,1),'2026'!$P$10:$P$107,"<"&DATE(2026,2,1))+SUMIFS('2026'!$R$10:$R$107,'2026'!$S$10:$S$107,">="&DATE(2026,1,1),'2026'!$S$10:$S$107,"<"&DATE(2026,2,1))+SUMIFS('2026'!$U$10:$U$107,'2026'!$V$10:$V$107,">="&DATE(2026,1,1),'2026'!$V$10:$V$107,"<"&DATE(2026,2,1))+SUMIFS('2025'!$I$10:$I$112,'2025'!$J$10:$J$112,">="&DATE(2026,1,1),'2025'!$J$10:$J$112,"<"&DATE(2026,2,1))+SUMIFS('2025'!$L$10:$L$112,'2025'!$M$10:$M$112,">="&DATE(2026,1,1),'2025'!$M$10:$M$112,"<"&DATE(2026,2,1))+SUMIFS('2025'!$O$10:$O$112,'2025'!$P$10:$P$112,">="&DATE(2026,1,1),'2025'!$P$10:$P$112,"<"&DATE(2026,2,1))+SUMIFS('2025'!$R$10:$R$112,'2025'!$S$10:$S$112,">="&DATE(2026,1,1),'2025'!$S$10:$S$112,"<"&DATE(2026,2,1))+SUMIFS('2025'!$U$10:$U$112,'2025'!$V$10:$V$112,">="&DATE(2026,1,1),'2025'!$V$10:$V$112,"<"&DATE(2026,2,1))+SUMIFS('2024'!$I$10:$I$108,'2024'!$J$10:$J$108,">="&DATE(2026,1,1),'2024'!$J$10:$J$108,"<"&DATE(2026,2,1))+SUMIFS('2024'!$L$10:$L$108,'2024'!$M$10:$M$108,">="&DATE(2026,1,1),'2024'!$M$10:$M$108,"<"&DATE(2026,2,1))+SUMIFS('2024'!$O$10:$O$108,'2024'!$P$10:$P$108,">="&DATE(2026,1,1),'2024'!$P$10:$P$108,"<"&DATE(2026,2,1))+SUMIFS('2024'!$R$10:$R$108,'2024'!$S$10:$S$108,">="&DATE(2026,1,1),'2024'!$S$10:$S$108,"<"&DATE(2026,2,1))+SUMIFS('2024'!$U$10:$U$108,'2024'!$V$10:$V$108,">="&DATE(2026,1,1),'2024'!$V$10:$V$108,"<"&DATE(2026,2,1))+SUMIFS('2023'!$I$10:$I$127,'2023'!$J$10:$J$127,">="&DATE(2026,1,1),'2023'!$J$10:$J$127,"<"&DATE(2026,2,1))+SUMIFS('2023'!$L$10:$L$127,'2023'!$M$10:$M$127,">="&DATE(2026,1,1),'2023'!$M$10:$M$127,"<"&DATE(2026,2,1))+SUMIFS('2023'!$O$10:$O$127,'2023'!$P$10:$P$127,">="&DATE(2026,1,1),'2023'!$P$10:$P$127,"<"&DATE(2026,2,1))+SUMIFS('2023'!$R$10:$R$127,'2023'!$S$10:$S$127,">="&DATE(2026,1,1),'2023'!$S$10:$S$127,"<"&DATE(2026,2,1))+SUMIFS('2023'!$U$10:$U$127,'2023'!$V$10:$V$127,">="&DATE(2026,1,1),'2023'!$V$10:$V$127,"<"&DATE(2026,2,1)),2) | F8: =ROUND(AVERAGE($B8:$D8),0) | G8: =IF(SUM($F$8:$F$19)=0,"",$F8/SUM($F$8:$F$19))
A9: Fevereiro | B9: =ROUND(SUMIFS('2026'!$I$10:$I$107,'2026'!$J$10:$J$107,">="&DATE(2023,2,1),'2026'!$J$10:$J$107,"<"&DATE(2023,3,1))+SUMIFS('2026'!$L$10:$L$107,'2026'!$M$10:$M$107,">="&DATE(2023,2,1),'2026'!$M$10:$M$107,"<"&DATE(2023,3,1))+SUMIFS('2026'!$O$10:$O$107,'2026'!$P$10:$P$107,">="&DATE(2023,2,1),'2026'!$P$10:$P$107,"<"&DATE(2023,3,1))+SUMIFS('2026'!$R$10:$R$107,'2026'!$S$10:$S$107,">="&DATE(2023,2,1),'2026'!$S$10:$S$107,"<"&DATE(2023,3,1))+SUMIFS('2026'!$U$10:$U$107,'2026'!$V$10:$V$107,">="&DATE(2023,2,1),'2026'!$V$10:$V$107,"<"&DATE(2023,3,1))+SUMIFS('2025'!$I$10:$I$112,'2025'!$J$10:$J$112,">="&DATE(2023,2,1),'2025'!$J$10:$J$112,"<"&DATE(2023,3,1))+SUMIFS('2025'!$L$10:$L$112,'2025'!$M$10:$M$112,">="&DATE(2023,2,1),'2025'!$M$10:$M$112,"<"&DATE(2023,3,1))+SUMIFS('2025'!$O$10:$O$112,'2025'!$P$10:$P$112,">="&DATE(2023,2,1),'2025'!$P$10:$P$112,"<"&DATE(2023,3,1))+SUMIFS('2025'!$R$10:$R$112,'2025'!$S$10:$S$112,">="&DATE(2023,2,1),'2025'!$S$10:$S$112,"<"&DATE(2023,3,1))+SUMIFS('2025'!$U$10:$U$112,'2025'!$V$10:$V$112,">="&DATE(2023,2,1),'2025'!$V$10:$V$112,"<"&DATE(2023,3,1))+SUMIFS('2024'!$I$10:$I$108,'2024'!$J$10:$J$108,">="&DATE(2023,2,1),'2024'!$J$10:$J$108,"<"&DATE(2023,3,1))+SUMIFS('2024'!$L$10:$L$108,'2024'!$M$10:$M$108,">="&DATE(2023,2,1),'2024'!$M$10:$M$108,"<"&DATE(2023,3,1))+SUMIFS('2024'!$O$10:$O$108,'2024'!$P$10:$P$108,">="&DATE(2023,2,1),'2024'!$P$10:$P$108,"<"&DATE(2023,3,1))+SUMIFS('2024'!$R$10:$R$108,'2024'!$S$10:$S$108,">="&DATE(2023,2,1),'2024'!$S$10:$S$108,"<"&DATE(2023,3,1))+SUMIFS('2024'!$U$10:$U$108,'2024'!$V$10:$V$108,">="&DATE(2023,2,1),'2024'!$V$10:$V$108,"<"&DATE(2023,3,1))+SUMIFS('2023'!$I$10:$I$127,'2023'!$J$10:$J$127,">="&DATE(2023,2,1),'2023'!$J$10:$J$127,"<"&DATE(2023,3,1))+SUMIFS('2023'!$L$10:$L$127,'2023'!$M$10:$M$127,">="&DATE(2023,2,1),'2023'!$M$10:$M$127,"<"&DATE(2023,3,1))+SUMIFS('2023'!$O$10:$O$127,'2023'!$P$10:$P$127,">="&DATE(2023,2,1),'2023'!$P$10:$P$127,"<"&DATE(2023,3,1))+SUMIFS('2023'!$R$10:$R$127,'2023'!$S$10:$S$127,">="&DATE(2023,2,1),'2023'!$S$10:$S$127,"<"&DATE(2023,3,1))+SUMIFS('2023'!$U$10:$U$127,'2023'!$V$10:$V$127,">="&DATE(2023,2,1),'2023'!$V$10:$V$127,"<"&DATE(2023,3,1)),2) | C9: =ROUND(SUMIFS('2026'!$I$10:$I$107,'2026'!$J$10:$J$107,">="&DATE(2024,2,1),'2026'!$J$10:$J$107,"<"&DATE(2024,3,1))+SUMIFS('2026'!$L$10:$L$107,'2026'!$M$10:$M$107,">="&DATE(2024,2,1),'2026'!$M$10:$M$107,"<"&DATE(2024,3,1))+SUMIFS('2026'!$O$10:$O$107,'2026'!$P$10:$P$107,">="&DATE(2024,2,1),'2026'!$P$10:$P$107,"<"&DATE(2024,3,1))+SUMIFS('2026'!$R$10:$R$107,'2026'!$S$10:$S$107,">="&DATE(2024,2,1),'2026'!$S$10:$S$107,"<"&DATE(2024,3,1))+SUMIFS('2026'!$U$10:$U$107,'2026'!$V$10:$V$107,">="&DATE(2024,2,1),'2026'!$V$10:$V$107,"<"&DATE(2024,3,1))+SUMIFS('2025'!$I$10:$I$112,'2025'!$J$10:$J$112,">="&DATE(2024,2,1),'2025'!$J$10:$J$112,"<"&DATE(2024,3,1))+SUMIFS('2025'!$L$10:$L$112,'2025'!$M$10:$M$112,">="&DATE(2024,2,1),'2025'!$M$10:$M$112,"<"&DATE(2024,3,1))+SUMIFS('2025'!$O$10:$O$112,'2025'!$P$10:$P$112,">="&DATE(2024,2,1),'2025'!$P$10:$P$112,"<"&DATE(2024,3,1))+SUMIFS('2025'!$R$10:$R$112,'2025'!$S$10:$S$112,">="&DATE(2024,2,1),'2025'!$S$10:$S$112,"<"&DATE(2024,3,1))+SUMIFS('2025'!$U$10:$U$112,'2025'!$V$10:$V$112,">="&DATE(2024,2,1),'2025'!$V$10:$V$112,"<"&DATE(2024,3,1))+SUMIFS('2024'!$I$10:$I$108,'2024'!$J$10:$J$108,">="&DATE(2024,2,1),'2024'!$J$10:$J$108,"<"&DATE(2024,3,1))+SUMIFS('2024'!$L$10:$L$108,'2024'!$M$10:$M$108,">="&DATE(2024,2,1),'2024'!$M$10:$M$108,"<"&DATE(2024,3,1))+SUMIFS('2024'!$O$10:$O$108,'2024'!$P$10:$P$108,">="&DATE(2024,2,1),'2024'!$P$10:$P$108,"<"&DATE(2024,3,1))+SUMIFS('2024'!$R$10:$R$108,'2024'!$S$10:$S$108,">="&DATE(2024,2,1),'2024'!$S$10:$S$108,"<"&DATE(2024,3,1))+SUMIFS('2024'!$U$10:$U$108,'2024'!$V$10:$V$108,">="&DATE(2024,2,1),'2024'!$V$10:$V$108,"<"&DATE(2024,3,1))+SUMIFS('2023'!$I$10:$I$127,'2023'!$J$10:$J$127,">="&DATE(2024,2,1),'2023'!$J$10:$J$127,"<"&DATE(2024,3,1))+SUMIFS('2023'!$L$10:$L$127,'2023'!$M$10:$M$127,">="&DATE(2024,2,1),'2023'!$M$10:$M$127,"<"&DATE(2024,3,1))+SUMIFS('2023'!$O$10:$O$127,'2023'!$P$10:$P$127,">="&DATE(2024,2,1),'2023'!$P$10:$P$127,"<"&DATE(2024,3,1))+SUMIFS('2023'!$R$10:$R$127,'2023'!$S$10:$S$127,">="&DATE(2024,2,1),'2023'!$S$10:$S$127,"<"&DATE(2024,3,1))+SUMIFS('2023'!$U$10:$U$127,'2023'!$V$10:$V$127,">="&DATE(2024,2,1),'2023'!$V$10:$V$127,"<"&DATE(2024,3,1)),2) | D9: =ROUND(SUMIFS('2026'!$I$10:$I$107,'2026'!$J$10:$J$107,">="&DATE(2025,2,1),'2026'!$J$10:$J$107,"<"&DATE(2025,3,1))+SUMIFS('2026'!$L$10:$L$107,'2026'!$M$10:$M$107,">="&DATE(2025,2,1),'2026'!$M$10:$M$107,"<"&DATE(2025,3,1))+SUMIFS('2026'!$O$10:$O$107,'2026'!$P$10:$P$107,">="&DATE(2025,2,1),'2026'!$P$10:$P$107,"<"&DATE(2025,3,1))+SUMIFS('2026'!$R$10:$R$107,'2026'!$S$10:$S$107,">="&DATE(2025,2,1),'2026'!$S$10:$S$107,"<"&DATE(2025,3,1))+SUMIFS('2026'!$U$10:$U$107,'2026'!$V$10:$V$107,">="&DATE(2025,2,1),'2026'!$V$10:$V$107,"<"&DATE(2025,3,1))+SUMIFS('2025'!$I$10:$I$112,'2025'!$J$10:$J$112,">="&DATE(2025,2,1),'2025'!$J$10:$J$112,"<"&DATE(2025,3,1))+SUMIFS('2025'!$L$10:$L$112,'2025'!$M$10:$M$112,">="&DATE(2025,2,1),'2025'!$M$10:$M$112,"<"&DATE(2025,3,1))+SUMIFS('2025'!$O$10:$O$112,'2025'!$P$10:$P$112,">="&DATE(2025,2,1),'2025'!$P$10:$P$112,"<"&DATE(2025,3,1))+SUMIFS('2025'!$R$10:$R$112,'2025'!$S$10:$S$112,">="&DATE(2025,2,1),'2025'!$S$10:$S$112,"<"&DATE(2025,3,1))+SUMIFS('2025'!$U$10:$U$112,'2025'!$V$10:$V$112,">="&DATE(2025,2,1),'2025'!$V$10:$V$112,"<"&DATE(2025,3,1))+SUMIFS('2024'!$I$10:$I$108,'2024'!$J$10:$J$108,">="&DATE(2025,2,1),'2024'!$J$10:$J$108,"<"&DATE(2025,3,1))+SUMIFS('2024'!$L$10:$L$108,'2024'!$M$10:$M$108,">="&DATE(2025,2,1),'2024'!$M$10:$M$108,"<"&DATE(2025,3,1))+SUMIFS('2024'!$O$10:$O$108,'2024'!$P$10:$P$108,">="&DATE(2025,2,1),'2024'!$P$10:$P$108,"<"&DATE(2025,3,1))+SUMIFS('2024'!$R$10:$R$108,'2024'!$S$10:$S$108,">="&DATE(2025,2,1),'2024'!$S$10:$S$108,"<"&DATE(2025,3,1))+SUMIFS('2024'!$U$10:$U$108,'2024'!$V$10:$V$108,">="&DATE(2025,2,1),'2024'!$V$10:$V$108,"<"&DATE(2025,3,1))+SUMIFS('2023'!$I$10:$I$127,'2023'!$J$10:$J$127,">="&DATE(2025,2,1),'2023'!$J$10:$J$127,"<"&DATE(2025,3,1))+SUMIFS('2023'!$L$10:$L$127,'2023'!$M$10:$M$127,">="&DATE(2025,2,1),'2023'!$M$10:$M$127,"<"&DATE(2025,3,1))+SUMIFS('2023'!$O$10:$O$127,'2023'!$P$10:$P$127,">="&DATE(2025,2,1),'2023'!$P$10:$P$127,"<"&DATE(2025,3,1))+SUMIFS('2023'!$R$10:$R$127,'2023'!$S$10:$S$127,">="&DATE(2025,2,1),'2023'!$S$10:$S$127,"<"&DATE(2025,3,1))+SUMIFS('2023'!$U$10:$U$127,'2023'!$V$10:$V$127,">="&DATE(2025,2,1),'2023'!$V$10:$V$127,"<"&DATE(2025,3,1)),2) | E9: =ROUND(SUMIFS('2026'!$I$10:$I$107,'2026'!$J$10:$J$107,">="&DATE(2026,2,1),'2026'!$J$10:$J$107,"<"&DATE(2026,3,1))+SUMIFS('2026'!$L$10:$L$107,'2026'!$M$10:$M$107,">="&DATE(2026,2,1),'2026'!$M$10:$M$107,"<"&DATE(2026,3,1))+SUMIFS('2026'!$O$10:$O$107,'2026'!$P$10:$P$107,">="&DATE(2026,2,1),'2026'!$P$10:$P$107,"<"&DATE(2026,3,1))+SUMIFS('2026'!$R$10:$R$107,'2026'!$S$10:$S$107,">="&DATE(2026,2,1),'2026'!$S$10:$S$107,"<"&DATE(2026,3,1))+SUMIFS('2026'!$U$10:$U$107,'2026'!$V$10:$V$107,">="&DATE(2026,2,1),'2026'!$V$10:$V$107,"<"&DATE(2026,3,1))+SUMIFS('2025'!$I$10:$I$112,'2025'!$J$10:$J$112,">="&DATE(2026,2,1),'2025'!$J$10:$J$112,"<"&DATE(2026,3,1))+SUMIFS('2025'!$L$10:$L$112,'2025'!$M$10:$M$112,">="&DATE(2026,2,1),'2025'!$M$10:$M$112,"<"&DATE(2026,3,1))+SUMIFS('2025'!$O$10:$O$112,'2025'!$P$10:$P$112,">="&DATE(2026,2,1),'2025'!$P$10:$P$112,"<"&DATE(2026,3,1))+SUMIFS('2025'!$R$10:$R$112,'2025'!$S$10:$S$112,">="&DATE(2026,2,1),'2025'!$S$10:$S$112,"<"&DATE(2026,3,1))+SUMIFS('2025'!$U$10:$U$112,'2025'!$V$10:$V$112,">="&DATE(2026,2,1),'2025'!$V$10:$V$112,"<"&DATE(2026,3,1))+SUMIFS('2024'!$I$10:$I$108,'2024'!$J$10:$J$108,">="&DATE(2026,2,1),'2024'!$J$10:$J$108,"<"&DATE(2026,3,1))+SUMIFS('2024'!$L$10:$L$108,'2024'!$M$10:$M$108,">="&DATE(2026,2,1),'2024'!$M$10:$M$108,"<"&DATE(2026,3,1))+SUMIFS('2024'!$O$10:$O$108,'2024'!$P$10:$P$108,">="&DATE(2026,2,1),'2024'!$P$10:$P$108,"<"&DATE(2026,3,1))+SUMIFS('2024'!$R$10:$R$108,'2024'!$S$10:$S$108,">="&DATE(2026,2,1),'2024'!$S$10:$S$108,"<"&DATE(2026,3,1))+SUMIFS('2024'!$U$10:$U$108,'2024'!$V$10:$V$108,">="&DATE(2026,2,1),'2024'!$V$10:$V$108,"<"&DATE(2026,3,1))+SUMIFS('2023'!$I$10:$I$127,'2023'!$J$10:$J$127,">="&DATE(2026,2,1),'2023'!$J$10:$J$127,"<"&DATE(2026,3,1))+SUMIFS('2023'!$L$10:$L$127,'2023'!$M$10:$M$127,">="&DATE(2026,2,1),'2023'!$M$10:$M$127,"<"&DATE(2026,3,1))+SUMIFS('2023'!$O$10:$O$127,'2023'!$P$10:$P$127,">="&DATE(2026,2,1),'2023'!$P$10:$P$127,"<"&DATE(2026,3,1))+SUMIFS('2023'!$R$10:$R$127,'2023'!$S$10:$S$127,">="&DATE(2026,2,1),'2023'!$S$10:$S$127,"<"&DATE(2026,3,1))+SUMIFS('2023'!$U$10:$U$127,'2023'!$V$10:$V$127,">="&DATE(2026,2,1),'2023'!$V$10:$V$127,"<"&DATE(2026,3,1)),2) | F9: =ROUND(AVERAGE($B9:$D9),0) | G9: =IF(SUM($F$8:$F$19)=0,"",$F9/SUM($F$8:$F$19))
A10: Março | B10: =ROUND(SUMIFS('2026'!$I$10:$I$107,'2026'!$J$10:$J$107,">="&DATE(2023,3,1),'2026'!$J$10:$J$107,"<"&DATE(2023,4,1))+SUMIFS('2026'!$L$10:$L$107,'2026'!$M$10:$M$107,">="&DATE(2023,3,1),'2026'!$M$10:$M$107,"<"&DATE(2023,4,1))+SUMIFS('2026'!$O$10:$O$107,'2026'!$P$10:$P$107,">="&DATE(2023,3,1),'2026'!$P$10:$P$107,"<"&DATE(2023,4,1))+SUMIFS('2026'!$R$10:$R$107,'2026'!$S$10:$S$107,">="&DATE(2023,3,1),'2026'!$S$10:$S$107,"<"&DATE(2023,4,1))+SUMIFS('2026'!$U$10:$U$107,'2026'!$V$10:$V$107,">="&DATE(2023,3,1),'2026'!$V$10:$V$107,"<"&DATE(2023,4,1))+SUMIFS('2025'!$I$10:$I$112,'2025'!$J$10:$J$112,">="&DATE(2023,3,1),'2025'!$J$10:$J$112,"<"&DATE(2023,4,1))+SUMIFS('2025'!$L$10:$L$112,'2025'!$M$10:$M$112,">="&DATE(2023,3,1),'2025'!$M$10:$M$112,"<"&DATE(2023,4,1))+SUMIFS('2025'!$O$10:$O$112,'2025'!$P$10:$P$112,">="&DATE(2023,3,1),'2025'!$P$10:$P$112,"<"&DATE(2023,4,1))+SUMIFS('2025'!$R$10:$R$112,'2025'!$S$10:$S$112,">="&DATE(2023,3,1),'2025'!$S$10:$S$112,"<"&DATE(2023,4,1))+SUMIFS('2025'!$U$10:$U$112,'2025'!$V$10:$V$112,">="&DATE(2023,3,1),'2025'!$V$10:$V$112,"<"&DATE(2023,4,1))+SUMIFS('2024'!$I$10:$I$108,'2024'!$J$10:$J$108,">="&DATE(2023,3,1),'2024'!$J$10:$J$108,"<"&DATE(2023,4,1))+SUMIFS('2024'!$L$10:$L$108,'2024'!$M$10:$M$108,">="&DATE(2023,3,1),'2024'!$M$10:$M$108,"<"&DATE(2023,4,1))+SUMIFS('2024'!$O$10:$O$108,'2024'!$P$10:$P$108,">="&DATE(2023,3,1),'2024'!$P$10:$P$108,"<"&DATE(2023,4,1))+SUMIFS('2024'!$R$10:$R$108,'2024'!$S$10:$S$108,">="&DATE(2023,3,1),'2024'!$S$10:$S$108,"<"&DATE(2023,4,1))+SUMIFS('2024'!$U$10:$U$108,'2024'!$V$10:$V$108,">="&DATE(2023,3,1),'2024'!$V$10:$V$108,"<"&DATE(2023,4,1))+SUMIFS('2023'!$I$10:$I$127,'2023'!$J$10:$J$127,">="&DATE(2023,3,1),'2023'!$J$10:$J$127,"<"&DATE(2023,4,1))+SUMIFS('2023'!$L$10:$L$127,'2023'!$M$10:$M$127,">="&DATE(2023,3,1),'2023'!$M$10:$M$127,"<"&DATE(2023,4,1))+SUMIFS('2023'!$O$10:$O$127,'2023'!$P$10:$P$127,">="&DATE(2023,3,1),'2023'!$P$10:$P$127,"<"&DATE(2023,4,1))+SUMIFS('2023'!$R$10:$R$127,'2023'!$S$10:$S$127,">="&DATE(2023,3,1),'2023'!$S$10:$S$127,"<"&DATE(2023,4,1))+SUMIFS('2023'!$U$10:$U$127,'2023'!$V$10:$V$127,">="&DATE(2023,3,1),'2023'!$V$10:$V$127,"<"&DATE(2023,4,1)),2) | C10: =ROUND(SUMIFS('2026'!$I$10:$I$107,'2026'!$J$10:$J$107,">="&DATE(2024,3,1),'2026'!$J$10:$J$107,"<"&DATE(2024,4,1))+SUMIFS('2026'!$L$10:$L$107,'2026'!$M$10:$M$107,">="&DATE(2024,3,1),'2026'!$M$10:$M$107,"<"&DATE(2024,4,1))+SUMIFS('2026'!$O$10:$O$107,'2026'!$P$10:$P$107,">="&DATE(2024,3,1),'2026'!$P$10:$P$107,"<"&DATE(2024,4,1))+SUMIFS('2026'!$R$10:$R$107,'2026'!$S$10:$S$107,">="&DATE(2024,3,1),'2026'!$S$10:$S$107,"<"&DATE(2024,4,1))+SUMIFS('2026'!$U$10:$U$107,'2026'!$V$10:$V$107,">="&DATE(2024,3,1),'2026'!$V$10:$V$107,"<"&DATE(2024,4,1))+SUMIFS('2025'!$I$10:$I$112,'2025'!$J$10:$J$112,">="&DATE(2024,3,1),'2025'!$J$10:$J$112,"<"&DATE(2024,4,1))+SUMIFS('2025'!$L$10:$L$112,'2025'!$M$10:$M$112,">="&DATE(2024,3,1),'2025'!$M$10:$M$112,"<"&DATE(2024,4,1))+SUMIFS('2025'!$O$10:$O$112,'2025'!$P$10:$P$112,">="&DATE(2024,3,1),'2025'!$P$10:$P$112,"<"&DATE(2024,4,1))+SUMIFS('2025'!$R$10:$R$112,'2025'!$S$10:$S$112,">="&DATE(2024,3,1),'2025'!$S$10:$S$112,"<"&DATE(2024,4,1))+SUMIFS('2025'!$U$10:$U$112,'2025'!$V$10:$V$112,">="&DATE(2024,3,1),'2025'!$V$10:$V$112,"<"&DATE(2024,4,1))+SUMIFS('2024'!$I$10:$I$108,'2024'!$J$10:$J$108,">="&DATE(2024,3,1),'2024'!$J$10:$J$108,"<"&DATE(2024,4,1))+SUMIFS('2024'!$L$10:$L$108,'2024'!$M$10:$M$108,">="&DATE(2024,3,1),'2024'!$M$10:$M$108,"<"&DATE(2024,4,1))+SUMIFS('2024'!$O$10:$O$108,'2024'!$P$10:$P$108,">="&DATE(2024,3,1),'2024'!$P$10:$P$108,"<"&DATE(2024,4,1))+SUMIFS('2024'!$R$10:$R$108,'2024'!$S$10:$S$108,">="&DATE(2024,3,1),'2024'!$S$10:$S$108,"<"&DATE(2024,4,1))+SUMIFS('2024'!$U$10:$U$108,'2024'!$V$10:$V$108,">="&DATE(2024,3,1),'2024'!$V$10:$V$108,"<"&DATE(2024,4,1))+SUMIFS('2023'!$I$10:$I$127,'2023'!$J$10:$J$127,">="&DATE(2024,3,1),'2023'!$J$10:$J$127,"<"&DATE(2024,4,1))+SUMIFS('2023'!$L$10:$L$127,'2023'!$M$10:$M$127,">="&DATE(2024,3,1),'2023'!$M$10:$M$127,"<"&DATE(2024,4,1))+SUMIFS('2023'!$O$10:$O$127,'2023'!$P$10:$P$127,">="&DATE(2024,3,1),'2023'!$P$10:$P$127,"<"&DATE(2024,4,1))+SUMIFS('2023'!$R$10:$R$127,'2023'!$S$10:$S$127,">="&DATE(2024,3,1),'2023'!$S$10:$S$127,"<"&DATE(2024,4,1))+SUMIFS('2023'!$U$10:$U$127,'2023'!$V$10:$V$127,">="&DATE(2024,3,1),'2023'!$V$10:$V$127,"<"&DATE(2024,4,1)),2) | D10: =ROUND(SUMIFS('2026'!$I$10:$I$107,'2026'!$J$10:$J$107,">="&DATE(2025,3,1),'2026'!$J$10:$J$107,"<"&DATE(2025,4,1))+SUMIFS('2026'!$L$10:$L$107,'2026'!$M$10:$M$107,">="&DATE(2025,3,1),'2026'!$M$10:$M$107,"<"&DATE(2025,4,1))+SUMIFS('2026'!$O$10:$O$107,'2026'!$P$10:$P$107,">="&DATE(2025,3,1),'2026'!$P$10:$P$107,"<"&DATE(2025,4,1))+SUMIFS('2026'!$R$10:$R$107,'2026'!$S$10:$S$107,">="&DATE(2025,3,1),'2026'!$S$10:$S$107,"<"&DATE(2025,4,1))+SUMIFS('2026'!$U$10:$U$107,'2026'!$V$10:$V$107,">="&DATE(2025,3,1),'2026'!$V$10:$V$107,"<"&DATE(2025,4,1))+SUMIFS('2025'!$I$10:$I$112,'2025'!$J$10:$J$112,">="&DATE(2025,3,1),'2025'!$J$10:$J$112,"<"&DATE(2025,4,1))+SUMIFS('2025'!$L$10:$L$112,'2025'!$M$10:$M$112,">="&DATE(2025,3,1),'2025'!$M$10:$M$112,"<"&DATE(2025,4,1))+SUMIFS('2025'!$O$10:$O$112,'2025'!$P$10:$P$112,">="&DATE(2025,3,1),'2025'!$P$10:$P$112,"<"&DATE(2025,4,1))+SUMIFS('2025'!$R$10:$R$112,'2025'!$S$10:$S$112,">="&DATE(2025,3,1),'2025'!$S$10:$S$112,"<"&DATE(2025,4,1))+SUMIFS('2025'!$U$10:$U$112,'2025'!$V$10:$V$112,">="&DATE(2025,3,1),'2025'!$V$10:$V$112,"<"&DATE(2025,4,1))+SUMIFS('2024'!$I$10:$I$108,'2024'!$J$10:$J$108,">="&DATE(2025,3,1),'2024'!$J$10:$J$108,"<"&DATE(2025,4,1))+SUMIFS('2024'!$L$10:$L$108,'2024'!$M$10:$M$108,">="&DATE(2025,3,1),'2024'!$M$10:$M$108,"<"&DATE(2025,4,1))+SUMIFS('2024'!$O$10:$O$108,'2024'!$P$10:$P$108,">="&DATE(2025,3,1),'2024'!$P$10:$P$108,"<"&DATE(2025,4,1))+SUMIFS('2024'!$R$10:$R$108,'2024'!$S$10:$S$108,">="&DATE(2025,3,1),'2024'!$S$10:$S$108,"<"&DATE(2025,4,1))+SUMIFS('2024'!$U$10:$U$108,'2024'!$V$10:$V$108,">="&DATE(2025,3,1),'2024'!$V$10:$V$108,"<"&DATE(2025,4,1))+SUMIFS('2023'!$I$10:$I$127,'2023'!$J$10:$J$127,">="&DATE(2025,3,1),'2023'!$J$10:$J$127,"<"&DATE(2025,4,1))+SUMIFS('2023'!$L$10:$L$127,'2023'!$M$10:$M$127,">="&DATE(2025,3,1),'2023'!$M$10:$M$127,"<"&DATE(2025,4,1))+SUMIFS('2023'!$O$10:$O$127,'2023'!$P$10:$P$127,">="&DATE(2025,3,1),'2023'!$P$10:$P$127,"<"&DATE(2025,4,1))+SUMIFS('2023'!$R$10:$R$127,'2023'!$S$10:$S$127,">="&DATE(2025,3,1),'2023'!$S$10:$S$127,"<"&DATE(2025,4,1))+SUMIFS('2023'!$U$10:$U$127,'2023'!$V$10:$V$127,">="&DATE(2025,3,1),'2023'!$V$10:$V$127,"<"&DATE(2025,4,1)),2) | E10: =ROUND(SUMIFS('2026'!$I$10:$I$107,'2026'!$J$10:$J$107,">="&DATE(2026,3,1),'2026'!$J$10:$J$107,"<"&DATE(2026,4,1))+SUMIFS('2026'!$L$10:$L$107,'2026'!$M$10:$M$107,">="&DATE(2026,3,1),'2026'!$M$10:$M$107,"<"&DATE(2026,4,1))+SUMIFS('2026'!$O$10:$O$107,'2026'!$P$10:$P$107,">="&DATE(2026,3,1),'2026'!$P$10:$P$107,"<"&DATE(2026,4,1))+SUMIFS('2026'!$R$10:$R$107,'2026'!$S$10:$S$107,">="&DATE(2026,3,1),'2026'!$S$10:$S$107,"<"&DATE(2026,4,1))+SUMIFS('2026'!$U$10:$U$107,'2026'!$V$10:$V$107,">="&DATE(2026,3,1),'2026'!$V$10:$V$107,"<"&DATE(2026,4,1))+SUMIFS('2025'!$I$10:$I$112,'2025'!$J$10:$J$112,">="&DATE(2026,3,1),'2025'!$J$10:$J$112,"<"&DATE(2026,4,1))+SUMIFS('2025'!$L$10:$L$112,'2025'!$M$10:$M$112,">="&DATE(2026,3,1),'2025'!$M$10:$M$112,"<"&DATE(2026,4,1))+SUMIFS('2025'!$O$10:$O$112,'2025'!$P$10:$P$112,">="&DATE(2026,3,1),'2025'!$P$10:$P$112,"<"&DATE(2026,4,1))+SUMIFS('2025'!$R$10:$R$112,'2025'!$S$10:$S$112,">="&DATE(2026,3,1),'2025'!$S$10:$S$112,"<"&DATE(2026,4,1))+SUMIFS('2025'!$U$10:$U$112,'2025'!$V$10:$V$112,">="&DATE(2026,3,1),'2025'!$V$10:$V$112,"<"&DATE(2026,4,1))+SUMIFS('2024'!$I$10:$I$108,'2024'!$J$10:$J$108,">="&DATE(2026,3,1),'2024'!$J$10:$J$108,"<"&DATE(2026,4,1))+SUMIFS('2024'!$L$10:$L$108,'2024'!$M$10:$M$108,">="&DATE(2026,3,1),'2024'!$M$10:$M$108,"<"&DATE(2026,4,1))+SUMIFS('2024'!$O$10:$O$108,'2024'!$P$10:$P$108,">="&DATE(2026,3,1),'2024'!$P$10:$P$108,"<"&DATE(2026,4,1))+SUMIFS('2024'!$R$10:$R$108,'2024'!$S$10:$S$108,">="&DATE(2026,3,1),'2024'!$S$10:$S$108,"<"&DATE(2026,4,1))+SUMIFS('2024'!$U$10:$U$108,'2024'!$V$10:$V$108,">="&DATE(2026,3,1),'2024'!$V$10:$V$108,"<"&DATE(2026,4,1))+SUMIFS('2023'!$I$10:$I$127,'2023'!$J$10:$J$127,">="&DATE(2026,3,1),'2023'!$J$10:$J$127,"<"&DATE(2026,4,1))+SUMIFS('2023'!$L$10:$L$127,'2023'!$M$10:$M$127,">="&DATE(2026,3,1),'2023'!$M$10:$M$127,"<"&DATE(2026,4,1))+SUMIFS('2023'!$O$10:$O$127,'2023'!$P$10:$P$127,">="&DATE(2026,3,1),'2023'!$P$10:$P$127,"<"&DATE(2026,4,1))+SUMIFS('2023'!$R$10:$R$127,'2023'!$S$10:$S$127,">="&DATE(2026,3,1),'2023'!$S$10:$S$127,"<"&DATE(2026,4,1))+SUMIFS('2023'!$U$10:$U$127,'2023'!$V$10:$V$127,">="&DATE(2026,3,1),'2023'!$V$10:$V$127,"<"&DATE(2026,4,1)),2) | F10: =ROUND(AVERAGE($B10:$D10),0) | G10: =IF(SUM($F$8:$F$19)=0,"",$F10/SUM($F$8:$F$19))
A11: Abril | B11: =ROUND(SUMIFS('2026'!$I$10:$I$107,'2026'!$J$10:$J$107,">="&DATE(2023,4,1),'2026'!$J$10:$J$107,"<"&DATE(2023,5,1))+SUMIFS('2026'!$L$10:$L$107,'2026'!$M$10:$M$107,">="&DATE(2023,4,1),'2026'!$M$10:$M$107,"<"&DATE(2023,5,1))+SUMIFS('2026'!$O$10:$O$107,'2026'!$P$10:$P$107,">="&DATE(2023,4,1),'2026'!$P$10:$P$107,"<"&DATE(2023,5,1))+SUMIFS('2026'!$R$10:$R$107,'2026'!$S$10:$S$107,">="&DATE(2023,4,1),'2026'!$S$10:$S$107,"<"&DATE(2023,5,1))+SUMIFS('2026'!$U$10:$U$107,'2026'!$V$10:$V$107,">="&DATE(2023,4,1),'2026'!$V$10:$V$107,"<"&DATE(2023,5,1))+SUMIFS('2025'!$I$10:$I$112,'2025'!$J$10:$J$112,">="&DATE(2023,4,1),'2025'!$J$10:$J$112,"<"&DATE(2023,5,1))+SUMIFS('2025'!$L$10:$L$112,'2025'!$M$10:$M$112,">="&DATE(2023,4,1),'2025'!$M$10:$M$112,"<"&DATE(2023,5,1))+SUMIFS('2025'!$O$10:$O$112,'2025'!$P$10:$P$112,">="&DATE(2023,4,1),'2025'!$P$10:$P$112,"<"&DATE(2023,5,1))+SUMIFS('2025'!$R$10:$R$112,'2025'!$S$10:$S$112,">="&DATE(2023,4,1),'2025'!$S$10:$S$112,"<"&DATE(2023,5,1))+SUMIFS('2025'!$U$10:$U$112,'2025'!$V$10:$V$112,">="&DATE(2023,4,1),'2025'!$V$10:$V$112,"<"&DATE(2023,5,1))+SUMIFS('2024'!$I$10:$I$108,'2024'!$J$10:$J$108,">="&DATE(2023,4,1),'2024'!$J$10:$J$108,"<"&DATE(2023,5,1))+SUMIFS('2024'!$L$10:$L$108,'2024'!$M$10:$M$108,">="&DATE(2023,4,1),'2024'!$M$10:$M$108,"<"&DATE(2023,5,1))+SUMIFS('2024'!$O$10:$O$108,'2024'!$P$10:$P$108,">="&DATE(2023,4,1),'2024'!$P$10:$P$108,"<"&DATE(2023,5,1))+SUMIFS('2024'!$R$10:$R$108,'2024'!$S$10:$S$108,">="&DATE(2023,4,1),'2024'!$S$10:$S$108,"<"&DATE(2023,5,1))+SUMIFS('2024'!$U$10:$U$108,'2024'!$V$10:$V$108,">="&DATE(2023,4,1),'2024'!$V$10:$V$108,"<"&DATE(2023,5,1))+SUMIFS('2023'!$I$10:$I$127,'2023'!$J$10:$J$127,">="&DATE(2023,4,1),'2023'!$J$10:$J$127,"<"&DATE(2023,5,1))+SUMIFS('2023'!$L$10:$L$127,'2023'!$M$10:$M$127,">="&DATE(2023,4,1),'2023'!$M$10:$M$127,"<"&DATE(2023,5,1))+SUMIFS('2023'!$O$10:$O$127,'2023'!$P$10:$P$127,">="&DATE(2023,4,1),'2023'!$P$10:$P$127,"<"&DATE(2023,5,1))+SUMIFS('2023'!$R$10:$R$127,'2023'!$S$10:$S$127,">="&DATE(2023,4,1),'2023'!$S$10:$S$127,"<"&DATE(2023,5,1))+SUMIFS('2023'!$U$10:$U$127,'2023'!$V$10:$V$127,">="&DATE(2023,4,1),'2023'!$V$10:$V$127,"<"&DATE(2023,5,1)),2) | C11: =ROUND(SUMIFS('2026'!$I$10:$I$107,'2026'!$J$10:$J$107,">="&DATE(2024,4,1),'2026'!$J$10:$J$107,"<"&DATE(2024,5,1))+SUMIFS('2026'!$L$10:$L$107,'2026'!$M$10:$M$107,">="&DATE(2024,4,1),'2026'!$M$10:$M$107,"<"&DATE(2024,5,1))+SUMIFS('2026'!$O$10:$O$107,'2026'!$P$10:$P$107,">="&DATE(2024,4,1),'2026'!$P$10:$P$107,"<"&DATE(2024,5,1))+SUMIFS('2026'!$R$10:$R$107,'2026'!$S$10:$S$107,">="&DATE(2024,4,1),'2026'!$S$10:$S$107,"<"&DATE(2024,5,1))+SUMIFS('2026'!$U$10:$U$107,'2026'!$V$10:$V$107,">="&DATE(2024,4,1),'2026'!$V$10:$V$107,"<"&DATE(2024,5,1))+SUMIFS('2025'!$I$10:$I$112,'2025'!$J$10:$J$112,">="&DATE(2024,4,1),'2025'!$J$10:$J$112,"<"&DATE(2024,5,1))+SUMIFS('2025'!$L$10:$L$112,'2025'!$M$10:$M$112,">="&DATE(2024,4,1),'2025'!$M$10:$M$112,"<"&DATE(2024,5,1))+SUMIFS('2025'!$O$10:$O$112,'2025'!$P$10:$P$112,">="&DATE(2024,4,1),'2025'!$P$10:$P$112,"<"&DATE(2024,5,1))+SUMIFS('2025'!$R$10:$R$112,'2025'!$S$10:$S$112,">="&DATE(2024,4,1),'2025'!$S$10:$S$112,"<"&DATE(2024,5,1))+SUMIFS('2025'!$U$10:$U$112,'2025'!$V$10:$V$112,">="&DATE(2024,4,1),'2025'!$V$10:$V$112,"<"&DATE(2024,5,1))+SUMIFS('2024'!$I$10:$I$108,'2024'!$J$10:$J$108,">="&DATE(2024,4,1),'2024'!$J$10:$J$108,"<"&DATE(2024,5,1))+SUMIFS('2024'!$L$10:$L$108,'2024'!$M$10:$M$108,">="&DATE(2024,4,1),'2024'!$M$10:$M$108,"<"&DATE(2024,5,1))+SUMIFS('2024'!$O$10:$O$108,'2024'!$P$10:$P$108,">="&DATE(2024,4,1),'2024'!$P$10:$P$108,"<"&DATE(2024,5,1))+SUMIFS('2024'!$R$10:$R$108,'2024'!$S$10:$S$108,">="&DATE(2024,4,1),'2024'!$S$10:$S$108,"<"&DATE(2024,5,1))+SUMIFS('2024'!$U$10:$U$108,'2024'!$V$10:$V$108,">="&DATE(2024,4,1),'2024'!$V$10:$V$108,"<"&DATE(2024,5,1))+SUMIFS('2023'!$I$10:$I$127,'2023'!$J$10:$J$127,">="&DATE(2024,4,1),'2023'!$J$10:$J$127,"<"&DATE(2024,5,1))+SUMIFS('2023'!$L$10:$L$127,'2023'!$M$10:$M$127,">="&DATE(2024,4,1),'2023'!$M$10:$M$127,"<"&DATE(2024,5,1))+SUMIFS('2023'!$O$10:$O$127,'2023'!$P$10:$P$127,">="&DATE(2024,4,1),'2023'!$P$10:$P$127,"<"&DATE(2024,5,1))+SUMIFS('2023'!$R$10:$R$127,'2023'!$S$10:$S$127,">="&DATE(2024,4,1),'2023'!$S$10:$S$127,"<"&DATE(2024,5,1))+SUMIFS('2023'!$U$10:$U$127,'2023'!$V$10:$V$127,">="&DATE(2024,4,1),'2023'!$V$10:$V$127,"<"&DATE(2024,5,1)),2) | D11: =ROUND(SUMIFS('2026'!$I$10:$I$107,'2026'!$J$10:$J$107,">="&DATE(2025,4,1),'2026'!$J$10:$J$107,"<"&DATE(2025,5,1))+SUMIFS('2026'!$L$10:$L$107,'2026'!$M$10:$M$107,">="&DATE(2025,4,1),'2026'!$M$10:$M$107,"<"&DATE(2025,5,1))+SUMIFS('2026'!$O$10:$O$107,'2026'!$P$10:$P$107,">="&DATE(2025,4,1),'2026'!$P$10:$P$107,"<"&DATE(2025,5,1))+SUMIFS('2026'!$R$10:$R$107,'2026'!$S$10:$S$107,">="&DATE(2025,4,1),'2026'!$S$10:$S$107,"<"&DATE(2025,5,1))+SUMIFS('2026'!$U$10:$U$107,'2026'!$V$10:$V$107,">="&DATE(2025,4,1),'2026'!$V$10:$V$107,"<"&DATE(2025,5,1))+SUMIFS('2025'!$I$10:$I$112,'2025'!$J$10:$J$112,">="&DATE(2025,4,1),'2025'!$J$10:$J$112,"<"&DATE(2025,5,1))+SUMIFS('2025'!$L$10:$L$112,'2025'!$M$10:$M$112,">="&DATE(2025,4,1),'2025'!$M$10:$M$112,"<"&DATE(2025,5,1))+SUMIFS('2025'!$O$10:$O$112,'2025'!$P$10:$P$112,">="&DATE(2025,4,1),'2025'!$P$10:$P$112,"<"&DATE(2025,5,1))+SUMIFS('2025'!$R$10:$R$112,'2025'!$S$10:$S$112,">="&DATE(2025,4,1),'2025'!$S$10:$S$112,"<"&DATE(2025,5,1))+SUMIFS('2025'!$U$10:$U$112,'2025'!$V$10:$V$112,">="&DATE(2025,4,1),'2025'!$V$10:$V$112,"<"&DATE(2025,5,1))+SUMIFS('2024'!$I$10:$I$108,'2024'!$J$10:$J$108,">="&DATE(2025,4,1),'2024'!$J$10:$J$108,"<"&DATE(2025,5,1))+SUMIFS('2024'!$L$10:$L$108,'2024'!$M$10:$M$108,">="&DATE(2025,4,1),'2024'!$M$10:$M$108,"<"&DATE(2025,5,1))+SUMIFS('2024'!$O$10:$O$108,'2024'!$P$10:$P$108,">="&DATE(2025,4,1),'2024'!$P$10:$P$108,"<"&DATE(2025,5,1))+SUMIFS('2024'!$R$10:$R$108,'2024'!$S$10:$S$108,">="&DATE(2025,4,1),'2024'!$S$10:$S$108,"<"&DATE(2025,5,1))+SUMIFS('2024'!$U$10:$U$108,'2024'!$V$10:$V$108,">="&DATE(2025,4,1),'2024'!$V$10:$V$108,"<"&DATE(2025,5,1))+SUMIFS('2023'!$I$10:$I$127,'2023'!$J$10:$J$127,">="&DATE(2025,4,1),'2023'!$J$10:$J$127,"<"&DATE(2025,5,1))+SUMIFS('2023'!$L$10:$L$127,'2023'!$M$10:$M$127,">="&DATE(2025,4,1),'2023'!$M$10:$M$127,"<"&DATE(2025,5,1))+SUMIFS('2023'!$O$10:$O$127,'2023'!$P$10:$P$127,">="&DATE(2025,4,1),'2023'!$P$10:$P$127,"<"&DATE(2025,5,1))+SUMIFS('2023'!$R$10:$R$127,'2023'!$S$10:$S$127,">="&DATE(2025,4,1),'2023'!$S$10:$S$127,"<"&DATE(2025,5,1))+SUMIFS('2023'!$U$10:$U$127,'2023'!$V$10:$V$127,">="&DATE(2025,4,1),'2023'!$V$10:$V$127,"<"&DATE(2025,5,1)),2) | E11: =ROUND(SUMIFS('2026'!$I$10:$I$107,'2026'!$J$10:$J$107,">="&DATE(2026,4,1),'2026'!$J$10:$J$107,"<"&DATE(2026,5,1))+SUMIFS('2026'!$L$10:$L$107,'2026'!$M$10:$M$107,">="&DATE(2026,4,1),'2026'!$M$10:$M$107,"<"&DATE(2026,5,1))+SUMIFS('2026'!$O$10:$O$107,'2026'!$P$10:$P$107,">="&DATE(2026,4,1),'2026'!$P$10:$P$107,"<"&DATE(2026,5,1))+SUMIFS('2026'!$R$10:$R$107,'2026'!$S$10:$S$107,">="&DATE(2026,4,1),'2026'!$S$10:$S$107,"<"&DATE(2026,5,1))+SUMIFS('2026'!$U$10:$U$107,'2026'!$V$10:$V$107,">="&DATE(2026,4,1),'2026'!$V$10:$V$107,"<"&DATE(2026,5,1))+SUMIFS('2025'!$I$10:$I$112,'2025'!$J$10:$J$112,">="&DATE(2026,4,1),'2025'!$J$10:$J$112,"<"&DATE(2026,5,1))+SUMIFS('2025'!$L$10:$L$112,'2025'!$M$10:$M$112,">="&DATE(2026,4,1),'2025'!$M$10:$M$112,"<"&DATE(2026,5,1))+SUMIFS('2025'!$O$10:$O$112,'2025'!$P$10:$P$112,">="&DATE(2026,4,1),'2025'!$P$10:$P$112,"<"&DATE(2026,5,1))+SUMIFS('2025'!$R$10:$R$112,'2025'!$S$10:$S$112,">="&DATE(2026,4,1),'2025'!$S$10:$S$112,"<"&DATE(2026,5,1))+SUMIFS('2025'!$U$10:$U$112,'2025'!$V$10:$V$112,">="&DATE(2026,4,1),'2025'!$V$10:$V$112,"<"&DATE(2026,5,1))+SUMIFS('2024'!$I$10:$I$108,'2024'!$J$10:$J$108,">="&DATE(2026,4,1),'2024'!$J$10:$J$108,"<"&DATE(2026,5,1))+SUMIFS('2024'!$L$10:$L$108,'2024'!$M$10:$M$108,">="&DATE(2026,4,1),'2024'!$M$10:$M$108,"<"&DATE(2026,5,1))+SUMIFS('2024'!$O$10:$O$108,'2024'!$P$10:$P$108,">="&DATE(2026,4,1),'2024'!$P$10:$P$108,"<"&DATE(2026,5,1))+SUMIFS('2024'!$R$10:$R$108,'2024'!$S$10:$S$108,">="&DATE(2026,4,1),'2024'!$S$10:$S$108,"<"&DATE(2026,5,1))+SUMIFS('2024'!$U$10:$U$108,'2024'!$V$10:$V$108,">="&DATE(2026,4,1),'2024'!$V$10:$V$108,"<"&DATE(2026,5,1))+SUMIFS('2023'!$I$10:$I$127,'2023'!$J$10:$J$127,">="&DATE(2026,4,1),'2023'!$J$10:$J$127,"<"&DATE(2026,5,1))+SUMIFS('2023'!$L$10:$L$127,'2023'!$M$10:$M$127,">="&DATE(2026,4,1),'2023'!$M$10:$M$127,"<"&DATE(2026,5,1))+SUMIFS('2023'!$O$10:$O$127,'2023'!$P$10:$P$127,">="&DATE(2026,4,1),'2023'!$P$10:$P$127,"<"&DATE(2026,5,1))+SUMIFS('2023'!$R$10:$R$127,'2023'!$S$10:$S$127,">="&DATE(2026,4,1),'2023'!$S$10:$S$127,"<"&DATE(2026,5,1))+SUMIFS('2023'!$U$10:$U$127,'2023'!$V$10:$V$127,">="&DATE(2026,4,1),'2023'!$V$10:$V$127,"<"&DATE(2026,5,1)),2) | F11: =ROUND(AVERAGE($B11:$D11),0) | G11: =IF(SUM($F$8:$F$19)=0,"",$F11/SUM($F$8:$F$19))
A12: Maio | B12: =ROUND(SUMIFS('2026'!$I$10:$I$107,'2026'!$J$10:$J$107,">="&DATE(2023,5,1),'2026'!$J$10:$J$107,"<"&DATE(2023,6,1))+SUMIFS('2026'!$L$10:$L$107,'2026'!$M$10:$M$107,">="&DATE(2023,5,1),'2026'!$M$10:$M$107,"<"&DATE(2023,6,1))+SUMIFS('2026'!$O$10:$O$107,'2026'!$P$10:$P$107,">="&DATE(2023,5,1),'2026'!$P$10:$P$107,"<"&DATE(2023,6,1))+SUMIFS('2026'!$R$10:$R$107,'2026'!$S$10:$S$107,">="&DATE(2023,5,1),'2026'!$S$10:$S$107,"<"&DATE(2023,6,1))+SUMIFS('2026'!$U$10:$U$107,'2026'!$V$10:$V$107,">="&DATE(2023,5,1),'2026'!$V$10:$V$107,"<"&DATE(2023,6,1))+SUMIFS('2025'!$I$10:$I$112,'2025'!$J$10:$J$112,">="&DATE(2023,5,1),'2025'!$J$10:$J$112,"<"&DATE(2023,6,1))+SUMIFS('2025'!$L$10:$L$112,'2025'!$M$10:$M$112,">="&DATE(2023,5,1),'2025'!$M$10:$M$112,"<"&DATE(2023,6,1))+SUMIFS('2025'!$O$10:$O$112,'2025'!$P$10:$P$112,">="&DATE(2023,5,1),'2025'!$P$10:$P$112,"<"&DATE(2023,6,1))+SUMIFS('2025'!$R$10:$R$112,'2025'!$S$10:$S$112,">="&DATE(2023,5,1),'2025'!$S$10:$S$112,"<"&DATE(2023,6,1))+SUMIFS('2025'!$U$10:$U$112,'2025'!$V$10:$V$112,">="&DATE(2023,5,1),'2025'!$V$10:$V$112,"<"&DATE(2023,6,1))+SUMIFS('2024'!$I$10:$I$108,'2024'!$J$10:$J$108,">="&DATE(2023,5,1),'2024'!$J$10:$J$108,"<"&DATE(2023,6,1))+SUMIFS('2024'!$L$10:$L$108,'2024'!$M$10:$M$108,">="&DATE(2023,5,1),'2024'!$M$10:$M$108,"<"&DATE(2023,6,1))+SUMIFS('2024'!$O$10:$O$108,'2024'!$P$10:$P$108,">="&DATE(2023,5,1),'2024'!$P$10:$P$108,"<"&DATE(2023,6,1))+SUMIFS('2024'!$R$10:$R$108,'2024'!$S$10:$S$108,">="&DATE(2023,5,1),'2024'!$S$10:$S$108,"<"&DATE(2023,6,1))+SUMIFS('2024'!$U$10:$U$108,'2024'!$V$10:$V$108,">="&DATE(2023,5,1),'2024'!$V$10:$V$108,"<"&DATE(2023,6,1))+SUMIFS('2023'!$I$10:$I$127,'2023'!$J$10:$J$127,">="&DATE(2023,5,1),'2023'!$J$10:$J$127,"<"&DATE(2023,6,1))+SUMIFS('2023'!$L$10:$L$127,'2023'!$M$10:$M$127,">="&DATE(2023,5,1),'2023'!$M$10:$M$127,"<"&DATE(2023,6,1))+SUMIFS('2023'!$O$10:$O$127,'2023'!$P$10:$P$127,">="&DATE(2023,5,1),'2023'!$P$10:$P$127,"<"&DATE(2023,6,1))+SUMIFS('2023'!$R$10:$R$127,'2023'!$S$10:$S$127,">="&DATE(2023,5,1),'2023'!$S$10:$S$127,"<"&DATE(2023,6,1))+SUMIFS('2023'!$U$10:$U$127,'2023'!$V$10:$V$127,">="&DATE(2023,5,1),'2023'!$V$10:$V$127,"<"&DATE(2023,6,1)),2) | C12: =ROUND(SUMIFS('2026'!$I$10:$I$107,'2026'!$J$10:$J$107,">="&DATE(2024,5,1),'2026'!$J$10:$J$107,"<"&DATE(2024,6,1))+SUMIFS('2026'!$L$10:$L$107,'2026'!$M$10:$M$107,">="&DATE(2024,5,1),'2026'!$M$10:$M$107,"<"&DATE(2024,6,1))+SUMIFS('2026'!$O$10:$O$107,'2026'!$P$10:$P$107,">="&DATE(2024,5,1),'2026'!$P$10:$P$107,"<"&DATE(2024,6,1))+SUMIFS('2026'!$R$10:$R$107,'2026'!$S$10:$S$107,">="&DATE(2024,5,1),'2026'!$S$10:$S$107,"<"&DATE(2024,6,1))+SUMIFS('2026'!$U$10:$U$107,'2026'!$V$10:$V$107,">="&DATE(2024,5,1),'2026'!$V$10:$V$107,"<"&DATE(2024,6,1))+SUMIFS('2025'!$I$10:$I$112,'2025'!$J$10:$J$112,">="&DATE(2024,5,1),'2025'!$J$10:$J$112,"<"&DATE(2024,6,1))+SUMIFS('2025'!$L$10:$L$112,'2025'!$M$10:$M$112,">="&DATE(2024,5,1),'2025'!$M$10:$M$112,"<"&DATE(2024,6,1))+SUMIFS('2025'!$O$10:$O$112,'2025'!$P$10:$P$112,">="&DATE(2024,5,1),'2025'!$P$10:$P$112,"<"&DATE(2024,6,1))+SUMIFS('2025'!$R$10:$R$112,'2025'!$S$10:$S$112,">="&DATE(2024,5,1),'2025'!$S$10:$S$112,"<"&DATE(2024,6,1))+SUMIFS('2025'!$U$10:$U$112,'2025'!$V$10:$V$112,">="&DATE(2024,5,1),'2025'!$V$10:$V$112,"<"&DATE(2024,6,1))+SUMIFS('2024'!$I$10:$I$108,'2024'!$J$10:$J$108,">="&DATE(2024,5,1),'2024'!$J$10:$J$108,"<"&DATE(2024,6,1))+SUMIFS('2024'!$L$10:$L$108,'2024'!$M$10:$M$108,">="&DATE(2024,5,1),'2024'!$M$10:$M$108,"<"&DATE(2024,6,1))+SUMIFS('2024'!$O$10:$O$108,'2024'!$P$10:$P$108,">="&DATE(2024,5,1),'2024'!$P$10:$P$108,"<"&DATE(2024,6,1))+SUMIFS('2024'!$R$10:$R$108,'2024'!$S$10:$S$108,">="&DATE(2024,5,1),'2024'!$S$10:$S$108,"<"&DATE(2024,6,1))+SUMIFS('2024'!$U$10:$U$108,'2024'!$V$10:$V$108,">="&DATE(2024,5,1),'2024'!$V$10:$V$108,"<"&DATE(2024,6,1))+SUMIFS('2023'!$I$10:$I$127,'2023'!$J$10:$J$127,">="&DATE(2024,5,1),'2023'!$J$10:$J$127,"<"&DATE(2024,6,1))+SUMIFS('2023'!$L$10:$L$127,'2023'!$M$10:$M$127,">="&DATE(2024,5,1),'2023'!$M$10:$M$127,"<"&DATE(2024,6,1))+SUMIFS('2023'!$O$10:$O$127,'2023'!$P$10:$P$127,">="&DATE(2024,5,1),'2023'!$P$10:$P$127,"<"&DATE(2024,6,1))+SUMIFS('2023'!$R$10:$R$127,'2023'!$S$10:$S$127,">="&DATE(2024,5,1),'2023'!$S$10:$S$127,"<"&DATE(2024,6,1))+SUMIFS('2023'!$U$10:$U$127,'2023'!$V$10:$V$127,">="&DATE(2024,5,1),'2023'!$V$10:$V$127,"<"&DATE(2024,6,1)),2) | D12: =ROUND(SUMIFS('2026'!$I$10:$I$107,'2026'!$J$10:$J$107,">="&DATE(2025,5,1),'2026'!$J$10:$J$107,"<"&DATE(2025,6,1))+SUMIFS('2026'!$L$10:$L$107,'2026'!$M$10:$M$107,">="&DATE(2025,5,1),'2026'!$M$10:$M$107,"<"&DATE(2025,6,1))+SUMIFS('2026'!$O$10:$O$107,'2026'!$P$10:$P$107,">="&DATE(2025,5,1),'2026'!$P$10:$P$107,"<"&DATE(2025,6,1))+SUMIFS('2026'!$R$10:$R$107,'2026'!$S$10:$S$107,">="&DATE(2025,5,1),'2026'!$S$10:$S$107,"<"&DATE(2025,6,1))+SUMIFS('2026'!$U$10:$U$107,'2026'!$V$10:$V$107,">="&DATE(2025,5,1),'2026'!$V$10:$V$107,"<"&DATE(2025,6,1))+SUMIFS('2025'!$I$10:$I$112,'2025'!$J$10:$J$112,">="&DATE(2025,5,1),'2025'!$J$10:$J$112,"<"&DATE(2025,6,1))+SUMIFS('2025'!$L$10:$L$112,'2025'!$M$10:$M$112,">="&DATE(2025,5,1),'2025'!$M$10:$M$112,"<"&DATE(2025,6,1))+SUMIFS('2025'!$O$10:$O$112,'2025'!$P$10:$P$112,">="&DATE(2025,5,1),'2025'!$P$10:$P$112,"<"&DATE(2025,6,1))+SUMIFS('2025'!$R$10:$R$112,'2025'!$S$10:$S$112,">="&DATE(2025,5,1),'2025'!$S$10:$S$112,"<"&DATE(2025,6,1))+SUMIFS('2025'!$U$10:$U$112,'2025'!$V$10:$V$112,">="&DATE(2025,5,1),'2025'!$V$10:$V$112,"<"&DATE(2025,6,1))+SUMIFS('2024'!$I$10:$I$108,'2024'!$J$10:$J$108,">="&DATE(2025,5,1),'2024'!$J$10:$J$108,"<"&DATE(2025,6,1))+SUMIFS('2024'!$L$10:$L$108,'2024'!$M$10:$M$108,">="&DATE(2025,5,1),'2024'!$M$10:$M$108,"<"&DATE(2025,6,1))+SUMIFS('2024'!$O$10:$O$108,'2024'!$P$10:$P$108,">="&DATE(2025,5,1),'2024'!$P$10:$P$108,"<"&DATE(2025,6,1))+SUMIFS('2024'!$R$10:$R$108,'2024'!$S$10:$S$108,">="&DATE(2025,5,1),'2024'!$S$10:$S$108,"<"&DATE(2025,6,1))+SUMIFS('2024'!$U$10:$U$108,'2024'!$V$10:$V$108,">="&DATE(2025,5,1),'2024'!$V$10:$V$108,"<"&DATE(2025,6,1))+SUMIFS('2023'!$I$10:$I$127,'2023'!$J$10:$J$127,">="&DATE(2025,5,1),'2023'!$J$10:$J$127,"<"&DATE(2025,6,1))+SUMIFS('2023'!$L$10:$L$127,'2023'!$M$10:$M$127,">="&DATE(2025,5,1),'2023'!$M$10:$M$127,"<"&DATE(2025,6,1))+SUMIFS('2023'!$O$10:$O$127,'2023'!$P$10:$P$127,">="&DATE(2025,5,1),'2023'!$P$10:$P$127,"<"&DATE(2025,6,1))+SUMIFS('2023'!$R$10:$R$127,'2023'!$S$10:$S$127,">="&DATE(2025,5,1),'2023'!$S$10:$S$127,"<"&DATE(2025,6,1))+SUMIFS('2023'!$U$10:$U$127,'2023'!$V$10:$V$127,">="&DATE(2025,5,1),'2023'!$V$10:$V$127,"<"&DATE(2025,6,1)),2) | E12: =ROUND(SUMIFS('2026'!$I$10:$I$107,'2026'!$J$10:$J$107,">="&DATE(2026,5,1),'2026'!$J$10:$J$107,"<"&DATE(2026,6,1))+SUMIFS('2026'!$L$10:$L$107,'2026'!$M$10:$M$107,">="&DATE(2026,5,1),'2026'!$M$10:$M$107,"<"&DATE(2026,6,1))+SUMIFS('2026'!$O$10:$O$107,'2026'!$P$10:$P$107,">="&DATE(2026,5,1),'2026'!$P$10:$P$107,"<"&DATE(2026,6,1))+SUMIFS('2026'!$R$10:$R$107,'2026'!$S$10:$S$107,">="&DATE(2026,5,1),'2026'!$S$10:$S$107,"<"&DATE(2026,6,1))+SUMIFS('2026'!$U$10:$U$107,'2026'!$V$10:$V$107,">="&DATE(2026,5,1),'2026'!$V$10:$V$107,"<"&DATE(2026,6,1))+SUMIFS('2025'!$I$10:$I$112,'2025'!$J$10:$J$112,">="&DATE(2026,5,1),'2025'!$J$10:$J$112,"<"&DATE(2026,6,1))+SUMIFS('2025'!$L$10:$L$112,'2025'!$M$10:$M$112,">="&DATE(2026,5,1),'2025'!$M$10:$M$112,"<"&DATE(2026,6,1))+SUMIFS('2025'!$O$10:$O$112,'2025'!$P$10:$P$112,">="&DATE(2026,5,1),'2025'!$P$10:$P$112,"<"&DATE(2026,6,1))+SUMIFS('2025'!$R$10:$R$112,'2025'!$S$10:$S$112,">="&DATE(2026,5,1),'2025'!$S$10:$S$112,"<"&DATE(2026,6,1))+SUMIFS('2025'!$U$10:$U$112,'2025'!$V$10:$V$112,">="&DATE(2026,5,1),'2025'!$V$10:$V$112,"<"&DATE(2026,6,1))+SUMIFS('2024'!$I$10:$I$108,'2024'!$J$10:$J$108,">="&DATE(2026,5,1),'2024'!$J$10:$J$108,"<"&DATE(2026,6,1))+SUMIFS('2024'!$L$10:$L$108,'2024'!$M$10:$M$108,">="&DATE(2026,5,1),'2024'!$M$10:$M$108,"<"&DATE(2026,6,1))+SUMIFS('2024'!$O$10:$O$108,'2024'!$P$10:$P$108,">="&DATE(2026,5,1),'2024'!$P$10:$P$108,"<"&DATE(2026,6,1))+SUMIFS('2024'!$R$10:$R$108,'2024'!$S$10:$S$108,">="&DATE(2026,5,1),'2024'!$S$10:$S$108,"<"&DATE(2026,6,1))+SUMIFS('2024'!$U$10:$U$108,'2024'!$V$10:$V$108,">="&DATE(2026,5,1),'2024'!$V$10:$V$108,"<"&DATE(2026,6,1))+SUMIFS('2023'!$I$10:$I$127,'2023'!$J$10:$J$127,">="&DATE(2026,5,1),'2023'!$J$10:$J$127,"<"&DATE(2026,6,1))+SUMIFS('2023'!$L$10:$L$127,'2023'!$M$10:$M$127,">="&DATE(2026,5,1),'2023'!$M$10:$M$127,"<"&DATE(2026,6,1))+SUMIFS('2023'!$O$10:$O$127,'2023'!$P$10:$P$127,">="&DATE(2026,5,1),'2023'!$P$10:$P$127,"<"&DATE(2026,6,1))+SUMIFS('2023'!$R$10:$R$127,'2023'!$S$10:$S$127,">="&DATE(2026,5,1),'2023'!$S$10:$S$127,"<"&DATE(2026,6,1))+SUMIFS('2023'!$U$10:$U$127,'2023'!$V$10:$V$127,">="&DATE(2026,5,1),'2023'!$V$10:$V$127,"<"&DATE(2026,6,1)),2) | F12: =ROUND(AVERAGE($B12:$D12),0) | G12: =IF(SUM($F$8:$F$19)=0,"",$F12/SUM($F$8:$F$19))
A13: Junho | B13: =ROUND(SUMIFS('2026'!$I$10:$I$107,'2026'!$J$10:$J$107,">="&DATE(2023,6,1),'2026'!$J$10:$J$107,"<"&DATE(2023,7,1))+SUMIFS('2026'!$L$10:$L$107,'2026'!$M$10:$M$107,">="&DATE(2023,6,1),'2026'!$M$10:$M$107,"<"&DATE(2023,7,1))+SUMIFS('2026'!$O$10:$O$107,'2026'!$P$10:$P$107,">="&DATE(2023,6,1),'2026'!$P$10:$P$107,"<"&DATE(2023,7,1))+SUMIFS('2026'!$R$10:$R$107,'2026'!$S$10:$S$107,">="&DATE(2023,6,1),'2026'!$S$10:$S$107,"<"&DATE(2023,7,1))+SUMIFS('2026'!$U$10:$U$107,'2026'!$V$10:$V$107,">="&DATE(2023,6,1),'2026'!$V$10:$V$107,"<"&DATE(2023,7,1))+SUMIFS('2025'!$I$10:$I$112,'2025'!$J$10:$J$112,">="&DATE(2023,6,1),'2025'!$J$10:$J$112,"<"&DATE(2023,7,1))+SUMIFS('2025'!$L$10:$L$112,'2025'!$M$10:$M$112,">="&DATE(2023,6,1),'2025'!$M$10:$M$112,"<"&DATE(2023,7,1))+SUMIFS('2025'!$O$10:$O$112,'2025'!$P$10:$P$112,">="&DATE(2023,6,1),'2025'!$P$10:$P$112,"<"&DATE(2023,7,1))+SUMIFS('2025'!$R$10:$R$112,'2025'!$S$10:$S$112,">="&DATE(2023,6,1),'2025'!$S$10:$S$112,"<"&DATE(2023,7,1))+SUMIFS('2025'!$U$10:$U$112,'2025'!$V$10:$V$112,">="&DATE(2023,6,1),'2025'!$V$10:$V$112,"<"&DATE(2023,7,1))+SUMIFS('2024'!$I$10:$I$108,'2024'!$J$10:$J$108,">="&DATE(2023,6,1),'2024'!$J$10:$J$108,"<"&DATE(2023,7,1))+SUMIFS('2024'!$L$10:$L$108,'2024'!$M$10:$M$108,">="&DATE(2023,6,1),'2024'!$M$10:$M$108,"<"&DATE(2023,7,1))+SUMIFS('2024'!$O$10:$O$108,'2024'!$P$10:$P$108,">="&DATE(2023,6,1),'2024'!$P$10:$P$108,"<"&DATE(2023,7,1))+SUMIFS('2024'!$R$10:$R$108,'2024'!$S$10:$S$108,">="&DATE(2023,6,1),'2024'!$S$10:$S$108,"<"&DATE(2023,7,1))+SUMIFS('2024'!$U$10:$U$108,'2024'!$V$10:$V$108,">="&DATE(2023,6,1),'2024'!$V$10:$V$108,"<"&DATE(2023,7,1))+SUMIFS('2023'!$I$10:$I$127,'2023'!$J$10:$J$127,">="&DATE(2023,6,1),'2023'!$J$10:$J$127,"<"&DATE(2023,7,1))+SUMIFS('2023'!$L$10:$L$127,'2023'!$M$10:$M$127,">="&DATE(2023,6,1),'2023'!$M$10:$M$127,"<"&DATE(2023,7,1))+SUMIFS('2023'!$O$10:$O$127,'2023'!$P$10:$P$127,">="&DATE(2023,6,1),'2023'!$P$10:$P$127,"<"&DATE(2023,7,1))+SUMIFS('2023'!$R$10:$R$127,'2023'!$S$10:$S$127,">="&DATE(2023,6,1),'2023'!$S$10:$S$127,"<"&DATE(2023,7,1))+SUMIFS('2023'!$U$10:$U$127,'2023'!$V$10:$V$127,">="&DATE(2023,6,1),'2023'!$V$10:$V$127,"<"&DATE(2023,7,1)),2) | C13: =ROUND(SUMIFS('2026'!$I$10:$I$107,'2026'!$J$10:$J$107,">="&DATE(2024,6,1),'2026'!$J$10:$J$107,"<"&DATE(2024,7,1))+SUMIFS('2026'!$L$10:$L$107,'2026'!$M$10:$M$107,">="&DATE(2024,6,1),'2026'!$M$10:$M$107,"<"&DATE(2024,7,1))+SUMIFS('2026'!$O$10:$O$107,'2026'!$P$10:$P$107,">="&DATE(2024,6,1),'2026'!$P$10:$P$107,"<"&DATE(2024,7,1))+SUMIFS('2026'!$R$10:$R$107,'2026'!$S$10:$S$107,">="&DATE(2024,6,1),'2026'!$S$10:$S$107,"<"&DATE(2024,7,1))+SUMIFS('2026'!$U$10:$U$107,'2026'!$V$10:$V$107,">="&DATE(2024,6,1),'2026'!$V$10:$V$107,"<"&DATE(2024,7,1))+SUMIFS('2025'!$I$10:$I$112,'2025'!$J$10:$J$112,">="&DATE(2024,6,1),'2025'!$J$10:$J$112,"<"&DATE(2024,7,1))+SUMIFS('2025'!$L$10:$L$112,'2025'!$M$10:$M$112,">="&DATE(2024,6,1),'2025'!$M$10:$M$112,"<"&DATE(2024,7,1))+SUMIFS('2025'!$O$10:$O$112,'2025'!$P$10:$P$112,">="&DATE(2024,6,1),'2025'!$P$10:$P$112,"<"&DATE(2024,7,1))+SUMIFS('2025'!$R$10:$R$112,'2025'!$S$10:$S$112,">="&DATE(2024,6,1),'2025'!$S$10:$S$112,"<"&DATE(2024,7,1))+SUMIFS('2025'!$U$10:$U$112,'2025'!$V$10:$V$112,">="&DATE(2024,6,1),'2025'!$V$10:$V$112,"<"&DATE(2024,7,1))+SUMIFS('2024'!$I$10:$I$108,'2024'!$J$10:$J$108,">="&DATE(2024,6,1),'2024'!$J$10:$J$108,"<"&DATE(2024,7,1))+SUMIFS('2024'!$L$10:$L$108,'2024'!$M$10:$M$108,">="&DATE(2024,6,1),'2024'!$M$10:$M$108,"<"&DATE(2024,7,1))+SUMIFS('2024'!$O$10:$O$108,'2024'!$P$10:$P$108,">="&DATE(2024,6,1),'2024'!$P$10:$P$108,"<"&DATE(2024,7,1))+SUMIFS('2024'!$R$10:$R$108,'2024'!$S$10:$S$108,">="&DATE(2024,6,1),'2024'!$S$10:$S$108,"<"&DATE(2024,7,1))+SUMIFS('2024'!$U$10:$U$108,'2024'!$V$10:$V$108,">="&DATE(2024,6,1),'2024'!$V$10:$V$108,"<"&DATE(2024,7,1))+SUMIFS('2023'!$I$10:$I$127,'2023'!$J$10:$J$127,">="&DATE(2024,6,1),'2023'!$J$10:$J$127,"<"&DATE(2024,7,1))+SUMIFS('2023'!$L$10:$L$127,'2023'!$M$10:$M$127,">="&DATE(2024,6,1),'2023'!$M$10:$M$127,"<"&DATE(2024,7,1))+SUMIFS('2023'!$O$10:$O$127,'2023'!$P$10:$P$127,">="&DATE(2024,6,1),'2023'!$P$10:$P$127,"<"&DATE(2024,7,1))+SUMIFS('2023'!$R$10:$R$127,'2023'!$S$10:$S$127,">="&DATE(2024,6,1),'2023'!$S$10:$S$127,"<"&DATE(2024,7,1))+SUMIFS('2023'!$U$10:$U$127,'2023'!$V$10:$V$127,">="&DATE(2024,6,1),'2023'!$V$10:$V$127,"<"&DATE(2024,7,1)),2) | D13: =ROUND(SUMIFS('2026'!$I$10:$I$107,'2026'!$J$10:$J$107,">="&DATE(2025,6,1),'2026'!$J$10:$J$107,"<"&DATE(2025,7,1))+SUMIFS('2026'!$L$10:$L$107,'2026'!$M$10:$M$107,">="&DATE(2025,6,1),'2026'!$M$10:$M$107,"<"&DATE(2025,7,1))+SUMIFS('2026'!$O$10:$O$107,'2026'!$P$10:$P$107,">="&DATE(2025,6,1),'2026'!$P$10:$P$107,"<"&DATE(2025,7,1))+SUMIFS('2026'!$R$10:$R$107,'2026'!$S$10:$S$107,">="&DATE(2025,6,1),'2026'!$S$10:$S$107,"<"&DATE(2025,7,1))+SUMIFS('2026'!$U$10:$U$107,'2026'!$V$10:$V$107,">="&DATE(2025,6,1),'2026'!$V$10:$V$107,"<"&DATE(2025,7,1))+SUMIFS('2025'!$I$10:$I$112,'2025'!$J$10:$J$112,">="&DATE(2025,6,1),'2025'!$J$10:$J$112,"<"&DATE(2025,7,1))+SUMIFS('2025'!$L$10:$L$112,'2025'!$M$10:$M$112,">="&DATE(2025,6,1),'2025'!$M$10:$M$112,"<"&DATE(2025,7,1))+SUMIFS('2025'!$O$10:$O$112,'2025'!$P$10:$P$112,">="&DATE(2025,6,1),'2025'!$P$10:$P$112,"<"&DATE(2025,7,1))+SUMIFS('2025'!$R$10:$R$112,'2025'!$S$10:$S$112,">="&DATE(2025,6,1),'2025'!$S$10:$S$112,"<"&DATE(2025,7,1))+SUMIFS('2025'!$U$10:$U$112,'2025'!$V$10:$V$112,">="&DATE(2025,6,1),'2025'!$V$10:$V$112,"<"&DATE(2025,7,1))+SUMIFS('2024'!$I$10:$I$108,'2024'!$J$10:$J$108,">="&DATE(2025,6,1),'2024'!$J$10:$J$108,"<"&DATE(2025,7,1))+SUMIFS('2024'!$L$10:$L$108,'2024'!$M$10:$M$108,">="&DATE(2025,6,1),'2024'!$M$10:$M$108,"<"&DATE(2025,7,1))+SUMIFS('2024'!$O$10:$O$108,'2024'!$P$10:$P$108,">="&DATE(2025,6,1),'2024'!$P$10:$P$108,"<"&DATE(2025,7,1))+SUMIFS('2024'!$R$10:$R$108,'2024'!$S$10:$S$108,">="&DATE(2025,6,1),'2024'!$S$10:$S$108,"<"&DATE(2025,7,1))+SUMIFS('2024'!$U$10:$U$108,'2024'!$V$10:$V$108,">="&DATE(2025,6,1),'2024'!$V$10:$V$108,"<"&DATE(2025,7,1))+SUMIFS('2023'!$I$10:$I$127,'2023'!$J$10:$J$127,">="&DATE(2025,6,1),'2023'!$J$10:$J$127,"<"&DATE(2025,7,1))+SUMIFS('2023'!$L$10:$L$127,'2023'!$M$10:$M$127,">="&DATE(2025,6,1),'2023'!$M$10:$M$127,"<"&DATE(2025,7,1))+SUMIFS('2023'!$O$10:$O$127,'2023'!$P$10:$P$127,">="&DATE(2025,6,1),'2023'!$P$10:$P$127,"<"&DATE(2025,7,1))+SUMIFS('2023'!$R$10:$R$127,'2023'!$S$10:$S$127,">="&DATE(2025,6,1),'2023'!$S$10:$S$127,"<"&DATE(2025,7,1))+SUMIFS('2023'!$U$10:$U$127,'2023'!$V$10:$V$127,">="&DATE(2025,6,1),'2023'!$V$10:$V$127,"<"&DATE(2025,7,1)),2) | E13: =ROUND(SUMIFS('2026'!$I$10:$I$107,'2026'!$J$10:$J$107,">="&DATE(2026,6,1),'2026'!$J$10:$J$107,"<"&DATE(2026,7,1))+SUMIFS('2026'!$L$10:$L$107,'2026'!$M$10:$M$107,">="&DATE(2026,6,1),'2026'!$M$10:$M$107,"<"&DATE(2026,7,1))+SUMIFS('2026'!$O$10:$O$107,'2026'!$P$10:$P$107,">="&DATE(2026,6,1),'2026'!$P$10:$P$107,"<"&DATE(2026,7,1))+SUMIFS('2026'!$R$10:$R$107,'2026'!$S$10:$S$107,">="&DATE(2026,6,1),'2026'!$S$10:$S$107,"<"&DATE(2026,7,1))+SUMIFS('2026'!$U$10:$U$107,'2026'!$V$10:$V$107,">="&DATE(2026,6,1),'2026'!$V$10:$V$107,"<"&DATE(2026,7,1))+SUMIFS('2025'!$I$10:$I$112,'2025'!$J$10:$J$112,">="&DATE(2026,6,1),'2025'!$J$10:$J$112,"<"&DATE(2026,7,1))+SUMIFS('2025'!$L$10:$L$112,'2025'!$M$10:$M$112,">="&DATE(2026,6,1),'2025'!$M$10:$M$112,"<"&DATE(2026,7,1))+SUMIFS('2025'!$O$10:$O$112,'2025'!$P$10:$P$112,">="&DATE(2026,6,1),'2025'!$P$10:$P$112,"<"&DATE(2026,7,1))+SUMIFS('2025'!$R$10:$R$112,'2025'!$S$10:$S$112,">="&DATE(2026,6,1),'2025'!$S$10:$S$112,"<"&DATE(2026,7,1))+SUMIFS('2025'!$U$10:$U$112,'2025'!$V$10:$V$112,">="&DATE(2026,6,1),'2025'!$V$10:$V$112,"<"&DATE(2026,7,1))+SUMIFS('2024'!$I$10:$I$108,'2024'!$J$10:$J$108,">="&DATE(2026,6,1),'2024'!$J$10:$J$108,"<"&DATE(2026,7,1))+SUMIFS('2024'!$L$10:$L$108,'2024'!$M$10:$M$108,">="&DATE(2026,6,1),'2024'!$M$10:$M$108,"<"&DATE(2026,7,1))+SUMIFS('2024'!$O$10:$O$108,'2024'!$P$10:$P$108,">="&DATE(2026,6,1),'2024'!$P$10:$P$108,"<"&DATE(2026,7,1))+SUMIFS('2024'!$R$10:$R$108,'2024'!$S$10:$S$108,">="&DATE(2026,6,1),'2024'!$S$10:$S$108,"<"&DATE(2026,7,1))+SUMIFS('2024'!$U$10:$U$108,'2024'!$V$10:$V$108,">="&DATE(2026,6,1),'2024'!$V$10:$V$108,"<"&DATE(2026,7,1))+SUMIFS('2023'!$I$10:$I$127,'2023'!$J$10:$J$127,">="&DATE(2026,6,1),'2023'!$J$10:$J$127,"<"&DATE(2026,7,1))+SUMIFS('2023'!$L$10:$L$127,'2023'!$M$10:$M$127,">="&DATE(2026,6,1),'2023'!$M$10:$M$127,"<"&DATE(2026,7,1))+SUMIFS('2023'!$O$10:$O$127,'2023'!$P$10:$P$127,">="&DATE(2026,6,1),'2023'!$P$10:$P$127,"<"&DATE(2026,7,1))+SUMIFS('2023'!$R$10:$R$127,'2023'!$S$10:$S$127,">="&DATE(2026,6,1),'2023'!$S$10:$S$127,"<"&DATE(2026,7,1))+SUMIFS('2023'!$U$10:$U$127,'2023'!$V$10:$V$127,">="&DATE(2026,6,1),'2023'!$V$10:$V$127,"<"&DATE(2026,7,1)),2) | F13: =ROUND(AVERAGE($B13:$D13),0) | G13: =IF(SUM($F$8:$F$19)=0,"",$F13/SUM($F$8:$F$19))
A14: Julho | B14: =ROUND(SUMIFS('2026'!$I$10:$I$107,'2026'!$J$10:$J$107,">="&DATE(2023,7,1),'2026'!$J$10:$J$107,"<"&DATE(2023,8,1))+SUMIFS('2026'!$L$10:$L$107,'2026'!$M$10:$M$107,">="&DATE(2023,7,1),'2026'!$M$10:$M$107,"<"&DATE(2023,8,1))+SUMIFS('2026'!$O$10:$O$107,'2026'!$P$10:$P$107,">="&DATE(2023,7,1),'2026'!$P$10:$P$107,"<"&DATE(2023,8,1))+SUMIFS('2026'!$R$10:$R$107,'2026'!$S$10:$S$107,">="&DATE(2023,7,1),'2026'!$S$10:$S$107,"<"&DATE(2023,8,1))+SUMIFS('2026'!$U$10:$U$107,'2026'!$V$10:$V$107,">="&DATE(2023,7,1),'2026'!$V$10:$V$107,"<"&DATE(2023,8,1))+SUMIFS('2025'!$I$10:$I$112,'2025'!$J$10:$J$112,">="&DATE(2023,7,1),'2025'!$J$10:$J$112,"<"&DATE(2023,8,1))+SUMIFS('2025'!$L$10:$L$112,'2025'!$M$10:$M$112,">="&DATE(2023,7,1),'2025'!$M$10:$M$112,"<"&DATE(2023,8,1))+SUMIFS('2025'!$O$10:$O$112,'2025'!$P$10:$P$112,">="&DATE(2023,7,1),'2025'!$P$10:$P$112,"<"&DATE(2023,8,1))+SUMIFS('2025'!$R$10:$R$112,'2025'!$S$10:$S$112,">="&DATE(2023,7,1),'2025'!$S$10:$S$112,"<"&DATE(2023,8,1))+SUMIFS('2025'!$U$10:$U$112,'2025'!$V$10:$V$112,">="&DATE(2023,7,1),'2025'!$V$10:$V$112,"<"&DATE(2023,8,1))+SUMIFS('2024'!$I$10:$I$108,'2024'!$J$10:$J$108,">="&DATE(2023,7,1),'2024'!$J$10:$J$108,"<"&DATE(2023,8,1))+SUMIFS('2024'!$L$10:$L$108,'2024'!$M$10:$M$108,">="&DATE(2023,7,1),'2024'!$M$10:$M$108,"<"&DATE(2023,8,1))+SUMIFS('2024'!$O$10:$O$108,'2024'!$P$10:$P$108,">="&DATE(2023,7,1),'2024'!$P$10:$P$108,"<"&DATE(2023,8,1))+SUMIFS('2024'!$R$10:$R$108,'2024'!$S$10:$S$108,">="&DATE(2023,7,1),'2024'!$S$10:$S$108,"<"&DATE(2023,8,1))+SUMIFS('2024'!$U$10:$U$108,'2024'!$V$10:$V$108,">="&DATE(2023,7,1),'2024'!$V$10:$V$108,"<"&DATE(2023,8,1))+SUMIFS('2023'!$I$10:$I$127,'2023'!$J$10:$J$127,">="&DATE(2023,7,1),'2023'!$J$10:$J$127,"<"&DATE(2023,8,1))+SUMIFS('2023'!$L$10:$L$127,'2023'!$M$10:$M$127,">="&DATE(2023,7,1),'2023'!$M$10:$M$127,"<"&DATE(2023,8,1))+SUMIFS('2023'!$O$10:$O$127,'2023'!$P$10:$P$127,">="&DATE(2023,7,1),'2023'!$P$10:$P$127,"<"&DATE(2023,8,1))+SUMIFS('2023'!$R$10:$R$127,'2023'!$S$10:$S$127,">="&DATE(2023,7,1),'2023'!$S$10:$S$127,"<"&DATE(2023,8,1))+SUMIFS('2023'!$U$10:$U$127,'2023'!$V$10:$V$127,">="&DATE(2023,7,1),'2023'!$V$10:$V$127,"<"&DATE(2023,8,1)),2) | C14: =ROUND(SUMIFS('2026'!$I$10:$I$107,'2026'!$J$10:$J$107,">="&DATE(2024,7,1),'2026'!$J$10:$J$107,"<"&DATE(2024,8,1))+SUMIFS('2026'!$L$10:$L$107,'2026'!$M$10:$M$107,">="&DATE(2024,7,1),'2026'!$M$10:$M$107,"<"&DATE(2024,8,1))+SUMIFS('2026'!$O$10:$O$107,'2026'!$P$10:$P$107,">="&DATE(2024,7,1),'2026'!$P$10:$P$107,"<"&DATE(2024,8,1))+SUMIFS('2026'!$R$10:$R$107,'2026'!$S$10:$S$107,">="&DATE(2024,7,1),'2026'!$S$10:$S$107,"<"&DATE(2024,8,1))+SUMIFS('2026'!$U$10:$U$107,'2026'!$V$10:$V$107,">="&DATE(2024,7,1),'2026'!$V$10:$V$107,"<"&DATE(2024,8,1))+SUMIFS('2025'!$I$10:$I$112,'2025'!$J$10:$J$112,">="&DATE(2024,7,1),'2025'!$J$10:$J$112,"<"&DATE(2024,8,1))+SUMIFS('2025'!$L$10:$L$112,'2025'!$M$10:$M$112,">="&DATE(2024,7,1),'2025'!$M$10:$M$112,"<"&DATE(2024,8,1))+SUMIFS('2025'!$O$10:$O$112,'2025'!$P$10:$P$112,">="&DATE(2024,7,1),'2025'!$P$10:$P$112,"<"&DATE(2024,8,1))+SUMIFS('2025'!$R$10:$R$112,'2025'!$S$10:$S$112,">="&DATE(2024,7,1),'2025'!$S$10:$S$112,"<"&DATE(2024,8,1))+SUMIFS('2025'!$U$10:$U$112,'2025'!$V$10:$V$112,">="&DATE(2024,7,1),'2025'!$V$10:$V$112,"<"&DATE(2024,8,1))+SUMIFS('2024'!$I$10:$I$108,'2024'!$J$10:$J$108,">="&DATE(2024,7,1),'2024'!$J$10:$J$108,"<"&DATE(2024,8,1))+SUMIFS('2024'!$L$10:$L$108,'2024'!$M$10:$M$108,">="&DATE(2024,7,1),'2024'!$M$10:$M$108,"<"&DATE(2024,8,1))+SUMIFS('2024'!$O$10:$O$108,'2024'!$P$10:$P$108,">="&DATE(2024,7,1),'2024'!$P$10:$P$108,"<"&DATE(2024,8,1))+SUMIFS('2024'!$R$10:$R$108,'2024'!$S$10:$S$108,">="&DATE(2024,7,1),'2024'!$S$10:$S$108,"<"&DATE(2024,8,1))+SUMIFS('2024'!$U$10:$U$108,'2024'!$V$10:$V$108,">="&DATE(2024,7,1),'2024'!$V$10:$V$108,"<"&DATE(2024,8,1))+SUMIFS('2023'!$I$10:$I$127,'2023'!$J$10:$J$127,">="&DATE(2024,7,1),'2023'!$J$10:$J$127,"<"&DATE(2024,8,1))+SUMIFS('2023'!$L$10:$L$127,'2023'!$M$10:$M$127,">="&DATE(2024,7,1),'2023'!$M$10:$M$127,"<"&DATE(2024,8,1))+SUMIFS('2023'!$O$10:$O$127,'2023'!$P$10:$P$127,">="&DATE(2024,7,1),'2023'!$P$10:$P$127,"<"&DATE(2024,8,1))+SUMIFS('2023'!$R$10:$R$127,'2023'!$S$10:$S$127,">="&DATE(2024,7,1),'2023'!$S$10:$S$127,"<"&DATE(2024,8,1))+SUMIFS('2023'!$U$10:$U$127,'2023'!$V$10:$V$127,">="&DATE(2024,7,1),'2023'!$V$10:$V$127,"<"&DATE(2024,8,1)),2) | D14: =ROUND(SUMIFS('2026'!$I$10:$I$107,'2026'!$J$10:$J$107,">="&DATE(2025,7,1),'2026'!$J$10:$J$107,"<"&DATE(2025,8,1))+SUMIFS('2026'!$L$10:$L$107,'2026'!$M$10:$M$107,">="&DATE(2025,7,1),'2026'!$M$10:$M$107,"<"&DATE(2025,8,1))+SUMIFS('2026'!$O$10:$O$107,'2026'!$P$10:$P$107,">="&DATE(2025,7,1),'2026'!$P$10:$P$107,"<"&DATE(2025,8,1))+SUMIFS('2026'!$R$10:$R$107,'2026'!$S$10:$S$107,">="&DATE(2025,7,1),'2026'!$S$10:$S$107,"<"&DATE(2025,8,1))+SUMIFS('2026'!$U$10:$U$107,'2026'!$V$10:$V$107,">="&DATE(2025,7,1),'2026'!$V$10:$V$107,"<"&DATE(2025,8,1))+SUMIFS('2025'!$I$10:$I$112,'2025'!$J$10:$J$112,">="&DATE(2025,7,1),'2025'!$J$10:$J$112,"<"&DATE(2025,8,1))+SUMIFS('2025'!$L$10:$L$112,'2025'!$M$10:$M$112,">="&DATE(2025,7,1),'2025'!$M$10:$M$112,"<"&DATE(2025,8,1))+SUMIFS('2025'!$O$10:$O$112,'2025'!$P$10:$P$112,">="&DATE(2025,7,1),'2025'!$P$10:$P$112,"<"&DATE(2025,8,1))+SUMIFS('2025'!$R$10:$R$112,'2025'!$S$10:$S$112,">="&DATE(2025,7,1),'2025'!$S$10:$S$112,"<"&DATE(2025,8,1))+SUMIFS('2025'!$U$10:$U$112,'2025'!$V$10:$V$112,">="&DATE(2025,7,1),'2025'!$V$10:$V$112,"<"&DATE(2025,8,1))+SUMIFS('2024'!$I$10:$I$108,'2024'!$J$10:$J$108,">="&DATE(2025,7,1),'2024'!$J$10:$J$108,"<"&DATE(2025,8,1))+SUMIFS('2024'!$L$10:$L$108,'2024'!$M$10:$M$108,">="&DATE(2025,7,1),'2024'!$M$10:$M$108,"<"&DATE(2025,8,1))+SUMIFS('2024'!$O$10:$O$108,'2024'!$P$10:$P$108,">="&DATE(2025,7,1),'2024'!$P$10:$P$108,"<"&DATE(2025,8,1))+SUMIFS('2024'!$R$10:$R$108,'2024'!$S$10:$S$108,">="&DATE(2025,7,1),'2024'!$S$10:$S$108,"<"&DATE(2025,8,1))+SUMIFS('2024'!$U$10:$U$108,'2024'!$V$10:$V$108,">="&DATE(2025,7,1),'2024'!$V$10:$V$108,"<"&DATE(2025,8,1))+SUMIFS('2023'!$I$10:$I$127,'2023'!$J$10:$J$127,">="&DATE(2025,7,1),'2023'!$J$10:$J$127,"<"&DATE(2025,8,1))+SUMIFS('2023'!$L$10:$L$127,'2023'!$M$10:$M$127,">="&DATE(2025,7,1),'2023'!$M$10:$M$127,"<"&DATE(2025,8,1))+SUMIFS('2023'!$O$10:$O$127,'2023'!$P$10:$P$127,">="&DATE(2025,7,1),'2023'!$P$10:$P$127,"<"&DATE(2025,8,1))+SUMIFS('2023'!$R$10:$R$127,'2023'!$S$10:$S$127,">="&DATE(2025,7,1),'2023'!$S$10:$S$127,"<"&DATE(2025,8,1))+SUMIFS('2023'!$U$10:$U$127,'2023'!$V$10:$V$127,">="&DATE(2025,7,1),'2023'!$V$10:$V$127,"<"&DATE(2025,8,1)),2) | E14: =ROUND(SUMIFS('2026'!$I$10:$I$107,'2026'!$J$10:$J$107,">="&DATE(2026,7,1),'2026'!$J$10:$J$107,"<"&DATE(2026,8,1))+SUMIFS('2026'!$L$10:$L$107,'2026'!$M$10:$M$107,">="&DATE(2026,7,1),'2026'!$M$10:$M$107,"<"&DATE(2026,8,1))+SUMIFS('2026'!$O$10:$O$107,'2026'!$P$10:$P$107,">="&DATE(2026,7,1),'2026'!$P$10:$P$107,"<"&DATE(2026,8,1))+SUMIFS('2026'!$R$10:$R$107,'2026'!$S$10:$S$107,">="&DATE(2026,7,1),'2026'!$S$10:$S$107,"<"&DATE(2026,8,1))+SUMIFS('2026'!$U$10:$U$107,'2026'!$V$10:$V$107,">="&DATE(2026,7,1),'2026'!$V$10:$V$107,"<"&DATE(2026,8,1))+SUMIFS('2025'!$I$10:$I$112,'2025'!$J$10:$J$112,">="&DATE(2026,7,1),'2025'!$J$10:$J$112,"<"&DATE(2026,8,1))+SUMIFS('2025'!$L$10:$L$112,'2025'!$M$10:$M$112,">="&DATE(2026,7,1),'2025'!$M$10:$M$112,"<"&DATE(2026,8,1))+SUMIFS('2025'!$O$10:$O$112,'2025'!$P$10:$P$112,">="&DATE(2026,7,1),'2025'!$P$10:$P$112,"<"&DATE(2026,8,1))+SUMIFS('2025'!$R$10:$R$112,'2025'!$S$10:$S$112,">="&DATE(2026,7,1),'2025'!$S$10:$S$112,"<"&DATE(2026,8,1))+SUMIFS('2025'!$U$10:$U$112,'2025'!$V$10:$V$112,">="&DATE(2026,7,1),'2025'!$V$10:$V$112,"<"&DATE(2026,8,1))+SUMIFS('2024'!$I$10:$I$108,'2024'!$J$10:$J$108,">="&DATE(2026,7,1),'2024'!$J$10:$J$108,"<"&DATE(2026,8,1))+SUMIFS('2024'!$L$10:$L$108,'2024'!$M$10:$M$108,">="&DATE(2026,7,1),'2024'!$M$10:$M$108,"<"&DATE(2026,8,1))+SUMIFS('2024'!$O$10:$O$108,'2024'!$P$10:$P$108,">="&DATE(2026,7,1),'2024'!$P$10:$P$108,"<"&DATE(2026,8,1))+SUMIFS('2024'!$R$10:$R$108,'2024'!$S$10:$S$108,">="&DATE(2026,7,1),'2024'!$S$10:$S$108,"<"&DATE(2026,8,1))+SUMIFS('2024'!$U$10:$U$108,'2024'!$V$10:$V$108,">="&DATE(2026,7,1),'2024'!$V$10:$V$108,"<"&DATE(2026,8,1))+SUMIFS('2023'!$I$10:$I$127,'2023'!$J$10:$J$127,">="&DATE(2026,7,1),'2023'!$J$10:$J$127,"<"&DATE(2026,8,1))+SUMIFS('2023'!$L$10:$L$127,'2023'!$M$10:$M$127,">="&DATE(2026,7,1),'2023'!$M$10:$M$127,"<"&DATE(2026,8,1))+SUMIFS('2023'!$O$10:$O$127,'2023'!$P$10:$P$127,">="&DATE(2026,7,1),'2023'!$P$10:$P$127,"<"&DATE(2026,8,1))+SUMIFS('2023'!$R$10:$R$127,'2023'!$S$10:$S$127,">="&DATE(2026,7,1),'2023'!$S$10:$S$127,"<"&DATE(2026,8,1))+SUMIFS('2023'!$U$10:$U$127,'2023'!$V$10:$V$127,">="&DATE(2026,7,1),'2023'!$V$10:$V$127,"<"&DATE(2026,8,1)),2) | F14: =ROUND(AVERAGE($B14:$D14),0) | G14: =IF(SUM($F$8:$F$19)=0,"",$F14/SUM($F$8:$F$19))
A15: Agosto | B15: =ROUND(SUMIFS('2026'!$I$10:$I$107,'2026'!$J$10:$J$107,">="&DATE(2023,8,1),'2026'!$J$10:$J$107,"<"&DATE(2023,9,1))+SUMIFS('2026'!$L$10:$L$107,'2026'!$M$10:$M$107,">="&DATE(2023,8,1),'2026'!$M$10:$M$107,"<"&DATE(2023,9,1))+SUMIFS('2026'!$O$10:$O$107,'2026'!$P$10:$P$107,">="&DATE(2023,8,1),'2026'!$P$10:$P$107,"<"&DATE(2023,9,1))+SUMIFS('2026'!$R$10:$R$107,'2026'!$S$10:$S$107,">="&DATE(2023,8,1),'2026'!$S$10:$S$107,"<"&DATE(2023,9,1))+SUMIFS('2026'!$U$10:$U$107,'2026'!$V$10:$V$107,">="&DATE(2023,8,1),'2026'!$V$10:$V$107,"<"&DATE(2023,9,1))+SUMIFS('2025'!$I$10:$I$112,'2025'!$J$10:$J$112,">="&DATE(2023,8,1),'2025'!$J$10:$J$112,"<"&DATE(2023,9,1))+SUMIFS('2025'!$L$10:$L$112,'2025'!$M$10:$M$112,">="&DATE(2023,8,1),'2025'!$M$10:$M$112,"<"&DATE(2023,9,1))+SUMIFS('2025'!$O$10:$O$112,'2025'!$P$10:$P$112,">="&DATE(2023,8,1),'2025'!$P$10:$P$112,"<"&DATE(2023,9,1))+SUMIFS('2025'!$R$10:$R$112,'2025'!$S$10:$S$112,">="&DATE(2023,8,1),'2025'!$S$10:$S$112,"<"&DATE(2023,9,1))+SUMIFS('2025'!$U$10:$U$112,'2025'!$V$10:$V$112,">="&DATE(2023,8,1),'2025'!$V$10:$V$112,"<"&DATE(2023,9,1))+SUMIFS('2024'!$I$10:$I$108,'2024'!$J$10:$J$108,">="&DATE(2023,8,1),'2024'!$J$10:$J$108,"<"&DATE(2023,9,1))+SUMIFS('2024'!$L$10:$L$108,'2024'!$M$10:$M$108,">="&DATE(2023,8,1),'2024'!$M$10:$M$108,"<"&DATE(2023,9,1))+SUMIFS('2024'!$O$10:$O$108,'2024'!$P$10:$P$108,">="&DATE(2023,8,1),'2024'!$P$10:$P$108,"<"&DATE(2023,9,1))+SUMIFS('2024'!$R$10:$R$108,'2024'!$S$10:$S$108,">="&DATE(2023,8,1),'2024'!$S$10:$S$108,"<"&DATE(2023,9,1))+SUMIFS('2024'!$U$10:$U$108,'2024'!$V$10:$V$108,">="&DATE(2023,8,1),'2024'!$V$10:$V$108,"<"&DATE(2023,9,1))+SUMIFS('2023'!$I$10:$I$127,'2023'!$J$10:$J$127,">="&DATE(2023,8,1),'2023'!$J$10:$J$127,"<"&DATE(2023,9,1))+SUMIFS('2023'!$L$10:$L$127,'2023'!$M$10:$M$127,">="&DATE(2023,8,1),'2023'!$M$10:$M$127,"<"&DATE(2023,9,1))+SUMIFS('2023'!$O$10:$O$127,'2023'!$P$10:$P$127,">="&DATE(2023,8,1),'2023'!$P$10:$P$127,"<"&DATE(2023,9,1))+SUMIFS('2023'!$R$10:$R$127,'2023'!$S$10:$S$127,">="&DATE(2023,8,1),'2023'!$S$10:$S$127,"<"&DATE(2023,9,1))+SUMIFS('2023'!$U$10:$U$127,'2023'!$V$10:$V$127,">="&DATE(2023,8,1),'2023'!$V$10:$V$127,"<"&DATE(2023,9,1)),2) | C15: =ROUND(SUMIFS('2026'!$I$10:$I$107,'2026'!$J$10:$J$107,">="&DATE(2024,8,1),'2026'!$J$10:$J$107,"<"&DATE(2024,9,1))+SUMIFS('2026'!$L$10:$L$107,'2026'!$M$10:$M$107,">="&DATE(2024,8,1),'2026'!$M$10:$M$107,"<"&DATE(2024,9,1))+SUMIFS('2026'!$O$10:$O$107,'2026'!$P$10:$P$107,">="&DATE(2024,8,1),'2026'!$P$10:$P$107,"<"&DATE(2024,9,1))+SUMIFS('2026'!$R$10:$R$107,'2026'!$S$10:$S$107,">="&DATE(2024,8,1),'2026'!$S$10:$S$107,"<"&DATE(2024,9,1))+SUMIFS('2026'!$U$10:$U$107,'2026'!$V$10:$V$107,">="&DATE(2024,8,1),'2026'!$V$10:$V$107,"<"&DATE(2024,9,1))+SUMIFS('2025'!$I$10:$I$112,'2025'!$J$10:$J$112,">="&DATE(2024,8,1),'2025'!$J$10:$J$112,"<"&DATE(2024,9,1))+SUMIFS('2025'!$L$10:$L$112,'2025'!$M$10:$M$112,">="&DATE(2024,8,1),'2025'!$M$10:$M$112,"<"&DATE(2024,9,1))+SUMIFS('2025'!$O$10:$O$112,'2025'!$P$10:$P$112,">="&DATE(2024,8,1),'2025'!$P$10:$P$112,"<"&DATE(2024,9,1))+SUMIFS('2025'!$R$10:$R$112,'2025'!$S$10:$S$112,">="&DATE(2024,8,1),'2025'!$S$10:$S$112,"<"&DATE(2024,9,1))+SUMIFS('2025'!$U$10:$U$112,'2025'!$V$10:$V$112,">="&DATE(2024,8,1),'2025'!$V$10:$V$112,"<"&DATE(2024,9,1))+SUMIFS('2024'!$I$10:$I$108,'2024'!$J$10:$J$108,">="&DATE(2024,8,1),'2024'!$J$10:$J$108,"<"&DATE(2024,9,1))+SUMIFS('2024'!$L$10:$L$108,'2024'!$M$10:$M$108,">="&DATE(2024,8,1),'2024'!$M$10:$M$108,"<"&DATE(2024,9,1))+SUMIFS('2024'!$O$10:$O$108,'2024'!$P$10:$P$108,">="&DATE(2024,8,1),'2024'!$P$10:$P$108,"<"&DATE(2024,9,1))+SUMIFS('2024'!$R$10:$R$108,'2024'!$S$10:$S$108,">="&DATE(2024,8,1),'2024'!$S$10:$S$108,"<"&DATE(2024,9,1))+SUMIFS('2024'!$U$10:$U$108,'2024'!$V$10:$V$108,">="&DATE(2024,8,1),'2024'!$V$10:$V$108,"<"&DATE(2024,9,1))+SUMIFS('2023'!$I$10:$I$127,'2023'!$J$10:$J$127,">="&DATE(2024,8,1),'2023'!$J$10:$J$127,"<"&DATE(2024,9,1))+SUMIFS('2023'!$L$10:$L$127,'2023'!$M$10:$M$127,">="&DATE(2024,8,1),'2023'!$M$10:$M$127,"<"&DATE(2024,9,1))+SUMIFS('2023'!$O$10:$O$127,'2023'!$P$10:$P$127,">="&DATE(2024,8,1),'2023'!$P$10:$P$127,"<"&DATE(2024,9,1))+SUMIFS('2023'!$R$10:$R$127,'2023'!$S$10:$S$127,">="&DATE(2024,8,1),'2023'!$S$10:$S$127,"<"&DATE(2024,9,1))+SUMIFS('2023'!$U$10:$U$127,'2023'!$V$10:$V$127,">="&DATE(2024,8,1),'2023'!$V$10:$V$127,"<"&DATE(2024,9,1)),2) | D15: =ROUND(SUMIFS('2026'!$I$10:$I$107,'2026'!$J$10:$J$107,">="&DATE(2025,8,1),'2026'!$J$10:$J$107,"<"&DATE(2025,9,1))+SUMIFS('2026'!$L$10:$L$107,'2026'!$M$10:$M$107,">="&DATE(2025,8,1),'2026'!$M$10:$M$107,"<"&DATE(2025,9,1))+SUMIFS('2026'!$O$10:$O$107,'2026'!$P$10:$P$107,">="&DATE(2025,8,1),'2026'!$P$10:$P$107,"<"&DATE(2025,9,1))+SUMIFS('2026'!$R$10:$R$107,'2026'!$S$10:$S$107,">="&DATE(2025,8,1),'2026'!$S$10:$S$107,"<"&DATE(2025,9,1))+SUMIFS('2026'!$U$10:$U$107,'2026'!$V$10:$V$107,">="&DATE(2025,8,1),'2026'!$V$10:$V$107,"<"&DATE(2025,9,1))+SUMIFS('2025'!$I$10:$I$112,'2025'!$J$10:$J$112,">="&DATE(2025,8,1),'2025'!$J$10:$J$112,"<"&DATE(2025,9,1))+SUMIFS('2025'!$L$10:$L$112,'2025'!$M$10:$M$112,">="&DATE(2025,8,1),'2025'!$M$10:$M$112,"<"&DATE(2025,9,1))+SUMIFS('2025'!$O$10:$O$112,'2025'!$P$10:$P$112,">="&DATE(2025,8,1),'2025'!$P$10:$P$112,"<"&DATE(2025,9,1))+SUMIFS('2025'!$R$10:$R$112,'2025'!$S$10:$S$112,">="&DATE(2025,8,1),'2025'!$S$10:$S$112,"<"&DATE(2025,9,1))+SUMIFS('2025'!$U$10:$U$112,'2025'!$V$10:$V$112,">="&DATE(2025,8,1),'2025'!$V$10:$V$112,"<"&DATE(2025,9,1))+SUMIFS('2024'!$I$10:$I$108,'2024'!$J$10:$J$108,">="&DATE(2025,8,1),'2024'!$J$10:$J$108,"<"&DATE(2025,9,1))+SUMIFS('2024'!$L$10:$L$108,'2024'!$M$10:$M$108,">="&DATE(2025,8,1),'2024'!$M$10:$M$108,"<"&DATE(2025,9,1))+SUMIFS('2024'!$O$10:$O$108,'2024'!$P$10:$P$108,">="&DATE(2025,8,1),'2024'!$P$10:$P$108,"<"&DATE(2025,9,1))+SUMIFS('2024'!$R$10:$R$108,'2024'!$S$10:$S$108,">="&DATE(2025,8,1),'2024'!$S$10:$S$108,"<"&DATE(2025,9,1))+SUMIFS('2024'!$U$10:$U$108,'2024'!$V$10:$V$108,">="&DATE(2025,8,1),'2024'!$V$10:$V$108,"<"&DATE(2025,9,1))+SUMIFS('2023'!$I$10:$I$127,'2023'!$J$10:$J$127,">="&DATE(2025,8,1),'2023'!$J$10:$J$127,"<"&DATE(2025,9,1))+SUMIFS('2023'!$L$10:$L$127,'2023'!$M$10:$M$127,">="&DATE(2025,8,1),'2023'!$M$10:$M$127,"<"&DATE(2025,9,1))+SUMIFS('2023'!$O$10:$O$127,'2023'!$P$10:$P$127,">="&DATE(2025,8,1),'2023'!$P$10:$P$127,"<"&DATE(2025,9,1))+SUMIFS('2023'!$R$10:$R$127,'2023'!$S$10:$S$127,">="&DATE(2025,8,1),'2023'!$S$10:$S$127,"<"&DATE(2025,9,1))+SUMIFS('2023'!$U$10:$U$127,'2023'!$V$10:$V$127,">="&DATE(2025,8,1),'2023'!$V$10:$V$127,"<"&DATE(2025,9,1)),2) | E15: =ROUND(SUMIFS('2026'!$I$10:$I$107,'2026'!$J$10:$J$107,">="&DATE(2026,8,1),'2026'!$J$10:$J$107,"<"&DATE(2026,9,1))+SUMIFS('2026'!$L$10:$L$107,'2026'!$M$10:$M$107,">="&DATE(2026,8,1),'2026'!$M$10:$M$107,"<"&DATE(2026,9,1))+SUMIFS('2026'!$O$10:$O$107,'2026'!$P$10:$P$107,">="&DATE(2026,8,1),'2026'!$P$10:$P$107,"<"&DATE(2026,9,1))+SUMIFS('2026'!$R$10:$R$107,'2026'!$S$10:$S$107,">="&DATE(2026,8,1),'2026'!$S$10:$S$107,"<"&DATE(2026,9,1))+SUMIFS('2026'!$U$10:$U$107,'2026'!$V$10:$V$107,">="&DATE(2026,8,1),'2026'!$V$10:$V$107,"<"&DATE(2026,9,1))+SUMIFS('2025'!$I$10:$I$112,'2025'!$J$10:$J$112,">="&DATE(2026,8,1),'2025'!$J$10:$J$112,"<"&DATE(2026,9,1))+SUMIFS('2025'!$L$10:$L$112,'2025'!$M$10:$M$112,">="&DATE(2026,8,1),'2025'!$M$10:$M$112,"<"&DATE(2026,9,1))+SUMIFS('2025'!$O$10:$O$112,'2025'!$P$10:$P$112,">="&DATE(2026,8,1),'2025'!$P$10:$P$112,"<"&DATE(2026,9,1))+SUMIFS('2025'!$R$10:$R$112,'2025'!$S$10:$S$112,">="&DATE(2026,8,1),'2025'!$S$10:$S$112,"<"&DATE(2026,9,1))+SUMIFS('2025'!$U$10:$U$112,'2025'!$V$10:$V$112,">="&DATE(2026,8,1),'2025'!$V$10:$V$112,"<"&DATE(2026,9,1))+SUMIFS('2024'!$I$10:$I$108,'2024'!$J$10:$J$108,">="&DATE(2026,8,1),'2024'!$J$10:$J$108,"<"&DATE(2026,9,1))+SUMIFS('2024'!$L$10:$L$108,'2024'!$M$10:$M$108,">="&DATE(2026,8,1),'2024'!$M$10:$M$108,"<"&DATE(2026,9,1))+SUMIFS('2024'!$O$10:$O$108,'2024'!$P$10:$P$108,">="&DATE(2026,8,1),'2024'!$P$10:$P$108,"<"&DATE(2026,9,1))+SUMIFS('2024'!$R$10:$R$108,'2024'!$S$10:$S$108,">="&DATE(2026,8,1),'2024'!$S$10:$S$108,"<"&DATE(2026,9,1))+SUMIFS('2024'!$U$10:$U$108,'2024'!$V$10:$V$108,">="&DATE(2026,8,1),'2024'!$V$10:$V$108,"<"&DATE(2026,9,1))+SUMIFS('2023'!$I$10:$I$127,'2023'!$J$10:$J$127,">="&DATE(2026,8,1),'2023'!$J$10:$J$127,"<"&DATE(2026,9,1))+SUMIFS('2023'!$L$10:$L$127,'2023'!$M$10:$M$127,">="&DATE(2026,8,1),'2023'!$M$10:$M$127,"<"&DATE(2026,9,1))+SUMIFS('2023'!$O$10:$O$127,'2023'!$P$10:$P$127,">="&DATE(2026,8,1),'2023'!$P$10:$P$127,"<"&DATE(2026,9,1))+SUMIFS('2023'!$R$10:$R$127,'2023'!$S$10:$S$127,">="&DATE(2026,8,1),'2023'!$S$10:$S$127,"<"&DATE(2026,9,1))+SUMIFS('2023'!$U$10:$U$127,'2023'!$V$10:$V$127,">="&DATE(2026,8,1),'2023'!$V$10:$V$127,"<"&DATE(2026,9,1)),2) | F15: =ROUND(AVERAGE($B15:$D15),0) | G15: =IF(SUM($F$8:$F$19)=0,"",$F15/SUM($F$8:$F$19))
A16: Setembro | B16: =ROUND(SUMIFS('2026'!$I$10:$I$107,'2026'!$J$10:$J$107,">="&DATE(2023,9,1),'2026'!$J$10:$J$107,"<"&DATE(2023,10,1))+SUMIFS('2026'!$L$10:$L$107,'2026'!$M$10:$M$107,">="&DATE(2023,9,1),'2026'!$M$10:$M$107,"<"&DATE(2023,10,1))+SUMIFS('2026'!$O$10:$O$107,'2026'!$P$10:$P$107,">="&DATE(2023,9,1),'2026'!$P$10:$P$107,"<"&DATE(2023,10,1))+SUMIFS('2026'!$R$10:$R$107,'2026'!$S$10:$S$107,">="&DATE(2023,9,1),'2026'!$S$10:$S$107,"<"&DATE(2023,10,1))+SUMIFS('2026'!$U$10:$U$107,'2026'!$V$10:$V$107,">="&DATE(2023,9,1),'2026'!$V$10:$V$107,"<"&DATE(2023,10,1))+SUMIFS('2025'!$I$10:$I$112,'2025'!$J$10:$J$112,">="&DATE(2023,9,1),'2025'!$J$10:$J$112,"<"&DATE(2023,10,1))+SUMIFS('2025'!$L$10:$L$112,'2025'!$M$10:$M$112,">="&DATE(2023,9,1),'2025'!$M$10:$M$112,"<"&DATE(2023,10,1))+SUMIFS('2025'!$O$10:$O$112,'2025'!$P$10:$P$112,">="&DATE(2023,9,1),'2025'!$P$10:$P$112,"<"&DATE(2023,10,1))+SUMIFS('2025'!$R$10:$R$112,'2025'!$S$10:$S$112,">="&DATE(2023,9,1),'2025'!$S$10:$S$112,"<"&DATE(2023,10,1))+SUMIFS('2025'!$U$10:$U$112,'2025'!$V$10:$V$112,">="&DATE(2023,9,1),'2025'!$V$10:$V$112,"<"&DATE(2023,10,1))+SUMIFS('2024'!$I$10:$I$108,'2024'!$J$10:$J$108,">="&DATE(2023,9,1),'2024'!$J$10:$J$108,"<"&DATE(2023,10,1))+SUMIFS('2024'!$L$10:$L$108,'2024'!$M$10:$M$108,">="&DATE(2023,9,1),'2024'!$M$10:$M$108,"<"&DATE(2023,10,1))+SUMIFS('2024'!$O$10:$O$108,'2024'!$P$10:$P$108,">="&DATE(2023,9,1),'2024'!$P$10:$P$108,"<"&DATE(2023,10,1))+SUMIFS('2024'!$R$10:$R$108,'2024'!$S$10:$S$108,">="&DATE(2023,9,1),'2024'!$S$10:$S$108,"<"&DATE(2023,10,1))+SUMIFS('2024'!$U$10:$U$108,'2024'!$V$10:$V$108,">="&DATE(2023,9,1),'2024'!$V$10:$V$108,"<"&DATE(2023,10,1))+SUMIFS('2023'!$I$10:$I$127,'2023'!$J$10:$J$127,">="&DATE(2023,9,1),'2023'!$J$10:$J$127,"<"&DATE(2023,10,1))+SUMIFS('2023'!$L$10:$L$127,'2023'!$M$10:$M$127,">="&DATE(2023,9,1),'2023'!$M$10:$M$127,"<"&DATE(2023,10,1))+SUMIFS('2023'!$O$10:$O$127,'2023'!$P$10:$P$127,">="&DATE(2023,9,1),'2023'!$P$10:$P$127,"<"&DATE(2023,10,1))+SUMIFS('2023'!$R$10:$R$127,'2023'!$S$10:$S$127,">="&DATE(2023,9,1),'2023'!$S$10:$S$127,"<"&DATE(2023,10,1))+SUMIFS('2023'!$U$10:$U$127,'2023'!$V$10:$V$127,">="&DATE(2023,9,1),'2023'!$V$10:$V$127,"<"&DATE(2023,10,1)),2) | C16: =ROUND(SUMIFS('2026'!$I$10:$I$107,'2026'!$J$10:$J$107,">="&DATE(2024,9,1),'2026'!$J$10:$J$107,"<"&DATE(2024,10,1))+SUMIFS('2026'!$L$10:$L$107,'2026'!$M$10:$M$107,">="&DATE(2024,9,1),'2026'!$M$10:$M$107,"<"&DATE(2024,10,1))+SUMIFS('2026'!$O$10:$O$107,'2026'!$P$10:$P$107,">="&DATE(2024,9,1),'2026'!$P$10:$P$107,"<"&DATE(2024,10,1))+SUMIFS('2026'!$R$10:$R$107,'2026'!$S$10:$S$107,">="&DATE(2024,9,1),'2026'!$S$10:$S$107,"<"&DATE(2024,10,1))+SUMIFS('2026'!$U$10:$U$107,'2026'!$V$10:$V$107,">="&DATE(2024,9,1),'2026'!$V$10:$V$107,"<"&DATE(2024,10,1))+SUMIFS('2025'!$I$10:$I$112,'2025'!$J$10:$J$112,">="&DATE(2024,9,1),'2025'!$J$10:$J$112,"<"&DATE(2024,10,1))+SUMIFS('2025'!$L$10:$L$112,'2025'!$M$10:$M$112,">="&DATE(2024,9,1),'2025'!$M$10:$M$112,"<"&DATE(2024,10,1))+SUMIFS('2025'!$O$10:$O$112,'2025'!$P$10:$P$112,">="&DATE(2024,9,1),'2025'!$P$10:$P$112,"<"&DATE(2024,10,1))+SUMIFS('2025'!$R$10:$R$112,'2025'!$S$10:$S$112,">="&DATE(2024,9,1),'2025'!$S$10:$S$112,"<"&DATE(2024,10,1))+SUMIFS('2025'!$U$10:$U$112,'2025'!$V$10:$V$112,">="&DATE(2024,9,1),'2025'!$V$10:$V$112,"<"&DATE(2024,10,1))+SUMIFS('2024'!$I$10:$I$108,'2024'!$J$10:$J$108,">="&DATE(2024,9,1),'2024'!$J$10:$J$108,"<"&DATE(2024,10,1))+SUMIFS('2024'!$L$10:$L$108,'2024'!$M$10:$M$108,">="&DATE(2024,9,1),'2024'!$M$10:$M$108,"<"&DATE(2024,10,1))+SUMIFS('2024'!$O$10:$O$108,'2024'!$P$10:$P$108,">="&DATE(2024,9,1),'2024'!$P$10:$P$108,"<"&DATE(2024,10,1))+SUMIFS('2024'!$R$10:$R$108,'2024'!$S$10:$S$108,">="&DATE(2024,9,1),'2024'!$S$10:$S$108,"<"&DATE(2024,10,1))+SUMIFS('2024'!$U$10:$U$108,'2024'!$V$10:$V$108,">="&DATE(2024,9,1),'2024'!$V$10:$V$108,"<"&DATE(2024,10,1))+SUMIFS('2023'!$I$10:$I$127,'2023'!$J$10:$J$127,">="&DATE(2024,9,1),'2023'!$J$10:$J$127,"<"&DATE(2024,10,1))+SUMIFS('2023'!$L$10:$L$127,'2023'!$M$10:$M$127,">="&DATE(2024,9,1),'2023'!$M$10:$M$127,"<"&DATE(2024,10,1))+SUMIFS('2023'!$O$10:$O$127,'2023'!$P$10:$P$127,">="&DATE(2024,9,1),'2023'!$P$10:$P$127,"<"&DATE(2024,10,1))+SUMIFS('2023'!$R$10:$R$127,'2023'!$S$10:$S$127,">="&DATE(2024,9,1),'2023'!$S$10:$S$127,"<"&DATE(2024,10,1))+SUMIFS('2023'!$U$10:$U$127,'2023'!$V$10:$V$127,">="&DATE(2024,9,1),'2023'!$V$10:$V$127,"<"&DATE(2024,10,1)),2) | D16: =ROUND(SUMIFS('2026'!$I$10:$I$107,'2026'!$J$10:$J$107,">="&DATE(2025,9,1),'2026'!$J$10:$J$107,"<"&DATE(2025,10,1))+SUMIFS('2026'!$L$10:$L$107,'2026'!$M$10:$M$107,">="&DATE(2025,9,1),'2026'!$M$10:$M$107,"<"&DATE(2025,10,1))+SUMIFS('2026'!$O$10:$O$107,'2026'!$P$10:$P$107,">="&DATE(2025,9,1),'2026'!$P$10:$P$107,"<"&DATE(2025,10,1))+SUMIFS('2026'!$R$10:$R$107,'2026'!$S$10:$S$107,">="&DATE(2025,9,1),'2026'!$S$10:$S$107,"<"&DATE(2025,10,1))+SUMIFS('2026'!$U$10:$U$107,'2026'!$V$10:$V$107,">="&DATE(2025,9,1),'2026'!$V$10:$V$107,"<"&DATE(2025,10,1))+SUMIFS('2025'!$I$10:$I$112,'2025'!$J$10:$J$112,">="&DATE(2025,9,1),'2025'!$J$10:$J$112,"<"&DATE(2025,10,1))+SUMIFS('2025'!$L$10:$L$112,'2025'!$M$10:$M$112,">="&DATE(2025,9,1),'2025'!$M$10:$M$112,"<"&DATE(2025,10,1))+SUMIFS('2025'!$O$10:$O$112,'2025'!$P$10:$P$112,">="&DATE(2025,9,1),'2025'!$P$10:$P$112,"<"&DATE(2025,10,1))+SUMIFS('2025'!$R$10:$R$112,'2025'!$S$10:$S$112,">="&DATE(2025,9,1),'2025'!$S$10:$S$112,"<"&DATE(2025,10,1))+SUMIFS('2025'!$U$10:$U$112,'2025'!$V$10:$V$112,">="&DATE(2025,9,1),'2025'!$V$10:$V$112,"<"&DATE(2025,10,1))+SUMIFS('2024'!$I$10:$I$108,'2024'!$J$10:$J$108,">="&DATE(2025,9,1),'2024'!$J$10:$J$108,"<"&DATE(2025,10,1))+SUMIFS('2024'!$L$10:$L$108,'2024'!$M$10:$M$108,">="&DATE(2025,9,1),'2024'!$M$10:$M$108,"<"&DATE(2025,10,1))+SUMIFS('2024'!$O$10:$O$108,'2024'!$P$10:$P$108,">="&DATE(2025,9,1),'2024'!$P$10:$P$108,"<"&DATE(2025,10,1))+SUMIFS('2024'!$R$10:$R$108,'2024'!$S$10:$S$108,">="&DATE(2025,9,1),'2024'!$S$10:$S$108,"<"&DATE(2025,10,1))+SUMIFS('2024'!$U$10:$U$108,'2024'!$V$10:$V$108,">="&DATE(2025,9,1),'2024'!$V$10:$V$108,"<"&DATE(2025,10,1))+SUMIFS('2023'!$I$10:$I$127,'2023'!$J$10:$J$127,">="&DATE(2025,9,1),'2023'!$J$10:$J$127,"<"&DATE(2025,10,1))+SUMIFS('2023'!$L$10:$L$127,'2023'!$M$10:$M$127,">="&DATE(2025,9,1),'2023'!$M$10:$M$127,"<"&DATE(2025,10,1))+SUMIFS('2023'!$O$10:$O$127,'2023'!$P$10:$P$127,">="&DATE(2025,9,1),'2023'!$P$10:$P$127,"<"&DATE(2025,10,1))+SUMIFS('2023'!$R$10:$R$127,'2023'!$S$10:$S$127,">="&DATE(2025,9,1),'2023'!$S$10:$S$127,"<"&DATE(2025,10,1))+SUMIFS('2023'!$U$10:$U$127,'2023'!$V$10:$V$127,">="&DATE(2025,9,1),'2023'!$V$10:$V$127,"<"&DATE(2025,10,1)),2) | E16: =ROUND(SUMIFS('2026'!$I$10:$I$107,'2026'!$J$10:$J$107,">="&DATE(2026,9,1),'2026'!$J$10:$J$107,"<"&DATE(2026,10,1))+SUMIFS('2026'!$L$10:$L$107,'2026'!$M$10:$M$107,">="&DATE(2026,9,1),'2026'!$M$10:$M$107,"<"&DATE(2026,10,1))+SUMIFS('2026'!$O$10:$O$107,'2026'!$P$10:$P$107,">="&DATE(2026,9,1),'2026'!$P$10:$P$107,"<"&DATE(2026,10,1))+SUMIFS('2026'!$R$10:$R$107,'2026'!$S$10:$S$107,">="&DATE(2026,9,1),'2026'!$S$10:$S$107,"<"&DATE(2026,10,1))+SUMIFS('2026'!$U$10:$U$107,'2026'!$V$10:$V$107,">="&DATE(2026,9,1),'2026'!$V$10:$V$107,"<"&DATE(2026,10,1))+SUMIFS('2025'!$I$10:$I$112,'2025'!$J$10:$J$112,">="&DATE(2026,9,1),'2025'!$J$10:$J$112,"<"&DATE(2026,10,1))+SUMIFS('2025'!$L$10:$L$112,'2025'!$M$10:$M$112,">="&DATE(2026,9,1),'2025'!$M$10:$M$112,"<"&DATE(2026,10,1))+SUMIFS('2025'!$O$10:$O$112,'2025'!$P$10:$P$112,">="&DATE(2026,9,1),'2025'!$P$10:$P$112,"<"&DATE(2026,10,1))+SUMIFS('2025'!$R$10:$R$112,'2025'!$S$10:$S$112,">="&DATE(2026,9,1),'2025'!$S$10:$S$112,"<"&DATE(2026,10,1))+SUMIFS('2025'!$U$10:$U$112,'2025'!$V$10:$V$112,">="&DATE(2026,9,1),'2025'!$V$10:$V$112,"<"&DATE(2026,10,1))+SUMIFS('2024'!$I$10:$I$108,'2024'!$J$10:$J$108,">="&DATE(2026,9,1),'2024'!$J$10:$J$108,"<"&DATE(2026,10,1))+SUMIFS('2024'!$L$10:$L$108,'2024'!$M$10:$M$108,">="&DATE(2026,9,1),'2024'!$M$10:$M$108,"<"&DATE(2026,10,1))+SUMIFS('2024'!$O$10:$O$108,'2024'!$P$10:$P$108,">="&DATE(2026,9,1),'2024'!$P$10:$P$108,"<"&DATE(2026,10,1))+SUMIFS('2024'!$R$10:$R$108,'2024'!$S$10:$S$108,">="&DATE(2026,9,1),'2024'!$S$10:$S$108,"<"&DATE(2026,10,1))+SUMIFS('2024'!$U$10:$U$108,'2024'!$V$10:$V$108,">="&DATE(2026,9,1),'2024'!$V$10:$V$108,"<"&DATE(2026,10,1))+SUMIFS('2023'!$I$10:$I$127,'2023'!$J$10:$J$127,">="&DATE(2026,9,1),'2023'!$J$10:$J$127,"<"&DATE(2026,10,1))+SUMIFS('2023'!$L$10:$L$127,'2023'!$M$10:$M$127,">="&DATE(2026,9,1),'2023'!$M$10:$M$127,"<"&DATE(2026,10,1))+SUMIFS('2023'!$O$10:$O$127,'2023'!$P$10:$P$127,">="&DATE(2026,9,1),'2023'!$P$10:$P$127,"<"&DATE(2026,10,1))+SUMIFS('2023'!$R$10:$R$127,'2023'!$S$10:$S$127,">="&DATE(2026,9,1),'2023'!$S$10:$S$127,"<"&DATE(2026,10,1))+SUMIFS('2023'!$U$10:$U$127,'2023'!$V$10:$V$127,">="&DATE(2026,9,1),'2023'!$V$10:$V$127,"<"&DATE(2026,10,1)),2) | F16: =ROUND(AVERAGE($B16:$D16),0) | G16: =IF(SUM($F$8:$F$19)=0,"",$F16/SUM($F$8:$F$19))
A17: Outubro | B17: =ROUND(SUMIFS('2026'!$I$10:$I$107,'2026'!$J$10:$J$107,">="&DATE(2023,10,1),'2026'!$J$10:$J$107,"<"&DATE(2023,11,1))+SUMIFS('2026'!$L$10:$L$107,'2026'!$M$10:$M$107,">="&DATE(2023,10,1),'2026'!$M$10:$M$107,"<"&DATE(2023,11,1))+SUMIFS('2026'!$O$10:$O$107,'2026'!$P$10:$P$107,">="&DATE(2023,10,1),'2026'!$P$10:$P$107,"<"&DATE(2023,11,1))+SUMIFS('2026'!$R$10:$R$107,'2026'!$S$10:$S$107,">="&DATE(2023,10,1),'2026'!$S$10:$S$107,"<"&DATE(2023,11,1))+SUMIFS('2026'!$U$10:$U$107,'2026'!$V$10:$V$107,">="&DATE(2023,10,1),'2026'!$V$10:$V$107,"<"&DATE(2023,11,1))+SUMIFS('2025'!$I$10:$I$112,'2025'!$J$10:$J$112,">="&DATE(2023,10,1),'2025'!$J$10:$J$112,"<"&DATE(2023,11,1))+SUMIFS('2025'!$L$10:$L$112,'2025'!$M$10:$M$112,">="&DATE(2023,10,1),'2025'!$M$10:$M$112,"<"&DATE(2023,11,1))+SUMIFS('2025'!$O$10:$O$112,'2025'!$P$10:$P$112,">="&DATE(2023,10,1),'2025'!$P$10:$P$112,"<"&DATE(2023,11,1))+SUMIFS('2025'!$R$10:$R$112,'2025'!$S$10:$S$112,">="&DATE(2023,10,1),'2025'!$S$10:$S$112,"<"&DATE(2023,11,1))+SUMIFS('2025'!$U$10:$U$112,'2025'!$V$10:$V$112,">="&DATE(2023,10,1),'2025'!$V$10:$V$112,"<"&DATE(2023,11,1))+SUMIFS('2024'!$I$10:$I$108,'2024'!$J$10:$J$108,">="&DATE(2023,10,1),'2024'!$J$10:$J$108,"<"&DATE(2023,11,1))+SUMIFS('2024'!$L$10:$L$108,'2024'!$M$10:$M$108,">="&DATE(2023,10,1),'2024'!$M$10:$M$108,"<"&DATE(2023,11,1))+SUMIFS('2024'!$O$10:$O$108,'2024'!$P$10:$P$108,">="&DATE(2023,10,1),'2024'!$P$10:$P$108,"<"&DATE(2023,11,1))+SUMIFS('2024'!$R$10:$R$108,'2024'!$S$10:$S$108,">="&DATE(2023,10,1),'2024'!$S$10:$S$108,"<"&DATE(2023,11,1))+SUMIFS('2024'!$U$10:$U$108,'2024'!$V$10:$V$108,">="&DATE(2023,10,1),'2024'!$V$10:$V$108,"<"&DATE(2023,11,1))+SUMIFS('2023'!$I$10:$I$127,'2023'!$J$10:$J$127,">="&DATE(2023,10,1),'2023'!$J$10:$J$127,"<"&DATE(2023,11,1))+SUMIFS('2023'!$L$10:$L$127,'2023'!$M$10:$M$127,">="&DATE(2023,10,1),'2023'!$M$10:$M$127,"<"&DATE(2023,11,1))+SUMIFS('2023'!$O$10:$O$127,'2023'!$P$10:$P$127,">="&DATE(2023,10,1),'2023'!$P$10:$P$127,"<"&DATE(2023,11,1))+SUMIFS('2023'!$R$10:$R$127,'2023'!$S$10:$S$127,">="&DATE(2023,10,1),'2023'!$S$10:$S$127,"<"&DATE(2023,11,1))+SUMIFS('2023'!$U$10:$U$127,'2023'!$V$10:$V$127,">="&DATE(2023,10,1),'2023'!$V$10:$V$127,"<"&DATE(2023,11,1)),2) | C17: =ROUND(SUMIFS('2026'!$I$10:$I$107,'2026'!$J$10:$J$107,">="&DATE(2024,10,1),'2026'!$J$10:$J$107,"<"&DATE(2024,11,1))+SUMIFS('2026'!$L$10:$L$107,'2026'!$M$10:$M$107,">="&DATE(2024,10,1),'2026'!$M$10:$M$107,"<"&DATE(2024,11,1))+SUMIFS('2026'!$O$10:$O$107,'2026'!$P$10:$P$107,">="&DATE(2024,10,1),'2026'!$P$10:$P$107,"<"&DATE(2024,11,1))+SUMIFS('2026'!$R$10:$R$107,'2026'!$S$10:$S$107,">="&DATE(2024,10,1),'2026'!$S$10:$S$107,"<"&DATE(2024,11,1))+SUMIFS('2026'!$U$10:$U$107,'2026'!$V$10:$V$107,">="&DATE(2024,10,1),'2026'!$V$10:$V$107,"<"&DATE(2024,11,1))+SUMIFS('2025'!$I$10:$I$112,'2025'!$J$10:$J$112,">="&DATE(2024,10,1),'2025'!$J$10:$J$112,"<"&DATE(2024,11,1))+SUMIFS('2025'!$L$10:$L$112,'2025'!$M$10:$M$112,">="&DATE(2024,10,1),'2025'!$M$10:$M$112,"<"&DATE(2024,11,1))+SUMIFS('2025'!$O$10:$O$112,'2025'!$P$10:$P$112,">="&DATE(2024,10,1),'2025'!$P$10:$P$112,"<"&DATE(2024,11,1))+SUMIFS('2025'!$R$10:$R$112,'2025'!$S$10:$S$112,">="&DATE(2024,10,1),'2025'!$S$10:$S$112,"<"&DATE(2024,11,1))+SUMIFS('2025'!$U$10:$U$112,'2025'!$V$10:$V$112,">="&DATE(2024,10,1),'2025'!$V$10:$V$112,"<"&DATE(2024,11,1))+SUMIFS('2024'!$I$10:$I$108,'2024'!$J$10:$J$108,">="&DATE(2024,10,1),'2024'!$J$10:$J$108,"<"&DATE(2024,11,1))+SUMIFS('2024'!$L$10:$L$108,'2024'!$M$10:$M$108,">="&DATE(2024,10,1),'2024'!$M$10:$M$108,"<"&DATE(2024,11,1))+SUMIFS('2024'!$O$10:$O$108,'2024'!$P$10:$P$108,">="&DATE(2024,10,1),'2024'!$P$10:$P$108,"<"&DATE(2024,11,1))+SUMIFS('2024'!$R$10:$R$108,'2024'!$S$10:$S$108,">="&DATE(2024,10,1),'2024'!$S$10:$S$108,"<"&DATE(2024,11,1))+SUMIFS('2024'!$U$10:$U$108,'2024'!$V$10:$V$108,">="&DATE(2024,10,1),'2024'!$V$10:$V$108,"<"&DATE(2024,11,1))+SUMIFS('2023'!$I$10:$I$127,'2023'!$J$10:$J$127,">="&DATE(2024,10,1),'2023'!$J$10:$J$127,"<"&DATE(2024,11,1))+SUMIFS('2023'!$L$10:$L$127,'2023'!$M$10:$M$127,">="&DATE(2024,10,1),'2023'!$M$10:$M$127,"<"&DATE(2024,11,1))+SUMIFS('2023'!$O$10:$O$127,'2023'!$P$10:$P$127,">="&DATE(2024,10,1),'2023'!$P$10:$P$127,"<"&DATE(2024,11,1))+SUMIFS('2023'!$R$10:$R$127,'2023'!$S$10:$S$127,">="&DATE(2024,10,1),'2023'!$S$10:$S$127,"<"&DATE(2024,11,1))+SUMIFS('2023'!$U$10:$U$127,'2023'!$V$10:$V$127,">="&DATE(2024,10,1),'2023'!$V$10:$V$127,"<"&DATE(2024,11,1)),2) | D17: =ROUND(SUMIFS('2026'!$I$10:$I$107,'2026'!$J$10:$J$107,">="&DATE(2025,10,1),'2026'!$J$10:$J$107,"<"&DATE(2025,11,1))+SUMIFS('2026'!$L$10:$L$107,'2026'!$M$10:$M$107,">="&DATE(2025,10,1),'2026'!$M$10:$M$107,"<"&DATE(2025,11,1))+SUMIFS('2026'!$O$10:$O$107,'2026'!$P$10:$P$107,">="&DATE(2025,10,1),'2026'!$P$10:$P$107,"<"&DATE(2025,11,1))+SUMIFS('2026'!$R$10:$R$107,'2026'!$S$10:$S$107,">="&DATE(2025,10,1),'2026'!$S$10:$S$107,"<"&DATE(2025,11,1))+SUMIFS('2026'!$U$10:$U$107,'2026'!$V$10:$V$107,">="&DATE(2025,10,1),'2026'!$V$10:$V$107,"<"&DATE(2025,11,1))+SUMIFS('2025'!$I$10:$I$112,'2025'!$J$10:$J$112,">="&DATE(2025,10,1),'2025'!$J$10:$J$112,"<"&DATE(2025,11,1))+SUMIFS('2025'!$L$10:$L$112,'2025'!$M$10:$M$112,">="&DATE(2025,10,1),'2025'!$M$10:$M$112,"<"&DATE(2025,11,1))+SUMIFS('2025'!$O$10:$O$112,'2025'!$P$10:$P$112,">="&DATE(2025,10,1),'2025'!$P$10:$P$112,"<"&DATE(2025,11,1))+SUMIFS('2025'!$R$10:$R$112,'2025'!$S$10:$S$112,">="&DATE(2025,10,1),'2025'!$S$10:$S$112,"<"&DATE(2025,11,1))+SUMIFS('2025'!$U$10:$U$112,'2025'!$V$10:$V$112,">="&DATE(2025,10,1),'2025'!$V$10:$V$112,"<"&DATE(2025,11,1))+SUMIFS('2024'!$I$10:$I$108,'2024'!$J$10:$J$108,">="&DATE(2025,10,1),'2024'!$J$10:$J$108,"<"&DATE(2025,11,1))+SUMIFS('2024'!$L$10:$L$108,'2024'!$M$10:$M$108,">="&DATE(2025,10,1),'2024'!$M$10:$M$108,"<"&DATE(2025,11,1))+SUMIFS('2024'!$O$10:$O$108,'2024'!$P$10:$P$108,">="&DATE(2025,10,1),'2024'!$P$10:$P$108,"<"&DATE(2025,11,1))+SUMIFS('2024'!$R$10:$R$108,'2024'!$S$10:$S$108,">="&DATE(2025,10,1),'2024'!$S$10:$S$108,"<"&DATE(2025,11,1))+SUMIFS('2024'!$U$10:$U$108,'2024'!$V$10:$V$108,">="&DATE(2025,10,1),'2024'!$V$10:$V$108,"<"&DATE(2025,11,1))+SUMIFS('2023'!$I$10:$I$127,'2023'!$J$10:$J$127,">="&DATE(2025,10,1),'2023'!$J$10:$J$127,"<"&DATE(2025,11,1))+SUMIFS('2023'!$L$10:$L$127,'2023'!$M$10:$M$127,">="&DATE(2025,10,1),'2023'!$M$10:$M$127,"<"&DATE(2025,11,1))+SUMIFS('2023'!$O$10:$O$127,'2023'!$P$10:$P$127,">="&DATE(2025,10,1),'2023'!$P$10:$P$127,"<"&DATE(2025,11,1))+SUMIFS('2023'!$R$10:$R$127,'2023'!$S$10:$S$127,">="&DATE(2025,10,1),'2023'!$S$10:$S$127,"<"&DATE(2025,11,1))+SUMIFS('2023'!$U$10:$U$127,'2023'!$V$10:$V$127,">="&DATE(2025,10,1),'2023'!$V$10:$V$127,"<"&DATE(2025,11,1)),2) | E17: =ROUND(SUMIFS('2026'!$I$10:$I$107,'2026'!$J$10:$J$107,">="&DATE(2026,10,1),'2026'!$J$10:$J$107,"<"&DATE(2026,11,1))+SUMIFS('2026'!$L$10:$L$107,'2026'!$M$10:$M$107,">="&DATE(2026,10,1),'2026'!$M$10:$M$107,"<"&DATE(2026,11,1))+SUMIFS('2026'!$O$10:$O$107,'2026'!$P$10:$P$107,">="&DATE(2026,10,1),'2026'!$P$10:$P$107,"<"&DATE(2026,11,1))+SUMIFS('2026'!$R$10:$R$107,'2026'!$S$10:$S$107,">="&DATE(2026,10,1),'2026'!$S$10:$S$107,"<"&DATE(2026,11,1))+SUMIFS('2026'!$U$10:$U$107,'2026'!$V$10:$V$107,">="&DATE(2026,10,1),'2026'!$V$10:$V$107,"<"&DATE(2026,11,1))+SUMIFS('2025'!$I$10:$I$112,'2025'!$J$10:$J$112,">="&DATE(2026,10,1),'2025'!$J$10:$J$112,"<"&DATE(2026,11,1))+SUMIFS('2025'!$L$10:$L$112,'2025'!$M$10:$M$112,">="&DATE(2026,10,1),'2025'!$M$10:$M$112,"<"&DATE(2026,11,1))+SUMIFS('2025'!$O$10:$O$112,'2025'!$P$10:$P$112,">="&DATE(2026,10,1),'2025'!$P$10:$P$112,"<"&DATE(2026,11,1))+SUMIFS('2025'!$R$10:$R$112,'2025'!$S$10:$S$112,">="&DATE(2026,10,1),'2025'!$S$10:$S$112,"<"&DATE(2026,11,1))+SUMIFS('2025'!$U$10:$U$112,'2025'!$V$10:$V$112,">="&DATE(2026,10,1),'2025'!$V$10:$V$112,"<"&DATE(2026,11,1))+SUMIFS('2024'!$I$10:$I$108,'2024'!$J$10:$J$108,">="&DATE(2026,10,1),'2024'!$J$10:$J$108,"<"&DATE(2026,11,1))+SUMIFS('2024'!$L$10:$L$108,'2024'!$M$10:$M$108,">="&DATE(2026,10,1),'2024'!$M$10:$M$108,"<"&DATE(2026,11,1))+SUMIFS('2024'!$O$10:$O$108,'2024'!$P$10:$P$108,">="&DATE(2026,10,1),'2024'!$P$10:$P$108,"<"&DATE(2026,11,1))+SUMIFS('2024'!$R$10:$R$108,'2024'!$S$10:$S$108,">="&DATE(2026,10,1),'2024'!$S$10:$S$108,"<"&DATE(2026,11,1))+SUMIFS('2024'!$U$10:$U$108,'2024'!$V$10:$V$108,">="&DATE(2026,10,1),'2024'!$V$10:$V$108,"<"&DATE(2026,11,1))+SUMIFS('2023'!$I$10:$I$127,'2023'!$J$10:$J$127,">="&DATE(2026,10,1),'2023'!$J$10:$J$127,"<"&DATE(2026,11,1))+SUMIFS('2023'!$L$10:$L$127,'2023'!$M$10:$M$127,">="&DATE(2026,10,1),'2023'!$M$10:$M$127,"<"&DATE(2026,11,1))+SUMIFS('2023'!$O$10:$O$127,'2023'!$P$10:$P$127,">="&DATE(2026,10,1),'2023'!$P$10:$P$127,"<"&DATE(2026,11,1))+SUMIFS('2023'!$R$10:$R$127,'2023'!$S$10:$S$127,">="&DATE(2026,10,1),'2023'!$S$10:$S$127,"<"&DATE(2026,11,1))+SUMIFS('2023'!$U$10:$U$127,'2023'!$V$10:$V$127,">="&DATE(2026,10,1),'2023'!$V$10:$V$127,"<"&DATE(2026,11,1)),2) | F17: =ROUND(AVERAGE($B17:$D17),0) | G17: =IF(SUM($F$8:$F$19)=0,"",$F17/SUM($F$8:$F$19))
A18: Novembro | B18: =ROUND(SUMIFS('2026'!$I$10:$I$107,'2026'!$J$10:$J$107,">="&DATE(2023,11,1),'2026'!$J$10:$J$107,"<"&DATE(2023,12,1))+SUMIFS('2026'!$L$10:$L$107,'2026'!$M$10:$M$107,">="&DATE(2023,11,1),'2026'!$M$10:$M$107,"<"&DATE(2023,12,1))+SUMIFS('2026'!$O$10:$O$107,'2026'!$P$10:$P$107,">="&DATE(2023,11,1),'2026'!$P$10:$P$107,"<"&DATE(2023,12,1))+SUMIFS('2026'!$R$10:$R$107,'2026'!$S$10:$S$107,">="&DATE(2023,11,1),'2026'!$S$10:$S$107,"<"&DATE(2023,12,1))+SUMIFS('2026'!$U$10:$U$107,'2026'!$V$10:$V$107,">="&DATE(2023,11,1),'2026'!$V$10:$V$107,"<"&DATE(2023,12,1))+SUMIFS('2025'!$I$10:$I$112,'2025'!$J$10:$J$112,">="&DATE(2023,11,1),'2025'!$J$10:$J$112,"<"&DATE(2023,12,1))+SUMIFS('2025'!$L$10:$L$112,'2025'!$M$10:$M$112,">="&DATE(2023,11,1),'2025'!$M$10:$M$112,"<"&DATE(2023,12,1))+SUMIFS('2025'!$O$10:$O$112,'2025'!$P$10:$P$112,">="&DATE(2023,11,1),'2025'!$P$10:$P$112,"<"&DATE(2023,12,1))+SUMIFS('2025'!$R$10:$R$112,'2025'!$S$10:$S$112,">="&DATE(2023,11,1),'2025'!$S$10:$S$112,"<"&DATE(2023,12,1))+SUMIFS('2025'!$U$10:$U$112,'2025'!$V$10:$V$112,">="&DATE(2023,11,1),'2025'!$V$10:$V$112,"<"&DATE(2023,12,1))+SUMIFS('2024'!$I$10:$I$108,'2024'!$J$10:$J$108,">="&DATE(2023,11,1),'2024'!$J$10:$J$108,"<"&DATE(2023,12,1))+SUMIFS('2024'!$L$10:$L$108,'2024'!$M$10:$M$108,">="&DATE(2023,11,1),'2024'!$M$10:$M$108,"<"&DATE(2023,12,1))+SUMIFS('2024'!$O$10:$O$108,'2024'!$P$10:$P$108,">="&DATE(2023,11,1),'2024'!$P$10:$P$108,"<"&DATE(2023,12,1))+SUMIFS('2024'!$R$10:$R$108,'2024'!$S$10:$S$108,">="&DATE(2023,11,1),'2024'!$S$10:$S$108,"<"&DATE(2023,12,1))+SUMIFS('2024'!$U$10:$U$108,'2024'!$V$10:$V$108,">="&DATE(2023,11,1),'2024'!$V$10:$V$108,"<"&DATE(2023,12,1))+SUMIFS('2023'!$I$10:$I$127,'2023'!$J$10:$J$127,">="&DATE(2023,11,1),'2023'!$J$10:$J$127,"<"&DATE(2023,12,1))+SUMIFS('2023'!$L$10:$L$127,'2023'!$M$10:$M$127,">="&DATE(2023,11,1),'2023'!$M$10:$M$127,"<"&DATE(2023,12,1))+SUMIFS('2023'!$O$10:$O$127,'2023'!$P$10:$P$127,">="&DATE(2023,11,1),'2023'!$P$10:$P$127,"<"&DATE(2023,12,1))+SUMIFS('2023'!$R$10:$R$127,'2023'!$S$10:$S$127,">="&DATE(2023,11,1),'2023'!$S$10:$S$127,"<"&DATE(2023,12,1))+SUMIFS('2023'!$U$10:$U$127,'2023'!$V$10:$V$127,">="&DATE(2023,11,1),'2023'!$V$10:$V$127,"<"&DATE(2023,12,1)),2) | C18: =ROUND(SUMIFS('2026'!$I$10:$I$107,'2026'!$J$10:$J$107,">="&DATE(2024,11,1),'2026'!$J$10:$J$107,"<"&DATE(2024,12,1))+SUMIFS('2026'!$L$10:$L$107,'2026'!$M$10:$M$107,">="&DATE(2024,11,1),'2026'!$M$10:$M$107,"<"&DATE(2024,12,1))+SUMIFS('2026'!$O$10:$O$107,'2026'!$P$10:$P$107,">="&DATE(2024,11,1),'2026'!$P$10:$P$107,"<"&DATE(2024,12,1))+SUMIFS('2026'!$R$10:$R$107,'2026'!$S$10:$S$107,">="&DATE(2024,11,1),'2026'!$S$10:$S$107,"<"&DATE(2024,12,1))+SUMIFS('2026'!$U$10:$U$107,'2026'!$V$10:$V$107,">="&DATE(2024,11,1),'2026'!$V$10:$V$107,"<"&DATE(2024,12,1))+SUMIFS('2025'!$I$10:$I$112,'2025'!$J$10:$J$112,">="&DATE(2024,11,1),'2025'!$J$10:$J$112,"<"&DATE(2024,12,1))+SUMIFS('2025'!$L$10:$L$112,'2025'!$M$10:$M$112,">="&DATE(2024,11,1),'2025'!$M$10:$M$112,"<"&DATE(2024,12,1))+SUMIFS('2025'!$O$10:$O$112,'2025'!$P$10:$P$112,">="&DATE(2024,11,1),'2025'!$P$10:$P$112,"<"&DATE(2024,12,1))+SUMIFS('2025'!$R$10:$R$112,'2025'!$S$10:$S$112,">="&DATE(2024,11,1),'2025'!$S$10:$S$112,"<"&DATE(2024,12,1))+SUMIFS('2025'!$U$10:$U$112,'2025'!$V$10:$V$112,">="&DATE(2024,11,1),'2025'!$V$10:$V$112,"<"&DATE(2024,12,1))+SUMIFS('2024'!$I$10:$I$108,'2024'!$J$10:$J$108,">="&DATE(2024,11,1),'2024'!$J$10:$J$108,"<"&DATE(2024,12,1))+SUMIFS('2024'!$L$10:$L$108,'2024'!$M$10:$M$108,">="&DATE(2024,11,1),'2024'!$M$10:$M$108,"<"&DATE(2024,12,1))+SUMIFS('2024'!$O$10:$O$108,'2024'!$P$10:$P$108,">="&DATE(2024,11,1),'2024'!$P$10:$P$108,"<"&DATE(2024,12,1))+SUMIFS('2024'!$R$10:$R$108,'2024'!$S$10:$S$108,">="&DATE(2024,11,1),'2024'!$S$10:$S$108,"<"&DATE(2024,12,1))+SUMIFS('2024'!$U$10:$U$108,'2024'!$V$10:$V$108,">="&DATE(2024,11,1),'2024'!$V$10:$V$108,"<"&DATE(2024,12,1))+SUMIFS('2023'!$I$10:$I$127,'2023'!$J$10:$J$127,">="&DATE(2024,11,1),'2023'!$J$10:$J$127,"<"&DATE(2024,12,1))+SUMIFS('2023'!$L$10:$L$127,'2023'!$M$10:$M$127,">="&DATE(2024,11,1),'2023'!$M$10:$M$127,"<"&DATE(2024,12,1))+SUMIFS('2023'!$O$10:$O$127,'2023'!$P$10:$P$127,">="&DATE(2024,11,1),'2023'!$P$10:$P$127,"<"&DATE(2024,12,1))+SUMIFS('2023'!$R$10:$R$127,'2023'!$S$10:$S$127,">="&DATE(2024,11,1),'2023'!$S$10:$S$127,"<"&DATE(2024,12,1))+SUMIFS('2023'!$U$10:$U$127,'2023'!$V$10:$V$127,">="&DATE(2024,11,1),'2023'!$V$10:$V$127,"<"&DATE(2024,12,1)),2) | D18: =ROUND(SUMIFS('2026'!$I$10:$I$107,'2026'!$J$10:$J$107,">="&DATE(2025,11,1),'2026'!$J$10:$J$107,"<"&DATE(2025,12,1))+SUMIFS('2026'!$L$10:$L$107,'2026'!$M$10:$M$107,">="&DATE(2025,11,1),'2026'!$M$10:$M$107,"<"&DATE(2025,12,1))+SUMIFS('2026'!$O$10:$O$107,'2026'!$P$10:$P$107,">="&DATE(2025,11,1),'2026'!$P$10:$P$107,"<"&DATE(2025,12,1))+SUMIFS('2026'!$R$10:$R$107,'2026'!$S$10:$S$107,">="&DATE(2025,11,1),'2026'!$S$10:$S$107,"<"&DATE(2025,12,1))+SUMIFS('2026'!$U$10:$U$107,'2026'!$V$10:$V$107,">="&DATE(2025,11,1),'2026'!$V$10:$V$107,"<"&DATE(2025,12,1))+SUMIFS('2025'!$I$10:$I$112,'2025'!$J$10:$J$112,">="&DATE(2025,11,1),'2025'!$J$10:$J$112,"<"&DATE(2025,12,1))+SUMIFS('2025'!$L$10:$L$112,'2025'!$M$10:$M$112,">="&DATE(2025,11,1),'2025'!$M$10:$M$112,"<"&DATE(2025,12,1))+SUMIFS('2025'!$O$10:$O$112,'2025'!$P$10:$P$112,">="&DATE(2025,11,1),'2025'!$P$10:$P$112,"<"&DATE(2025,12,1))+SUMIFS('2025'!$R$10:$R$112,'2025'!$S$10:$S$112,">="&DATE(2025,11,1),'2025'!$S$10:$S$112,"<"&DATE(2025,12,1))+SUMIFS('2025'!$U$10:$U$112,'2025'!$V$10:$V$112,">="&DATE(2025,11,1),'2025'!$V$10:$V$112,"<"&DATE(2025,12,1))+SUMIFS('2024'!$I$10:$I$108,'2024'!$J$10:$J$108,">="&DATE(2025,11,1),'2024'!$J$10:$J$108,"<"&DATE(2025,12,1))+SUMIFS('2024'!$L$10:$L$108,'2024'!$M$10:$M$108,">="&DATE(2025,11,1),'2024'!$M$10:$M$108,"<"&DATE(2025,12,1))+SUMIFS('2024'!$O$10:$O$108,'2024'!$P$10:$P$108,">="&DATE(2025,11,1),'2024'!$P$10:$P$108,"<"&DATE(2025,12,1))+SUMIFS('2024'!$R$10:$R$108,'2024'!$S$10:$S$108,">="&DATE(2025,11,1),'2024'!$S$10:$S$108,"<"&DATE(2025,12,1))+SUMIFS('2024'!$U$10:$U$108,'2024'!$V$10:$V$108,">="&DATE(2025,11,1),'2024'!$V$10:$V$108,"<"&DATE(2025,12,1))+SUMIFS('2023'!$I$10:$I$127,'2023'!$J$10:$J$127,">="&DATE(2025,11,1),'2023'!$J$10:$J$127,"<"&DATE(2025,12,1))+SUMIFS('2023'!$L$10:$L$127,'2023'!$M$10:$M$127,">="&DATE(2025,11,1),'2023'!$M$10:$M$127,"<"&DATE(2025,12,1))+SUMIFS('2023'!$O$10:$O$127,'2023'!$P$10:$P$127,">="&DATE(2025,11,1),'2023'!$P$10:$P$127,"<"&DATE(2025,12,1))+SUMIFS('2023'!$R$10:$R$127,'2023'!$S$10:$S$127,">="&DATE(2025,11,1),'2023'!$S$10:$S$127,"<"&DATE(2025,12,1))+SUMIFS('2023'!$U$10:$U$127,'2023'!$V$10:$V$127,">="&DATE(2025,11,1),'2023'!$V$10:$V$127,"<"&DATE(2025,12,1)),2) | E18: =ROUND(SUMIFS('2026'!$I$10:$I$107,'2026'!$J$10:$J$107,">="&DATE(2026,11,1),'2026'!$J$10:$J$107,"<"&DATE(2026,12,1))+SUMIFS('2026'!$L$10:$L$107,'2026'!$M$10:$M$107,">="&DATE(2026,11,1),'2026'!$M$10:$M$107,"<"&DATE(2026,12,1))+SUMIFS('2026'!$O$10:$O$107,'2026'!$P$10:$P$107,">="&DATE(2026,11,1),'2026'!$P$10:$P$107,"<"&DATE(2026,12,1))+SUMIFS('2026'!$R$10:$R$107,'2026'!$S$10:$S$107,">="&DATE(2026,11,1),'2026'!$S$10:$S$107,"<"&DATE(2026,12,1))+SUMIFS('2026'!$U$10:$U$107,'2026'!$V$10:$V$107,">="&DATE(2026,11,1),'2026'!$V$10:$V$107,"<"&DATE(2026,12,1))+SUMIFS('2025'!$I$10:$I$112,'2025'!$J$10:$J$112,">="&DATE(2026,11,1),'2025'!$J$10:$J$112,"<"&DATE(2026,12,1))+SUMIFS('2025'!$L$10:$L$112,'2025'!$M$10:$M$112,">="&DATE(2026,11,1),'2025'!$M$10:$M$112,"<"&DATE(2026,12,1))+SUMIFS('2025'!$O$10:$O$112,'2025'!$P$10:$P$112,">="&DATE(2026,11,1),'2025'!$P$10:$P$112,"<"&DATE(2026,12,1))+SUMIFS('2025'!$R$10:$R$112,'2025'!$S$10:$S$112,">="&DATE(2026,11,1),'2025'!$S$10:$S$112,"<"&DATE(2026,12,1))+SUMIFS('2025'!$U$10:$U$112,'2025'!$V$10:$V$112,">="&DATE(2026,11,1),'2025'!$V$10:$V$112,"<"&DATE(2026,12,1))+SUMIFS('2024'!$I$10:$I$108,'2024'!$J$10:$J$108,">="&DATE(2026,11,1),'2024'!$J$10:$J$108,"<"&DATE(2026,12,1))+SUMIFS('2024'!$L$10:$L$108,'2024'!$M$10:$M$108,">="&DATE(2026,11,1),'2024'!$M$10:$M$108,"<"&DATE(2026,12,1))+SUMIFS('2024'!$O$10:$O$108,'2024'!$P$10:$P$108,">="&DATE(2026,11,1),'2024'!$P$10:$P$108,"<"&DATE(2026,12,1))+SUMIFS('2024'!$R$10:$R$108,'2024'!$S$10:$S$108,">="&DATE(2026,11,1),'2024'!$S$10:$S$108,"<"&DATE(2026,12,1))+SUMIFS('2024'!$U$10:$U$108,'2024'!$V$10:$V$108,">="&DATE(2026,11,1),'2024'!$V$10:$V$108,"<"&DATE(2026,12,1))+SUMIFS('2023'!$I$10:$I$127,'2023'!$J$10:$J$127,">="&DATE(2026,11,1),'2023'!$J$10:$J$127,"<"&DATE(2026,12,1))+SUMIFS('2023'!$L$10:$L$127,'2023'!$M$10:$M$127,">="&DATE(2026,11,1),'2023'!$M$10:$M$127,"<"&DATE(2026,12,1))+SUMIFS('2023'!$O$10:$O$127,'2023'!$P$10:$P$127,">="&DATE(2026,11,1),'2023'!$P$10:$P$127,"<"&DATE(2026,12,1))+SUMIFS('2023'!$R$10:$R$127,'2023'!$S$10:$S$127,">="&DATE(2026,11,1),'2023'!$S$10:$S$127,"<"&DATE(2026,12,1))+SUMIFS('2023'!$U$10:$U$127,'2023'!$V$10:$V$127,">="&DATE(2026,11,1),'2023'!$V$10:$V$127,"<"&DATE(2026,12,1)),2) | F18: =ROUND(AVERAGE($B18:$D18),0) | G18: =IF(SUM($F$8:$F$19)=0,"",$F18/SUM($F$8:$F$19))
A19: Dezembro | B19: =ROUND(SUMIFS('2026'!$I$10:$I$107,'2026'!$J$10:$J$107,">="&DATE(2023,12,1),'2026'!$J$10:$J$107,"<"&DATE(2023,13,1))+SUMIFS('2026'!$L$10:$L$107,'2026'!$M$10:$M$107,">="&DATE(2023,12,1),'2026'!$M$10:$M$107,"<"&DATE(2023,13,1))+SUMIFS('2026'!$O$10:$O$107,'2026'!$P$10:$P$107,">="&DATE(2023,12,1),'2026'!$P$10:$P$107,"<"&DATE(2023,13,1))+SUMIFS('2026'!$R$10:$R$107,'2026'!$S$10:$S$107,">="&DATE(2023,12,1),'2026'!$S$10:$S$107,"<"&DATE(2023,13,1))+SUMIFS('2026'!$U$10:$U$107,'2026'!$V$10:$V$107,">="&DATE(2023,12,1),'2026'!$V$10:$V$107,"<"&DATE(2023,13,1))+SUMIFS('2025'!$I$10:$I$112,'2025'!$J$10:$J$112,">="&DATE(2023,12,1),'2025'!$J$10:$J$112,"<"&DATE(2023,13,1))+SUMIFS('2025'!$L$10:$L$112,'2025'!$M$10:$M$112,">="&DATE(2023,12,1),'2025'!$M$10:$M$112,"<"&DATE(2023,13,1))+SUMIFS('2025'!$O$10:$O$112,'2025'!$P$10:$P$112,">="&DATE(2023,12,1),'2025'!$P$10:$P$112,"<"&DATE(2023,13,1))+SUMIFS('2025'!$R$10:$R$112,'2025'!$S$10:$S$112,">="&DATE(2023,12,1),'2025'!$S$10:$S$112,"<"&DATE(2023,13,1))+SUMIFS('2025'!$U$10:$U$112,'2025'!$V$10:$V$112,">="&DATE(2023,12,1),'2025'!$V$10:$V$112,"<"&DATE(2023,13,1))+SUMIFS('2024'!$I$10:$I$108,'2024'!$J$10:$J$108,">="&DATE(2023,12,1),'2024'!$J$10:$J$108,"<"&DATE(2023,13,1))+SUMIFS('2024'!$L$10:$L$108,'2024'!$M$10:$M$108,">="&DATE(2023,12,1),'2024'!$M$10:$M$108,"<"&DATE(2023,13,1))+SUMIFS('2024'!$O$10:$O$108,'2024'!$P$10:$P$108,">="&DATE(2023,12,1),'2024'!$P$10:$P$108,"<"&DATE(2023,13,1))+SUMIFS('2024'!$R$10:$R$108,'2024'!$S$10:$S$108,">="&DATE(2023,12,1),'2024'!$S$10:$S$108,"<"&DATE(2023,13,1))+SUMIFS('2024'!$U$10:$U$108,'2024'!$V$10:$V$108,">="&DATE(2023,12,1),'2024'!$V$10:$V$108,"<"&DATE(2023,13,1))+SUMIFS('2023'!$I$10:$I$127,'2023'!$J$10:$J$127,">="&DATE(2023,12,1),'2023'!$J$10:$J$127,"<"&DATE(2023,13,1))+SUMIFS('2023'!$L$10:$L$127,'2023'!$M$10:$M$127,">="&DATE(2023,12,1),'2023'!$M$10:$M$127,"<"&DATE(2023,13,1))+SUMIFS('2023'!$O$10:$O$127,'2023'!$P$10:$P$127,">="&DATE(2023,12,1),'2023'!$P$10:$P$127,"<"&DATE(2023,13,1))+SUMIFS('2023'!$R$10:$R$127,'2023'!$S$10:$S$127,">="&DATE(2023,12,1),'2023'!$S$10:$S$127,"<"&DATE(2023,13,1))+SUMIFS('2023'!$U$10:$U$127,'2023'!$V$10:$V$127,">="&DATE(2023,12,1),'2023'!$V$10:$V$127,"<"&DATE(2023,13,1)),2) | C19: =ROUND(SUMIFS('2026'!$I$10:$I$107,'2026'!$J$10:$J$107,">="&DATE(2024,12,1),'2026'!$J$10:$J$107,"<"&DATE(2024,13,1))+SUMIFS('2026'!$L$10:$L$107,'2026'!$M$10:$M$107,">="&DATE(2024,12,1),'2026'!$M$10:$M$107,"<"&DATE(2024,13,1))+SUMIFS('2026'!$O$10:$O$107,'2026'!$P$10:$P$107,">="&DATE(2024,12,1),'2026'!$P$10:$P$107,"<"&DATE(2024,13,1))+SUMIFS('2026'!$R$10:$R$107,'2026'!$S$10:$S$107,">="&DATE(2024,12,1),'2026'!$S$10:$S$107,"<"&DATE(2024,13,1))+SUMIFS('2026'!$U$10:$U$107,'2026'!$V$10:$V$107,">="&DATE(2024,12,1),'2026'!$V$10:$V$107,"<"&DATE(2024,13,1))+SUMIFS('2025'!$I$10:$I$112,'2025'!$J$10:$J$112,">="&DATE(2024,12,1),'2025'!$J$10:$J$112,"<"&DATE(2024,13,1))+SUMIFS('2025'!$L$10:$L$112,'2025'!$M$10:$M$112,">="&DATE(2024,12,1),'2025'!$M$10:$M$112,"<"&DATE(2024,13,1))+SUMIFS('2025'!$O$10:$O$112,'2025'!$P$10:$P$112,">="&DATE(2024,12,1),'2025'!$P$10:$P$112,"<"&DATE(2024,13,1))+SUMIFS('2025'!$R$10:$R$112,'2025'!$S$10:$S$112,">="&DATE(2024,12,1),'2025'!$S$10:$S$112,"<"&DATE(2024,13,1))+SUMIFS('2025'!$U$10:$U$112,'2025'!$V$10:$V$112,">="&DATE(2024,12,1),'2025'!$V$10:$V$112,"<"&DATE(2024,13,1))+SUMIFS('2024'!$I$10:$I$108,'2024'!$J$10:$J$108,">="&DATE(2024,12,1),'2024'!$J$10:$J$108,"<"&DATE(2024,13,1))+SUMIFS('2024'!$L$10:$L$108,'2024'!$M$10:$M$108,">="&DATE(2024,12,1),'2024'!$M$10:$M$108,"<"&DATE(2024,13,1))+SUMIFS('2024'!$O$10:$O$108,'2024'!$P$10:$P$108,">="&DATE(2024,12,1),'2024'!$P$10:$P$108,"<"&DATE(2024,13,1))+SUMIFS('2024'!$R$10:$R$108,'2024'!$S$10:$S$108,">="&DATE(2024,12,1),'2024'!$S$10:$S$108,"<"&DATE(2024,13,1))+SUMIFS('2024'!$U$10:$U$108,'2024'!$V$10:$V$108,">="&DATE(2024,12,1),'2024'!$V$10:$V$108,"<"&DATE(2024,13,1))+SUMIFS('2023'!$I$10:$I$127,'2023'!$J$10:$J$127,">="&DATE(2024,12,1),'2023'!$J$10:$J$127,"<"&DATE(2024,13,1))+SUMIFS('2023'!$L$10:$L$127,'2023'!$M$10:$M$127,">="&DATE(2024,12,1),'2023'!$M$10:$M$127,"<"&DATE(2024,13,1))+SUMIFS('2023'!$O$10:$O$127,'2023'!$P$10:$P$127,">="&DATE(2024,12,1),'2023'!$P$10:$P$127,"<"&DATE(2024,13,1))+SUMIFS('2023'!$R$10:$R$127,'2023'!$S$10:$S$127,">="&DATE(2024,12,1),'2023'!$S$10:$S$127,"<"&DATE(2024,13,1))+SUMIFS('2023'!$U$10:$U$127,'2023'!$V$10:$V$127,">="&DATE(2024,12,1),'2023'!$V$10:$V$127,"<"&DATE(2024,13,1)),2) | D19: =ROUND(SUMIFS('2026'!$I$10:$I$107,'2026'!$J$10:$J$107,">="&DATE(2025,12,1),'2026'!$J$10:$J$107,"<"&DATE(2025,13,1))+SUMIFS('2026'!$L$10:$L$107,'2026'!$M$10:$M$107,">="&DATE(2025,12,1),'2026'!$M$10:$M$107,"<"&DATE(2025,13,1))+SUMIFS('2026'!$O$10:$O$107,'2026'!$P$10:$P$107,">="&DATE(2025,12,1),'2026'!$P$10:$P$107,"<"&DATE(2025,13,1))+SUMIFS('2026'!$R$10:$R$107,'2026'!$S$10:$S$107,">="&DATE(2025,12,1),'2026'!$S$10:$S$107,"<"&DATE(2025,13,1))+SUMIFS('2026'!$U$10:$U$107,'2026'!$V$10:$V$107,">="&DATE(2025,12,1),'2026'!$V$10:$V$107,"<"&DATE(2025,13,1))+SUMIFS('2025'!$I$10:$I$112,'2025'!$J$10:$J$112,">="&DATE(2025,12,1),'2025'!$J$10:$J$112,"<"&DATE(2025,13,1))+SUMIFS('2025'!$L$10:$L$112,'2025'!$M$10:$M$112,">="&DATE(2025,12,1),'2025'!$M$10:$M$112,"<"&DATE(2025,13,1))+SUMIFS('2025'!$O$10:$O$112,'2025'!$P$10:$P$112,">="&DATE(2025,12,1),'2025'!$P$10:$P$112,"<"&DATE(2025,13,1))+SUMIFS('2025'!$R$10:$R$112,'2025'!$S$10:$S$112,">="&DATE(2025,12,1),'2025'!$S$10:$S$112,"<"&DATE(2025,13,1))+SUMIFS('2025'!$U$10:$U$112,'2025'!$V$10:$V$112,">="&DATE(2025,12,1),'2025'!$V$10:$V$112,"<"&DATE(2025,13,1))+SUMIFS('2024'!$I$10:$I$108,'2024'!$J$10:$J$108,">="&DATE(2025,12,1),'2024'!$J$10:$J$108,"<"&DATE(2025,13,1))+SUMIFS('2024'!$L$10:$L$108,'2024'!$M$10:$M$108,">="&DATE(2025,12,1),'2024'!$M$10:$M$108,"<"&DATE(2025,13,1))+SUMIFS('2024'!$O$10:$O$108,'2024'!$P$10:$P$108,">="&DATE(2025,12,1),'2024'!$P$10:$P$108,"<"&DATE(2025,13,1))+SUMIFS('2024'!$R$10:$R$108,'2024'!$S$10:$S$108,">="&DATE(2025,12,1),'2024'!$S$10:$S$108,"<"&DATE(2025,13,1))+SUMIFS('2024'!$U$10:$U$108,'2024'!$V$10:$V$108,">="&DATE(2025,12,1),'2024'!$V$10:$V$108,"<"&DATE(2025,13,1))+SUMIFS('2023'!$I$10:$I$127,'2023'!$J$10:$J$127,">="&DATE(2025,12,1),'2023'!$J$10:$J$127,"<"&DATE(2025,13,1))+SUMIFS('2023'!$L$10:$L$127,'2023'!$M$10:$M$127,">="&DATE(2025,12,1),'2023'!$M$10:$M$127,"<"&DATE(2025,13,1))+SUMIFS('2023'!$O$10:$O$127,'2023'!$P$10:$P$127,">="&DATE(2025,12,1),'2023'!$P$10:$P$127,"<"&DATE(2025,13,1))+SUMIFS('2023'!$R$10:$R$127,'2023'!$S$10:$S$127,">="&DATE(2025,12,1),'2023'!$S$10:$S$127,"<"&DATE(2025,13,1))+SUMIFS('2023'!$U$10:$U$127,'2023'!$V$10:$V$127,">="&DATE(2025,12,1),'2023'!$V$10:$V$127,"<"&DATE(2025,13,1)),2) | E19: =ROUND(SUMIFS('2026'!$I$10:$I$107,'2026'!$J$10:$J$107,">="&DATE(2026,12,1),'2026'!$J$10:$J$107,"<"&DATE(2026,13,1))+SUMIFS('2026'!$L$10:$L$107,'2026'!$M$10:$M$107,">="&DATE(2026,12,1),'2026'!$M$10:$M$107,"<"&DATE(2026,13,1))+SUMIFS('2026'!$O$10:$O$107,'2026'!$P$10:$P$107,">="&DATE(2026,12,1),'2026'!$P$10:$P$107,"<"&DATE(2026,13,1))+SUMIFS('2026'!$R$10:$R$107,'2026'!$S$10:$S$107,">="&DATE(2026,12,1),'2026'!$S$10:$S$107,"<"&DATE(2026,13,1))+SUMIFS('2026'!$U$10:$U$107,'2026'!$V$10:$V$107,">="&DATE(2026,12,1),'2026'!$V$10:$V$107,"<"&DATE(2026,13,1))+SUMIFS('2025'!$I$10:$I$112,'2025'!$J$10:$J$112,">="&DATE(2026,12,1),'2025'!$J$10:$J$112,"<"&DATE(2026,13,1))+SUMIFS('2025'!$L$10:$L$112,'2025'!$M$10:$M$112,">="&DATE(2026,12,1),'2025'!$M$10:$M$112,"<"&DATE(2026,13,1))+SUMIFS('2025'!$O$10:$O$112,'2025'!$P$10:$P$112,">="&DATE(2026,12,1),'2025'!$P$10:$P$112,"<"&DATE(2026,13,1))+SUMIFS('2025'!$R$10:$R$112,'2025'!$S$10:$S$112,">="&DATE(2026,12,1),'2025'!$S$10:$S$112,"<"&DATE(2026,13,1))+SUMIFS('2025'!$U$10:$U$112,'2025'!$V$10:$V$112,">="&DATE(2026,12,1),'2025'!$V$10:$V$112,"<"&DATE(2026,13,1))+SUMIFS('2024'!$I$10:$I$108,'2024'!$J$10:$J$108,">="&DATE(2026,12,1),'2024'!$J$10:$J$108,"<"&DATE(2026,13,1))+SUMIFS('2024'!$L$10:$L$108,'2024'!$M$10:$M$108,">="&DATE(2026,12,1),'2024'!$M$10:$M$108,"<"&DATE(2026,13,1))+SUMIFS('2024'!$O$10:$O$108,'2024'!$P$10:$P$108,">="&DATE(2026,12,1),'2024'!$P$10:$P$108,"<"&DATE(2026,13,1))+SUMIFS('2024'!$R$10:$R$108,'2024'!$S$10:$S$108,">="&DATE(2026,12,1),'2024'!$S$10:$S$108,"<"&DATE(2026,13,1))+SUMIFS('2024'!$U$10:$U$108,'2024'!$V$10:$V$108,">="&DATE(2026,12,1),'2024'!$V$10:$V$108,"<"&DATE(2026,13,1))+SUMIFS('2023'!$I$10:$I$127,'2023'!$J$10:$J$127,">="&DATE(2026,12,1),'2023'!$J$10:$J$127,"<"&DATE(2026,13,1))+SUMIFS('2023'!$L$10:$L$127,'2023'!$M$10:$M$127,">="&DATE(2026,12,1),'2023'!$M$10:$M$127,"<"&DATE(2026,13,1))+SUMIFS('2023'!$O$10:$O$127,'2023'!$P$10:$P$127,">="&DATE(2026,12,1),'2023'!$P$10:$P$127,"<"&DATE(2026,13,1))+SUMIFS('2023'!$R$10:$R$127,'2023'!$S$10:$S$127,">="&DATE(2026,12,1),'2023'!$S$10:$S$127,"<"&DATE(2026,13,1))+SUMIFS('2023'!$U$10:$U$127,'2023'!$V$10:$V$127,">="&DATE(2026,12,1),'2023'!$V$10:$V$127,"<"&DATE(2026,13,1)),2) | F19: =ROUND(AVERAGE($B19:$D19),0) | G19: =IF(SUM($F$8:$F$19)=0,"",$F19/SUM($F$8:$F$19))
A20: TOTAL | B20: =ROUND(SUM(B$8:B$19),0) | C20: =ROUND(SUM(C$8:C$19),0) | D20: =ROUND(SUM(D$8:D$19),0) | E20: =ROUND(SUM(E$8:E$19),0) | F20: =ROUND(SUM(F$8:F$19),0)
A22: PADRÃO SAZONAL DE VENDAS vendas pela data do contrato · índice = média do mês ÷ média geral
A23: Mês | B23: 2023 | C23: 2024 | D23: 2025 | E23: 2026 | F23: Média 23–25 | G23: Índice | H23: Dispersão | I23: Classificação
A24: Janeiro | B24: ='2023'!$C$26 | C24: ='2024'!$C$10 | D24: ='2025'!$C$10 | E24: ='2026'!$C$10 | F24: =ROUND(AVERAGE($B24:$D24),0) | G24: =IF($F$36=0,"",$F24/($F$36/12)) | H24: =IF(OR($F24=0,COUNT($B24:$D24)<2),"",ROUND(STDEV($B24:$D24)/$F24,2)) | I24: =IF($G24="","",IF($H24>0.7,"Irregular",IF($G24>=1.2,"Forte",IF($G24<=0.8,"Fraco","Normal"))))
A25: Fevereiro | B25: ='2023'!$C$33 | C25: ='2024'!$C$21 | D25: ='2025'!$C$20 | E25: ='2026'!$C$17 | F25: =ROUND(AVERAGE($B25:$D25),0) | G25: =IF($F$36=0,"",$F25/($F$36/12)) | H25: =IF(OR($F25=0,COUNT($B25:$D25)<2),"",ROUND(STDEV($B25:$D25)/$F25,2)) | I25: =IF($G25="","",IF($H25>0.7,"Irregular",IF($G25>=1.2,"Forte",IF($G25<=0.8,"Fraco","Normal"))))
A26: Março | B26: ='2023'!$C$37 | C26: ='2024'!$C$35 | D26: ='2025'!$C$29 | E26: ='2026'!$C$27 | F26: =ROUND(AVERAGE($B26:$D26),0) | G26: =IF($F$36=0,"",$F26/($F$36/12)) | H26: =IF(OR($F26=0,COUNT($B26:$D26)<2),"",ROUND(STDEV($B26:$D26)/$F26,2)) | I26: =IF($G26="","",IF($H26>0.7,"Irregular",IF($G26>=1.2,"Forte",IF($G26<=0.8,"Fraco","Normal"))))
A27: Abril | B27: ='2023'!$C$49 | C27: ='2024'!$C$43 | D27: ='2025'!$C$40 | E27: ='2026'!$C$38 | F27: =ROUND(AVERAGE($B27:$D27),0) | G27: =IF($F$36=0,"",$F27/($F$36/12)) | H27: =IF(OR($F27=0,COUNT($B27:$D27)<2),"",ROUND(STDEV($B27:$D27)/$F27,2)) | I27: =IF($G27="","",IF($H27>0.7,"Irregular",IF($G27>=1.2,"Forte",IF($G27<=0.8,"Fraco","Normal"))))
A28: Maio | B28: ='2023'!$C$55 | C28: ='2024'!$C$49 | D28: ='2025'!$C$51 | E28: ='2026'!$C$49 | F28: =ROUND(AVERAGE($B28:$D28),0) | G28: =IF($F$36=0,"",$F28/($F$36/12)) | H28: =IF(OR($F28=0,COUNT($B28:$D28)<2),"",ROUND(STDEV($B28:$D28)/$F28,2)) | I28: =IF($G28="","",IF($H28>0.7,"Irregular",IF($G28>=1.2,"Forte",IF($G28<=0.8,"Fraco","Normal"))))
A29: Junho | B29: ='2023'!$C$63 | C29: ='2024'!$C$57 | D29: ='2025'!$C$58 | E29: ='2026'!$C$58 | F29: =ROUND(AVERAGE($B29:$D29),0) | G29: =IF($F$36=0,"",$F29/($F$36/12)) | H29: =IF(OR($F29=0,COUNT($B29:$D29)<2),"",ROUND(STDEV($B29:$D29)/$F29,2)) | I29: =IF($G29="","",IF($H29>0.7,"Irregular",IF($G29>=1.2,"Forte",IF($G29<=0.8,"Fraco","Normal"))))
A30: Julho | B30: ='2023'!$C$75 | C30: ='2024'!$C$63 | D30: ='2025'!$C$69 | E30: ='2026'!$C$69 | F30: =ROUND(AVERAGE($B30:$D30),0) | G30: =IF($F$36=0,"",$F30/($F$36/12)) | H30: =IF(OR($F30=0,COUNT($B30:$D30)<2),"",ROUND(STDEV($B30:$D30)/$F30,2)) | I30: =IF($G30="","",IF($H30>0.7,"Irregular",IF($G30>=1.2,"Forte",IF($G30<=0.8,"Fraco","Normal"))))
A31: Agosto | B31: ='2023'!$C$81 | C31: ='2024'!$C$69 | D31: ='2025'!$C$78 | E31: ='2026'!$C$80 | F31: =ROUND(AVERAGE($B31:$D31),0) | G31: =IF($F$36=0,"",$F31/($F$36/12)) | H31: =IF(OR($F31=0,COUNT($B31:$D31)<2),"",ROUND(STDEV($B31:$D31)/$F31,2)) | I31: =IF($G31="","",IF($H31>0.7,"Irregular",IF($G31>=1.2,"Forte",IF($G31<=0.8,"Fraco","Normal"))))
A32: Setembro | B32: ='2023'!$C$90 | C32: ='2024'!$C$76 | D32: ='2025'!$C$83 | E32: ='2026'!$C$88 | F32: =ROUND(AVERAGE($B32:$D32),0) | G32: =IF($F$36=0,"",$F32/($F$36/12)) | H32: =IF(OR($F32=0,COUNT($B32:$D32)<2),"",ROUND(STDEV($B32:$D32)/$F32,2)) | I32: =IF($G32="","",IF($H32>0.7,"Irregular",IF($G32>=1.2,"Forte",IF($G32<=0.8,"Fraco","Normal"))))
A33: Outubro | B33: ='2023'!$C$100 | C33: ='2024'!$C$84 | D33: ='2025'!$C$95 | E33: ='2026'!$C$93 | F33: =ROUND(AVERAGE($B33:$D33),0) | G33: =IF($F$36=0,"",$F33/($F$36/12)) | H33: =IF(OR($F33=0,COUNT($B33:$D33)<2),"",ROUND(STDEV($B33:$D33)/$F33,2)) | I33: =IF($G33="","",IF($H33>0.7,"Irregular",IF($G33>=1.2,"Forte",IF($G33<=0.8,"Fraco","Normal"))))
A34: Novembro | B34: ='2023'!$C$112 | C34: ='2024'!$C$91 | D34: ='2025'!$C$100 | E34: ='2026'!$C$98 | F34: =ROUND(AVERAGE($B34:$D34),0) | G34: =IF($F$36=0,"",$F34/($F$36/12)) | H34: =IF(OR($F34=0,COUNT($B34:$D34)<2),"",ROUND(STDEV($B34:$D34)/$F34,2)) | I34: =IF($G34="","",IF($H34>0.7,"Irregular",IF($G34>=1.2,"Forte",IF($G34<=0.8,"Fraco","Normal"))))
A35: Dezembro | B35: ='2023'!$C$119 | C35: ='2024'!$C$99 | D35: ='2025'!$C$106 | E35: ='2026'!$C$103 | F35: =ROUND(AVERAGE($B35:$D35),0) | G35: =IF($F$36=0,"",$F35/($F$36/12)) | H35: =IF(OR($F35=0,COUNT($B35:$D35)<2),"",ROUND(STDEV($B35:$D35)/$F35,2)) | I35: =IF($G35="","",IF($H35>0.7,"Irregular",IF($G35>=1.2,"Forte",IF($G35<=0.8,"Fraco","Normal"))))
A36: TOTAL / MÉDIA | B36: =ROUND(SUM(B$24:B$35),0) | C36: =ROUND(SUM(C$24:C$35),0) | D36: =ROUND(SUM(D$24:D$35),0) | E36: =ROUND(SUM(E$24:E$35),0) | F36: =ROUND(SUM(F$24:F$35),0)
A38: CONCENTRAÇÃO DA CARTEIRA o quanto o ano depende de poucos projetos
A39: Ano | B39: Projetos | C39: Vendido | D39: Ticket médio | E39: Maior projeto | F39: % do maior | G39: Top 3 | H39: % do top 3 | I39: Leitura
A40: 2026 | B40: =COUNT('2026'!$Y$10:$Y$107) | C40: ='2026'!$A$7 | D40: =IF(COUNT('2026'!$Y$10:$Y$107)=0,"",ROUND('2026'!$A$7/COUNT('2026'!$Y$10:$Y$107),0)) | E40: =IF(COUNT('2026'!$Y$10:$Y$107)=0,"",MAX('2026'!$Y$10:$Y$107)) | F40: =IF(OR(COUNT('2026'!$Y$10:$Y$107)=0,'2026'!$A$7=0),"",MAX('2026'!$Y$10:$Y$107)/'2026'!$A$7) | G40: =IF(COUNT('2026'!$Y$10:$Y$107)<3,"",ROUND(LARGE('2026'!$Y$10:$Y$107,1)+LARGE('2026'!$Y$10:$Y$107,2)+LARGE('2026'!$Y$10:$Y$107,3),0)) | H40: =IF(OR($G40="",'2026'!$A$7=0),"",$G40/'2026'!$A$7) | I40: =IF($H40="","",IF($H40>=0.45,"Muito concentrado",IF($H40>=0.3,"Concentrado","Distribuído")))
A41: 2025 | B41: =COUNT('2025'!$Y$10:$Y$112) | C41: ='2025'!$A$7 | D41: =IF(COUNT('2025'!$Y$10:$Y$112)=0,"",ROUND('2025'!$A$7/COUNT('2025'!$Y$10:$Y$112),0)) | E41: =IF(COUNT('2025'!$Y$10:$Y$112)=0,"",MAX('2025'!$Y$10:$Y$112)) | F41: =IF(OR(COUNT('2025'!$Y$10:$Y$112)=0,'2025'!$A$7=0),"",MAX('2025'!$Y$10:$Y$112)/'2025'!$A$7) | G41: =IF(COUNT('2025'!$Y$10:$Y$112)<3,"",ROUND(LARGE('2025'!$Y$10:$Y$112,1)+LARGE('2025'!$Y$10:$Y$112,2)+LARGE('2025'!$Y$10:$Y$112,3),0)) | H41: =IF(OR($G41="",'2025'!$A$7=0),"",$G41/'2025'!$A$7) | I41: =IF($H41="","",IF($H41>=0.45,"Muito concentrado",IF($H41>=0.3,"Concentrado","Distribuído")))
A42: 2024 | B42: =COUNT('2024'!$Y$10:$Y$108) | C42: ='2024'!$A$7 | D42: =IF(COUNT('2024'!$Y$10:$Y$108)=0,"",ROUND('2024'!$A$7/COUNT('2024'!$Y$10:$Y$108),0)) | E42: =IF(COUNT('2024'!$Y$10:$Y$108)=0,"",MAX('2024'!$Y$10:$Y$108)) | F42: =IF(OR(COUNT('2024'!$Y$10:$Y$108)=0,'2024'!$A$7=0),"",MAX('2024'!$Y$10:$Y$108)/'2024'!$A$7) | G42: =IF(COUNT('2024'!$Y$10:$Y$108)<3,"",ROUND(LARGE('2024'!$Y$10:$Y$108,1)+LARGE('2024'!$Y$10:$Y$108,2)+LARGE('2024'!$Y$10:$Y$108,3),0)) | H42: =IF(OR($G42="",'2024'!$A$7=0),"",$G42/'2024'!$A$7) | I42: =IF($H42="","",IF($H42>=0.45,"Muito concentrado",IF($H42>=0.3,"Concentrado","Distribuído")))
A43: 2023 | B43: =COUNT('2023'!$Y$26:$Y$127) | C43: ='2023'!$A$7 | D43: =IF(COUNT('2023'!$Y$26:$Y$127)=0,"",ROUND('2023'!$A$7/COUNT('2023'!$Y$26:$Y$127),0)) | E43: =IF(COUNT('2023'!$Y$26:$Y$127)=0,"",MAX('2023'!$Y$26:$Y$127)) | F43: =IF(OR(COUNT('2023'!$Y$26:$Y$127)=0,'2023'!$A$7=0),"",MAX('2023'!$Y$26:$Y$127)/'2023'!$A$7) | G43: =IF(COUNT('2023'!$Y$26:$Y$127)<3,"",ROUND(LARGE('2023'!$Y$26:$Y$127,1)+LARGE('2023'!$Y$26:$Y$127,2)+LARGE('2023'!$Y$26:$Y$127,3),0)) | H43: =IF(OR($G43="",'2023'!$A$7=0),"",$G43/'2023'!$A$7) | I43: =IF($H43="","",IF($H43>=0.45,"Muito concentrado",IF($H43>=0.3,"Concentrado","Distribuído")))
A46: LEITURA DO PADRÃO
A47: ="Maior índice de vendas: "&INDEX($A$24:$A$35,MATCH(MAX($G$24:$G$35),$G$24:$G$35,0))&" ("&TEXT(MAX($G$24:$G$35),"0.00")&", classificado como "&INDEX($I$24:$I$35,MATCH(MAX($G$24:$G$35),$G$24:$G$35,0))&"). Menor índice: "&INDEX($A$24:$A$35,MATCH(MIN($G$24:$G$35),$G$24:$G$35,0))&" ("&TEXT(MIN($G$24:$G$35),"0.00")&")."
A48: ="O mês de padrão MAIS CONFIÁVEL é "&INDEX($A$24:$A$35,MATCH(MIN($H$24:$H$35),$H$24:$H$35,0))&" — dispersão de apenas "&TEXT(MIN($H$24:$H$35),"0.00")&" entre os três anos, com índice "&TEXT(INDEX($G$24:$G$35,MATCH(MIN($H$24:$H$35),$H$24:$H$35,0)),"0.00")&". Esse é o único tipo de mês em que o índice vale como referência de planejamento."
A49: ="Dos 12 meses, "&COUNTIF($I$24:$I$35,"Irregular")&" estão marcados como Irregular e "&COUNTIF($I$24:$I$35,"Normal")&" como Normal. Índice alto com dispersão alta não é sazonalidade: é um projeto grande que caiu naquele mês em um dos anos."
A50: ="Caixa: o mês que historicamente mais traz dinheiro é "&INDEX($A$8:$A$19,MATCH(MAX($G$8:$G$19),$G$8:$G$19,0))&", com "&TEXT(MAX($G$8:$G$19),"0%")&" do caixa do ano. Repare que o mês de maior VENDA e o de maior CAIXA não coincidem — é o descasamento entre vender e receber."
A52: Ressalvas honestas sobre a sazonalidade: (1) a base tem três anos fechados — 2023, 2024 e 2025 — e três pontos por mês é pouco para afirmar padrão; trate o índice como sinal, não como previsão. (2) A operação começou em março de 2023, então janeiro e fevereiro daquele ano puxam a média para baixo. (3) Setembro de 2025 sozinho (R$ 572 mil, dois mega-projetos) distorce o mês inteiro — é por isso que a coluna Dispersão existe: quando ela passa de 0,70, a planilha marca o mês como Irregular. (4) 2026 aparece nas tabelas mas fica FORA do cálculo da média, porque o ano não fechou.

Sheet 2026
A1: VALVIC MARCENARIA
A2: Vargas Decor Ltda · CNPJ 17.269.304/0001-51 · Belo Horizonte / MG
A3: CONTROLE DE PAGAMENTOS · 2026
A4: Uma linha por projeto · fundo creme = você preenche · fundo cinza = calculado · Recebido, Saldo, % e Situação saem sozinhos
A6: VENDIDO NO ANO | D6: RECEBIDO | F6: A RECEBER | H6: % RECEBIDO | I6: META DO ANO | L6: % DA META | O6: FALTA PARA A META | R6: CONFERÊNCIA
A7: =ROUND(SUMPRODUCT((COUNTIF(Listas!$A$2:$A$15,$A$10:$A$106)=0)*$C$10:$C$106),2) | D7: =ROUND(SUM($I$10:$I$106,$L$10:$L$106,$O$10:$O$106,$R$10:$R$106,$U$10:$U$106),2) | F7: =ROUND($A$7-$D$7,2) | H7: =IF($A$7=0,"",$D$7/$A$7) | I7: 3000000 | L7: =IF(OR($I$7="",$I$7=0),"",$A$7/$I$7) | O7: =IF(OR($I$7="",$I$7=0),"",MAX(0,$I$7-$A$7)) | R7: =IF(ROUND(($C$10+$C$17+$C$27+$C$38+$C$49+$C$58+$C$69+$C$80+$C$88+$C$93+$C$98+$C$103)-$A$7,2)=0,"OK · os meses somam igual às linhas","DIVERGE em "&TEXT(($C$10+$C$17+$C$27+$C$38+$C$49+$C$58+$C$69+$C$80+$C$88+$C$93+$C$98+$C$103)-$A$7,"R$ #,##0.00")& " — confira se alguma linha ficou fora de um bloco de mês")
A9: Cliente | B9: Projeto | C9: Investimento | D9: Forma de pagamento | E9: Recebido | F9: Saldo a receber | G9: % recebido | H9: Situação | I9: 1º Pagt. (R$) | J9: Data | K9: Descrição | L9: 2º Pagt. (R$) | M9: Data | N9: Descrição | O9: 3º Pagt. (R$) | P9: Data | Q9: Descrição | R9: 4º Pagt. (R$) | S9: Data | T9: Descrição | U9: 5º Pagt. (R$) | V9: Data | W9: Descrição | X9: aux | Y9: aux2
A10: Janeiro | C10: =SUM(C11:C15) | E10: =SUM(E11:E15) | F10: =SUM(F11:F15) | G10: =IF(OR(C10="",C10=0),"",E10/C10) | H10: =COUNT(C11:C15)&" projeto(s)"
A11: Luiz | B11: casa completa | C11: 87680 | D11: 10 vezes sem juros no cartao | E11: =IF($C11="","",ROUND(SUM(I11,L11,O11,R11,U11),2)) | F11: =IF($C11="","",ROUND($C11-$E11,2)) | G11: =IF(OR($C11="",$C11=0),"",$E11/$C11) | H11: =IF($C11="","",IF($E11=0,"A receber",IF(ROUND($F11,2)=0,"Quitado",IF($F11<0,"Recebido a mais","Parcial")))) | I11: 87680 | J11: 46036 | K11: cartao | X11: =IF($C11="","",$F11) | Y11: =IF($C11="","",$C11)
A12: Raquel | B12: Quarto | C12: 22600 | D12: 50% entrada + 5 vezes no cartao | E12: =IF($C12="","",ROUND(SUM(I12,L12,O12,R12,U12),2)) | F12: =IF($C12="","",ROUND($C12-$E12,2)) | G12: =IF(OR($C12="",$C12=0),"",$E12/$C12) | H12: =IF($C12="","",IF($E12=0,"A receber",IF(ROUND($F12,2)=0,"Quitado",IF($F12<0,"Recebido a mais","Parcial")))) | I12: 11300 | J12: 46048 | K12: pix | L12: 11300 | M12: 46129 | N12: pix | X12: =IF($C12="","",$F12) | Y12: =IF($C12="","",$C12)
E13: =IF($C13="","",ROUND(SUM(I13,L13,O13,R13,U13),2)) | F13: =IF($C13="","",ROUND($C13-$E13,2)) | G13: =IF(OR($C13="",$C13=0),"",$E13/$C13) | H13: =IF($C13="","",IF($E13=0,"A receber",IF(ROUND($F13,2)=0,"Quitado",IF($F13<0,"Recebido a mais","Parcial")))) | X13: =IF($C13="","",$F13) | Y13: =IF($C13="","",$C13)
E14: =IF($C14="","",ROUND(SUM(I14,L14,O14,R14,U14),2)) | F14: =IF($C14="","",ROUND($C14-$E14,2)) | G14: =IF(OR($C14="",$C14=0),"",$E14/$C14) | H14: =IF($C14="","",IF($E14=0,"A receber",IF(ROUND($F14,2)=0,"Quitado",IF($F14<0,"Recebido a mais","Parcial")))) | X14: =IF($C14="","",$F14) | Y14: =IF($C14="","",$C14)
E15: =IF($C15="","",ROUND(SUM(I15,L15,O15,R15,U15),2)) | F15: =IF($C15="","",ROUND($C15-$E15,2)) | G15: =IF(OR($C15="",$C15=0),"",$E15/$C15) | H15: =IF($C15="","",IF($E15=0,"A receber",IF(ROUND($F15,2)=0,"Quitado",IF($F15<0,"Recebido a mais","Parcial")))) | X15: =IF($C15="","",$F15) | Y15: =IF($C15="","",$C15)
A17: Fevereiro | C17: =SUM(C18:C25) | E17: =SUM(E18:E25) | F17: =SUM(F18:F25) | G17: =IF(OR(C17="",C17=0),"",E17/C17) | H17: =COUNT(C18:C25)&" projeto(s)"
A18: Matheus | B18: Painel | C18: 9180 | D18: 50% + 50% | E18: =IF($C18="","",ROUND(SUM(I18,L18,O18,R18,U18),2)) | F18: =IF($C18="","",ROUND($C18-$E18,2)) | G18: =IF(OR($C18="",$C18=0),"",$E18/$C18) | H18: =IF($C18="","",IF($E18=0,"A receber",IF(ROUND($F18,2)=0,"Quitado",IF($F18<0,"Recebido a mais","Parcial")))) | I18: 4590 | J18: 46058 | K18: pix | L18: 4590 | M18: 46090 | N18: pix | X18: =IF($C18="","",$F18) | Y18: =IF($C18="","",$C18)
A19: Bibiane | B19: Casa completa | C19: 68000 | D19: 30 mil entrada + restante no final | E19: =IF($C19="","",ROUND(SUM(I19,L19,O19,R19,U19),2)) | F19: =IF($C19="","",ROUND($C19-$E19,2)) | G19: =IF(OR($C19="",$C19=0),"",$E19/$C19) | H19: =IF($C19="","",IF($E19=0,"A receber",IF(ROUND($F19,2)=0,"Quitado",IF($F19<0,"Recebido a mais","Parcial")))) | I19: 30000 | J19: 46062 | K19: pix | L19: 10000 | M19: 46099 | N19: pix | O19: 10000 | P19: 46106 | Q19: pix | R19: 18000 | S19: 46140 | T19: pix | X19: =IF($C19="","",$F19) | Y19: =IF($C19="","",$C19)
A20: Bruna | B20: Quarto filha | C20: 10150 | D20: 50% + 10vezes no cartao | E20: =IF($C20="","",ROUND(SUM(I20,L20,O20,R20,U20),2)) | F20: =IF($C20="","",ROUND($C20-$E20,2)) | G20: =IF(OR($C20="",$C20=0),"",$E20/$C20) | H20: =IF($C20="","",IF($E20=0,"A receber",IF(ROUND($F20,2)=0,"Quitado",IF($F20<0,"Recebido a mais","Parcial")))) | I20: 5000 | J20: 46065 | K20: pix | L20: 5150 | M20: 46138 | N20: cartao | X20: =IF($C20="","",$F20) | Y20: =IF($C20="","",$C20)
A21: Augusto | B21: Apt | C21: 90000 | D21: Entrada 70% + final de 30% | E21: =IF($C21="","",ROUND(SUM(I21,L21,O21,R21,U21),2)) | F21: =IF($C21="","",ROUND($C21-$E21,2)) | G21: =IF(OR($C21="",$C21=0),"",$E21/$C21) | H21: =IF($C21="","",IF($E21=0,"A receber",IF(ROUND($F21,2)=0,"Quitado",IF($F21<0,"Recebido a mais","Parcial")))) | I21: 63000 | J21: 46072 | K21: pix | X21: =IF($C21="","",$F21) | Y21: =IF($C21="","",$C21)
A22: Sylvia | B22: painel e quarto filhas | C22: 24345 | D22: entrada de 30% + restante em 10 vz | E22: =IF($C22="","",ROUND(SUM(I22,L22,O22,R22,U22),2)) | F22: =IF($C22="","",ROUND($C22-$E22,2)) | G22: =IF(OR($C22="",$C22=0),"",$E22/$C22) | H22: =IF($C22="","",IF($E22=0,"A receber",IF(ROUND($F22,2)=0,"Quitado",IF($F22<0,"Recebido a mais","Parcial")))) | I22: 17045 | J22: 46084 | K22: cartao | L22: 7300 | M22: 46093 | N22: pix | X22: =IF($C22="","",$F22) | Y22: =IF($C22="","",$C22)
E23: =IF($C23="","",ROUND(SUM(I23,L23,O23,R23,U23),2)) | F23: =IF($C23="","",ROUND($C23-$E23,2)) | G23: =IF(OR($C23="",$C23=0),"",$E23/$C23) | H23: =IF($C23="","",IF($E23=0,"A receber",IF(ROUND($F23,2)=0,"Quitado",IF($F23<0,"Recebido a mais","Parcial")))) | X23: =IF($C23="","",$F23) | Y23: =IF($C23="","",$C23)
E24: =IF($C24="","",ROUND(SUM(I24,L24,O24,R24,U24),2)) | F24: =IF($C24="","",ROUND($C24-$E24,2)) | G24: =IF(OR($C24="",$C24=0),"",$E24/$C24) | H24: =IF($C24="","",IF($E24=0,"A receber",IF(ROUND($F24,2)=0,"Quitado",IF($F24<0,"Recebido a mais","Parcial")))) | X24: =IF($C24="","",$F24) | Y24: =IF($C24="","",$C24)
E25: =IF($C25="","",ROUND(SUM(I25,L25,O25,R25,U25),2)) | F25: =IF($C25="","",ROUND($C25-$E25,2)) | G25: =IF(OR($C25="",$C25=0),"",$E25/$C25) | H25: =IF($C25="","",IF($E25=0,"A receber",IF(ROUND($F25,2)=0,"Quitado",IF($F25<0,"Recebido a mais","Parcial")))) | X25: =IF($C25="","",$F25) | Y25: =IF($C25="","",$C25)
A27: Março | C27: =SUM(C28:C36) | E27: =SUM(E28:E36) | F27: =SUM(F28:F36) | G27: =IF(OR(C27="",C27=0),"",E27/C27) | H27: =COUNT(C28:C36)&" projeto(s)"
A28: Rosemary | B28: Closet | C28: 15300 | D28: 30% entrada + rest. 10x | E28: =IF($C28="","",ROUND(SUM(I28,L28,O28,R28,U28),2)) | F28: =IF($C28="","",ROUND($C28-$E28,2)) | G28: =IF(OR($C28="",$C28=0),"",$E28/$C28) | H28: =IF($C28="","",IF($E28=0,"A receber",IF(ROUND($F28,2)=0,"Quitado",IF($F28<0,"Recebido a mais","Parcial")))) | I28: 11270 | J28: 46090 | K28: cartao | L28: 4030 | M28: 46090 | N28: dinheiro/pix | X28: =IF($C28="","",$F28) | Y28: =IF($C28="","",$C28)
A29: Matheus | B29: Cozinha e lavanderia | C29: 22850 | D29: 70% + 30% | E29: =IF($C29="","",ROUND(SUM(I29,L29,O29,R29,U29),2)) | F29: =IF($C29="","",ROUND($C29-$E29,2)) | G29: =IF(OR($C29="",$C29=0),"",$E29/$C29) | H29: =IF($C29="","",IF($E29=0,"A receber",IF(ROUND($F29,2)=0,"Quitado",IF($F29<0,"Recebido a mais","Parcial")))) | I29: 16000 | J29: 46090 | K29: pix | L29: 3500 | M29: 46175 | N29: pix | O29: 3350 | P29: 46175 | X29: =IF($C29="","",$F29) | Y29: =IF($C29="","",$C29)
A30: Isaias e Nubia | B30: Painel de Tv | C30: 16900 | D30: cartao + parcelas | E30: =IF($C30="","",ROUND(SUM(I30,L30,O30,R30,U30),2)) | F30: =IF($C30="","",ROUND($C30-$E30,2)) | G30: =IF(OR($C30="",$C30=0),"",$E30/$C30) | H30: =IF($C30="","",IF($E30=0,"A receber",IF(ROUND($F30,2)=0,"Quitado",IF($F30<0,"Recebido a mais","Parcial")))) | I30: 8000 | J30: 46108 | K30: cartao | L30: 5000 | M30: 46157 | N30: pix | O30: 3900 | P30: 46179 | X30: =IF($C30="","",$F30) | Y30: =IF($C30="","",$C30)
A31: Reginaldo | B31: Escritório | C31: 14530 | D31: entrada + 4v | E31: =IF($C31="","",ROUND(SUM(I31,L31,O31,R31,U31),2)) | F31: =IF($C31="","",ROUND($C31-$E31,2)) | G31: =IF(OR($C31="",$C31=0),"",$E31/$C31) | H31: =IF($C31="","",IF($E31=0,"A receber",IF(ROUND($F31,2)=0,"Quitado",IF($F31<0,"Recebido a mais","Parcial")))) | I31: 7000 | J31: 46088 | K31: cartao | L31: 7530 | M31: 46203 | X31: =IF($C31="","",$F31) | Y31: =IF($C31="","",$C31)
A32: Marcelo Maciel | B32: consultorio | C32: 28880 | D32: 70+30 | E32: =IF($C32="","",ROUND(SUM(I32,L32,O32,R32,U32),2)) | F32: =IF($C32="","",ROUND($C32-$E32,2)) | G32: =IF(OR($C32="",$C32=0),"",$E32/$C32) | H32: =IF($C32="","",IF($E32=0,"A receber",IF(ROUND($F32,2)=0,"Quitado",IF($F32<0,"Recebido a mais","Parcial")))) | I32: 20280 | J32: 46104 | K32: pix | L32: 8600 | M32: 46189 | N32: pix | X32: =IF($C32="","",$F32) | Y32: =IF($C32="","",$C32)
A33: Maria | B33: Casa Vale dos Cristais | C33: 117738 | D33: 50+50 | E33: =IF($C33="","",ROUND(SUM(I33,L33,O33,R33,U33),2)) | F33: =IF($C33="","",ROUND($C33-$E33,2)) | G33: =IF(OR($C33="",$C33=0),"",$E33/$C33) | H33: =IF($C33="","",IF($E33=0,"A receber",IF(ROUND($F33,2)=0,"Quitado",IF($F33<0,"Recebido a mais","Parcial")))) | J33: 46112 | K33: pix | X33: =IF($C33="","",$F33) | Y33: =IF($C33="","",$C33)
E34: =IF($C34="","",ROUND(SUM(I34,L34,O34,R34,U34),2)) | F34: =IF($C34="","",ROUND($C34-$E34,2)) | G34: =IF(OR($C34="",$C34=0),"",$E34/$C34) | H34: =IF($C34="","",IF($E34=0,"A receber",IF(ROUND($F34,2)=0,"Quitado",IF($F34<0,"Recebido a mais","Parcial")))) | X34: =IF($C34="","",$F34) | Y34: =IF($C34="","",$C34)
E35: =IF($C35="","",ROUND(SUM(I35,L35,O35,R35,U35),2)) | F35: =IF($C35="","",ROUND($C35-$E35,2)) | G35: =IF(OR($C35="",$C35=0),"",$E35/$C35) | H35: =IF($C35="","",IF($E35=0,"A receber",IF(ROUND($F35,2)=0,"Quitado",IF($F35<0,"Recebido a mais","Parcial")))) | X35: =IF($C35="","",$F35) | Y35: =IF($C35="","",$C35)
E36: =IF($C36="","",ROUND(SUM(I36,L36,O36,R36,U36),2)) | F36: =IF($C36="","",ROUND($C36-$E36,2)) | G36: =IF(OR($C36="",$C36=0),"",$E36/$C36) | H36: =IF($C36="","",IF($E36=0,"A receber",IF(ROUND($F36,2)=0,"Quitado",IF($F36<0,"Recebido a mais","Parcial")))) | X36: =IF($C36="","",$F36) | Y36: =IF($C36="","",$C36)
A38: Abril | C38: =SUM(C39:C47) | E38: =SUM(E39:E47) | F38: =SUM(F39:F47) | G38: =IF(OR(C38="",C38=0),"",E38/C38) | H38: =COUNT(C39:C47)&" projeto(s)"
A39: Gisele | B39: Cozinha | C39: 20300 | D39: 50% + 50% | E39: =IF($C39="","",ROUND(SUM(I39,L39,O39,R39,U39),2)) | F39: =IF($C39="","",ROUND($C39-$E39,2)) | G39: =IF(OR($C39="",$C39=0),"",$E39/$C39) | H39: =IF($C39="","",IF($E39=0,"A receber",IF(ROUND($F39,2)=0,"Quitado",IF($F39<0,"Recebido a mais","Parcial")))) | I39: 10000 | J39: 46128 | K39: especie | L39: 10300 | M39: 46171 | N39: pix | X39: =IF($C39="","",$F39) | Y39: =IF($C39="","",$C39)
A40: Andre alphavillie | B40: casa | C40: 87000 | D40: investimento | E40: =IF($C40="","",ROUND(SUM(I40,L40,O40,R40,U40),2)) | F40: =IF($C40="","",ROUND($C40-$E40,2)) | G40: =IF(OR($C40="",$C40=0),"",$E40/$C40) | H40: =IF($C40="","",IF($E40=0,"A receber",IF(ROUND($F40,2)=0,"Quitado",IF($F40<0,"Recebido a mais","Parcial")))) | X40: =IF($C40="","",$F40) | Y40: =IF($C40="","",$C40)
A41: Yasmin | B41: cozinha | C41: 26000 | D41: 70%+30% | E41: =IF($C41="","",ROUND(SUM(I41,L41,O41,R41,U41),2)) | F41: =IF($C41="","",ROUND($C41-$E41,2)) | G41: =IF(OR($C41="",$C41=0),"",$E41/$C41) | H41: =IF($C41="","",IF($E41=0,"A receber",IF(ROUND($F41,2)=0,"Quitado",IF($F41<0,"Recebido a mais","Parcial")))) | I41: 18000 | J41: 46155 | K41: pix | X41: =IF($C41="","",$F41) | Y41: =IF($C41="","",$C41)
A42: Cristiane | B42: casa completa | C42: 94400 | E42: =IF($C42="","",ROUND(SUM(I42,L42,O42,R42,U42),2)) | F42: =IF($C42="","",ROUND($C42-$E42,2)) | G42: =IF(OR($C42="",$C42=0),"",$E42/$C42) | H42: =IF($C42="","",IF($E42=0,"A receber",IF(ROUND($F42,2)=0,"Quitado",IF($F42<0,"Recebido a mais","Parcial")))) | I42: 22500 | J42: 46147 | K42: pix | L42: 10000 | M42: 46202 | N42: pix | X42: =IF($C42="","",$F42) | Y42: =IF($C42="","",$C42)
A43: Rejane | B43: Cozinha | C43: 35600 | D43: 40%+9vz cartao | E43: =IF($C43="","",ROUND(SUM(I43,L43,O43,R43,U43),2)) | F43: =IF($C43="","",ROUND($C43-$E43,2)) | G43: =IF(OR($C43="",$C43=0),"",$E43/$C43) | H43: =IF($C43="","",IF($E43=0,"A receber",IF(ROUND($F43,2)=0,"Quitado",IF($F43<0,"Recebido a mais","Parcial")))) | I43: 14240 | J43: 46136 | K43: pix | X43: =IF($C43="","",$F43) | Y43: =IF($C43="","",$C43)
A44: Leyde | B44: Sala e banheiro | C44: 9990 | D44: 100% a vista | E44: =IF($C44="","",ROUND(SUM(I44,L44,O44,R44,U44),2)) | F44: =IF($C44="","",ROUND($C44-$E44,2)) | G44: =IF(OR($C44="",$C44=0),"",$E44/$C44) | H44: =IF($C44="","",IF($E44=0,"A receber",IF(ROUND($F44,2)=0,"Quitado",IF($F44<0,"Recebido a mais","Parcial")))) | I44: 9990 | J44: 46133 | K44: pix | X44: =IF($C44="","",$F44) | Y44: =IF($C44="","",$C44)
E45: =IF($C45="","",ROUND(SUM(I45,L45,O45,R45,U45),2)) | F45: =IF($C45="","",ROUND($C45-$E45,2)) | G45: =IF(OR($C45="",$C45=0),"",$E45/$C45) | H45: =IF($C45="","",IF($E45=0,"A receber",IF(ROUND($F45,2)=0,"Quitado",IF($F45<0,"Recebido a mais","Parcial")))) | X45: =IF($C45="","",$F45) | Y45: =IF($C45="","",$C45)
E46: =IF($C46="","",ROUND(SUM(I46,L46,O46,R46,U46),2)) | F46: =IF($C46="","",ROUND($C46-$E46,2)) | G46: =IF(OR($C46="",$C46=0),"",$E46/$C46) | H46: =IF($C46="","",IF($E46=0,"A receber",IF(ROUND($F46,2)=0,"Quitado",IF($F46<0,"Recebido a mais","Parcial")))) | X46: =IF($C46="","",$F46) | Y46: =IF($C46="","",$C46)
E47: =IF($C47="","",ROUND(SUM(I47,L47,O47,R47,U47),2)) | F47: =IF($C47="","",ROUND($C47-$E47,2)) | G47: =IF(OR($C47="",$C47=0),"",$E47/$C47) | H47: =IF($C47="","",IF($E47=0,"A receber",IF(ROUND($F47,2)=0,"Quitado",IF($F47<0,"Recebido a mais","Parcial")))) | X47: =IF($C47="","",$F47) | Y47: =IF($C47="","",$C47)
A49: Maio | C49: =SUM(C50:C56) | E49: =SUM(E50:E56) | F49: =SUM(F50:F56) | G49: =IF(OR(C49="",C49=0),"",E49/C49) | H49: =COUNT(C50:C56)&" projeto(s)"
A50: Daniel | B50: Escritorio | C50: 11200 | D50: 30% + cartao | E50: =IF($C50="","",ROUND(SUM(I50,L50,O50,R50,U50),2)) | F50: =IF($C50="","",ROUND($C50-$E50,2)) | G50: =IF(OR($C50="",$C50=0),"",$E50/$C50) | H50: =IF($C50="","",IF($E50=0,"A receber",IF(ROUND($F50,2)=0,"Quitado",IF($F50<0,"Recebido a mais","Parcial")))) | I50: 3360 | J50: 46154 | K50: pix | L50: 7840 | M50: 46155 | N50: cartao | X50: =IF($C50="","",$F50) | Y50: =IF($C50="","",$C50)
A51: Marina Borges | B51: casa nova | C51: 25500 | E51: =IF($C51="","",ROUND(SUM(I51,L51,O51,R51,U51),2)) | F51: =IF($C51="","",ROUND($C51-$E51,2)) | G51: =IF(OR($C51="",$C51=0),"",$E51/$C51) | H51: =IF($C51="","",IF($E51=0,"A receber",IF(ROUND($F51,2)=0,"Quitado",IF($F51<0,"Recebido a mais","Parcial")))) | I51: 15500 | J51: 46167 | K51: pix | X51: =IF($C51="","",$F51) | Y51: =IF($C51="","",$C51)
A52: Maria - Vale dos cristais | B52: Painel hall garagem | C52: 18100 | D52: 50% + 50% | E52: =IF($C52="","",ROUND(SUM(I52,L52,O52,R52,U52),2)) | F52: =IF($C52="","",ROUND($C52-$E52,2)) | G52: =IF(OR($C52="",$C52=0),"",$E52/$C52) | H52: =IF($C52="","",IF($E52=0,"A receber",IF(ROUND($F52,2)=0,"Quitado",IF($F52<0,"Recebido a mais","Parcial")))) | I52: 9050 | J52: 46155 | K52: pix | X52: =IF($C52="","",$F52) | Y52: =IF($C52="","",$C52)
A53: Marcelo e Simony | B53: apt novo | C53: 34850 | D53: 30% + 10vz cartao | E53: =IF($C53="","",ROUND(SUM(I53,L53,O53,R53,U53),2)) | F53: =IF($C53="","",ROUND($C53-$E53,2)) | G53: =IF(OR($C53="",$C53=0),"",$E53/$C53) | H53: =IF($C53="","",IF($E53=0,"A receber",IF(ROUND($F53,2)=0,"Quitado",IF($F53<0,"Recebido a mais","Parcial")))) | I53: 13150 | J53: 46192 | K53: pix | X53: =IF($C53="","",$F53) | Y53: =IF($C53="","",$C53)
E54: =IF($C54="","",ROUND(SUM(I54,L54,O54,R54,U54),2)) | F54: =IF($C54="","",ROUND($C54-$E54,2)) | G54: =IF(OR($C54="",$C54=0),"",$E54/$C54) | H54: =IF($C54="","",IF($E54=0,"A receber",IF(ROUND($F54,2)=0,"Quitado",IF($F54<0,"Recebido a mais","Parcial")))) | X54: =IF($C54="","",$F54) | Y54: =IF($C54="","",$C54)
E55: =IF($C55="","",ROUND(SUM(I55,L55,O55,R55,U55),2)) | F55: =IF($C55="","",ROUND($C55-$E55,2)) | G55: =IF(OR($C55="",$C55=0),"",$E55/$C55) | H55: =IF($C55="","",IF($E55=0,"A receber",IF(ROUND($F55,2)=0,"Quitado",IF($F55<0,"Recebido a mais","Parcial")))) | X55: =IF($C55="","",$F55) | Y55: =IF($C55="","",$C55)
E56: =IF($C56="","",ROUND(SUM(I56,L56,O56,R56,U56),2)) | F56: =IF($C56="","",ROUND($C56-$E56,2)) | G56: =IF(OR($C56="",$C56=0),"",$E56/$C56) | H56: =IF($C56="","",IF($E56=0,"A receber",IF(ROUND($F56,2)=0,"Quitado",IF($F56<0,"Recebido a mais","Parcial")))) | X56: =IF($C56="","",$F56) | Y56: =IF($C56="","",$C56)
A58: Junho | C58: =SUM(C59:C67) | E58: =SUM(E59:E67) | F58: =SUM(F59:F67) | G58: =IF(OR(C58="",C58=0),"",E58/C58) | H58: =COUNT(C59:C67)&" projeto(s)"
A59: Fabio | B59: consultorio | C59: 9200 | D59: 50% + 50% | E59: =IF($C59="","",ROUND(SUM(I59,L59,O59,R59,U59),2)) | F59: =IF($C59="","",ROUND($C59-$E59,2)) | G59: =IF(OR($C59="",$C59=0),"",$E59/$C59) | H59: =IF($C59="","",IF($E59=0,"A receber",IF(ROUND($F59,2)=0,"Quitado",IF($F59<0,"Recebido a mais","Parcial")))) | I59: 5000 | J59: 46175 | K59: pix | L59: 4200 | X59: =IF($C59="","",$F59) | Y59: =IF($C59="","",$C59)
A60: Alexandrina | B60: lavanderia | C60: 4278 | D60: na entrega | E60: =IF($C60="","",ROUND(SUM(I60,L60,O60,R60,U60),2)) | F60: =IF($C60="","",ROUND($C60-$E60,2)) | G60: =IF(OR($C60="",$C60=0),"",$E60/$C60) | H60: =IF($C60="","",IF($E60=0,"A receber",IF(ROUND($F60,2)=0,"Quitado",IF($F60<0,"Recebido a mais","Parcial")))) | I60: 2300 | J60: 46198 | K60: pix | X60: =IF($C60="","",$F60) | Y60: =IF($C60="","",$C60)
A61: Bernardo | B61: cozinha e banheiro | C61: 12900 | E61: =IF($C61="","",ROUND(SUM(I61,L61,O61,R61,U61),2)) | F61: =IF($C61="","",ROUND($C61-$E61,2)) | G61: =IF(OR($C61="",$C61=0),"",$E61/$C61) | H61: =IF($C61="","",IF($E61=0,"A receber",IF(ROUND($F61,2)=0,"Quitado",IF($F61<0,"Recebido a mais","Parcial")))) | I61: 3900 | J61: 46185 | K61: pix | X61: =IF($C61="","",$F61) | Y61: =IF($C61="","",$C61)
A62: Carla | B62: cozinha | C62: 27000 | D62: 50% + 50% | E62: =IF($C62="","",ROUND(SUM(I62,L62,O62,R62,U62),2)) | F62: =IF($C62="","",ROUND($C62-$E62,2)) | G62: =IF(OR($C62="",$C62=0),"",$E62/$C62) | H62: =IF($C62="","",IF($E62=0,"A receber",IF(ROUND($F62,2)=0,"Quitado",IF($F62<0,"Recebido a mais","Parcial")))) | I62: 13500 | J62: 46190 | K62: pix | X62: =IF($C62="","",$F62) | Y62: =IF($C62="","",$C62)
A63: Lucas Mello | B63: Casa | C63: 46000 | D63: 50% + 50% | E63: =IF($C63="","",ROUND(SUM(I63,L63,O63,R63,U63),2)) | F63: =IF($C63="","",ROUND($C63-$E63,2)) | G63: =IF(OR($C63="",$C63=0),"",$E63/$C63) | H63: =IF($C63="","",IF($E63=0,"A receber",IF(ROUND($F63,2)=0,"Quitado",IF($F63<0,"Recebido a mais","Parcial")))) | I63: 24000 | J63: 46184 | K63: pix | X63: =IF($C63="","",$F63) | Y63: =IF($C63="","",$C63)
A64: Luciana Rajao | B64: manutencoes | C64: 12000 | D64: boletos - 30/60/90 | E64: =IF($C64="","",ROUND(SUM(I64,L64,O64,R64,U64),2)) | F64: =IF($C64="","",ROUND($C64-$E64,2)) | G64: =IF(OR($C64="",$C64=0),"",$E64/$C64) | H64: =IF($C64="","",IF($E64=0,"A receber",IF(ROUND($F64,2)=0,"Quitado",IF($F64<0,"Recebido a mais","Parcial")))) | X64: =IF($C64="","",$F64) | Y64: =IF($C64="","",$C64)
E65: =IF($C65="","",ROUND(SUM(I65,L65,O65,R65,U65),2)) | F65: =IF($C65="","",ROUND($C65-$E65,2)) | G65: =IF(OR($C65="",$C65=0),"",$E65/$C65) | H65: =IF($C65="","",IF($E65=0,"A receber",IF(ROUND($F65,2)=0,"Quitado",IF($F65<0,"Recebido a mais","Parcial")))) | X65: =IF($C65="","",$F65) | Y65: =IF($C65="","",$C65)
E66: =IF($C66="","",ROUND(SUM(I66,L66,O66,R66,U66),2)) | F66: =IF($C66="","",ROUND($C66-$E66,2)) | G66: =IF(OR($C66="",$C66=0),"",$E66/$C66) | H66: =IF($C66="","",IF($E66=0,"A receber",IF(ROUND($F66,2)=0,"Quitado",IF($F66<0,"Recebido a mais","Parcial")))) | X66: =IF($C66="","",$F66) | Y66: =IF($C66="","",$C66)
E67: =IF($C67="","",ROUND(SUM(I67,L67,O67,R67,U67),2)) | F67: =IF($C67="","",ROUND($C67-$E67,2)) | G67: =IF(OR($C67="",$C67=0),"",$E67/$C67) | H67: =IF($C67="","",IF($E67=0,"A receber",IF(ROUND($F67,2)=0,"Quitado",IF($F67<0,"Recebido a mais","Parcial")))) | X67: =IF($C67="","",$F67) | Y67: =IF($C67="","",$C67)
A69: Julho | C69: =SUM(C70:C78) | E69: =SUM(E70:E78) | F69: =SUM(F70:F78) | G69: =IF(OR(C69="",C69=0),"",E69/C69) | H69: =COUNT(C70:C78)&" projeto(s)"
A70: Richard e Camila | B70: Roupeiro | C70: 19000 | D70: 50% + 50+ | E70: =IF($C70="","",ROUND(SUM(I70,L70,O70,R70,U70),2)) | F70: =IF($C70="","",ROUND($C70-$E70,2)) | G70: =IF(OR($C70="",$C70=0),"",$E70/$C70) | H70: =IF($C70="","",IF($E70=0,"A receber",IF(ROUND($F70,2)=0,"Quitado",IF($F70<0,"Recebido a mais","Parcial")))) | X70: =IF($C70="","",$F70) | Y70: =IF($C70="","",$C70)
A71: Ana Carolina | B71: Casa completa | C71: 108490 | E71: =IF($C71="","",ROUND(SUM(I71,L71,O71,R71,U71),2)) | F71: =IF($C71="","",ROUND($C71-$E71,2)) | G71: =IF(OR($C71="",$C71=0),"",$E71/$C71) | H71: =IF($C71="","",IF($E71=0,"A receber",IF(ROUND($F71,2)=0,"Quitado",IF($F71<0,"Recebido a mais","Parcial")))) | I71: 32550 | J71: 46210 | K71: pix | X71: =IF($C71="","",$F71) | Y71: =IF($C71="","",$C71)
A72: Tania | B72: quarto | C72: 8536 | E72: =IF($C72="","",ROUND(SUM(I72,L72,O72,R72,U72),2)) | F72: =IF($C72="","",ROUND($C72-$E72,2)) | G72: =IF(OR($C72="",$C72=0),"",$E72/$C72) | H72: =IF($C72="","",IF($E72=0,"A receber",IF(ROUND($F72,2)=0,"Quitado",IF($F72<0,"Recebido a mais","Parcial")))) | X72: =IF($C72="","",$F72) | Y72: =IF($C72="","",$C72)
A73: Andrea | B73: Clinica dermatologia | C73: 47000 | E73: =IF($C73="","",ROUND(SUM(I73,L73,O73,R73,U73),2)) | F73: =IF($C73="","",ROUND($C73-$E73,2)) | G73: =IF(OR($C73="",$C73=0),"",$E73/$C73) | H73: =IF($C73="","",IF($E73=0,"A receber",IF(ROUND($F73,2)=0,"Quitado",IF($F73<0,"Recebido a mais","Parcial")))) | X73: =IF($C73="","",$F73) | Y73: =IF($C73="","",$C73)
A74: Gisele | B74: Banheiro | C74: 13950 | E74: =IF($C74="","",ROUND(SUM(I74,L74,O74,R74,U74),2)) | F74: =IF($C74="","",ROUND($C74-$E74,2)) | G74: =IF(OR($C74="",$C74=0),"",$E74/$C74) | H74: =IF($C74="","",IF($E74=0,"A receber",IF(ROUND($F74,2)=0,"Quitado",IF($F74<0,"Recebido a mais","Parcial")))) | X74: =IF($C74="","",$F74) | Y74: =IF($C74="","",$C74)
A75: Luiz adv | B75: roupeiro | C75: 5300 | E75: =IF($C75="","",ROUND(SUM(I75,L75,O75,R75,U75),2)) | F75: =IF($C75="","",ROUND($C75-$E75,2)) | G75: =IF(OR($C75="",$C75=0),"",$E75/$C75) | H75: =IF($C75="","",IF($E75=0,"A receber",IF(ROUND($F75,2)=0,"Quitado",IF($F75<0,"Recebido a mais","Parcial")))) | X75: =IF($C75="","",$F75) | Y75: =IF($C75="","",$C75)
E76: =IF($C76="","",ROUND(SUM(I76,L76,O76,R76,U76),2)) | F76: =IF($C76="","",ROUND($C76-$E76,2)) | G76: =IF(OR($C76="",$C76=0),"",$E76/$C76) | H76: =IF($C76="","",IF($E76=0,"A receber",IF(ROUND($F76,2)=0,"Quitado",IF($F76<0,"Recebido a mais","Parcial")))) | X76: =IF($C76="","",$F76) | Y76: =IF($C76="","",$C76)
E77: =IF($C77="","",ROUND(SUM(I77,L77,O77,R77,U77),2)) | F77: =IF($C77="","",ROUND($C77-$E77,2)) | G77: =IF(OR($C77="",$C77=0),"",$E77/$C77) | H77: =IF($C77="","",IF($E77=0,"A receber",IF(ROUND($F77,2)=0,"Quitado",IF($F77<0,"Recebido a mais","Parcial")))) | X77: =IF($C77="","",$F77) | Y77: =IF($C77="","",$C77)
E78: =IF($C78="","",ROUND(SUM(I78,L78,O78,R78,U78),2)) | F78: =IF($C78="","",ROUND($C78-$E78,2)) | G78: =IF(OR($C78="",$C78=0),"",$E78/$C78) | H78: =IF($C78="","",IF($E78=0,"A receber",IF(ROUND($F78,2)=0,"Quitado",IF($F78<0,"Recebido a mais","Parcial")))) | X78: =IF($C78="","",$F78) | Y78: =IF($C78="","",$C78)
A80: Agosto | C80: =SUM(C81:C86) | E80: =SUM(E81:E86) | F80: =SUM(F81:F86) | G80: =IF(OR(C80="",C80=0),"",E80/C80) | H80: =COUNT(C81:C86)&" projeto(s)"
A81: Jairo | B81: casa | C81: 63000 | E81: =IF($C81="","",ROUND(SUM(I81,L81,O81,R81,U81),2)) | F81: =IF($C81="","",ROUND($C81-$E81,2)) | G81: =IF(OR($C81="",$C81=0),"",$E81/$C81) | H81: =IF($C81="","",IF($E81=0,"A receber",IF(ROUND($F81,2)=0,"Quitado",IF($F81<0,"Recebido a mais","Parcial")))) | X81: =IF($C81="","",$F81) | Y81: =IF($C81="","",$C81)
A82: Flavia | B82: hall | C82: 15000 | E82: =IF($C82="","",ROUND(SUM(I82,L82,O82,R82,U82),2)) | F82: =IF($C82="","",ROUND($C82-$E82,2)) | G82: =IF(OR($C82="",$C82=0),"",$E82/$C82) | H82: =IF($C82="","",IF($E82=0,"A receber",IF(ROUND($F82,2)=0,"Quitado",IF($F82<0,"Recebido a mais","Parcial")))) | X82: =IF($C82="","",$F82) | Y82: =IF($C82="","",$C82)
A83: Luiz | B83: Escritorio | C83: 20000 | E83: =IF($C83="","",ROUND(SUM(I83,L83,O83,R83,U83),2)) | F83: =IF($C83="","",ROUND($C83-$E83,2)) | G83: =IF(OR($C83="",$C83=0),"",$E83/$C83) | H83: =IF($C83="","",IF($E83=0,"A receber",IF(ROUND($F83,2)=0,"Quitado",IF($F83<0,"Recebido a mais","Parcial")))) | X83: =IF($C83="","",$F83) | Y83: =IF($C83="","",$C83)
E84: =IF($C84="","",ROUND(SUM(I84,L84,O84,R84,U84),2)) | F84: =IF($C84="","",ROUND($C84-$E84,2)) | G84: =IF(OR($C84="",$C84=0),"",$E84/$C84) | H84: =IF($C84="","",IF($E84=0,"A receber",IF(ROUND($F84,2)=0,"Quitado",IF($F84<0,"Recebido a mais","Parcial")))) | X84: =IF($C84="","",$F84) | Y84: =IF($C84="","",$C84)
E85: =IF($C85="","",ROUND(SUM(I85,L85,O85,R85,U85),2)) | F85: =IF($C85="","",ROUND($C85-$E85,2)) | G85: =IF(OR($C85="",$C85=0),"",$E85/$C85) | H85: =IF($C85="","",IF($E85=0,"A receber",IF(ROUND($F85,2)=0,"Quitado",IF($F85<0,"Recebido a mais","Parcial")))) | X85: =IF($C85="","",$F85) | Y85: =IF($C85="","",$C85)
E86: =IF($C86="","",ROUND(SUM(I86,L86,O86,R86,U86),2)) | F86: =IF($C86="","",ROUND($C86-$E86,2)) | G86: =IF(OR($C86="",$C86=0),"",$E86/$C86) | H86: =IF($C86="","",IF($E86=0,"A receber",IF(ROUND($F86,2)=0,"Quitado",IF($F86<0,"Recebido a mais","Parcial")))) | X86: =IF($C86="","",$F86) | Y86: =IF($C86="","",$C86)
A88: Setembro | C88: =SUM(C89:C91) | E88: =SUM(E89:E91) | F88: =SUM(F89:F91) | G88: =IF(OR(C88="",C88=0),"",E88/C88) | H88: =COUNT(C89:C91)&" projeto(s)"
E89: =IF($C89="","",ROUND(SUM(I89,L89,O89,R89,U89),2)) | F89: =IF($C89="","",ROUND($C89-$E89,2)) | G89: =IF(OR($C89="",$C89=0),"",$E89/$C89) | H89: =IF($C89="","",IF($E89=0,"A receber",IF(ROUND($F89,2)=0,"Quitado",IF($F89<0,"Recebido a mais","Parcial")))) | X89: =IF($C89="","",$F89) | Y89: =IF($C89="","",$C89)
E90: =IF($C90="","",ROUND(SUM(I90,L90,O90,R90,U90),2)) | F90: =IF($C90="","",ROUND($C90-$E90,2)) | G90: =IF(OR($C90="",$C90=0),"",$E90/$C90) | H90: =IF($C90="","",IF($E90=0,"A receber",IF(ROUND($F90,2)=0,"Quitado",IF($F90<0,"Recebido a mais","Parcial")))) | X90: =IF($C90="","",$F90) | Y90: =IF($C90="","",$C90)
E91: =IF($C91="","",ROUND(SUM(I91,L91,O91,R91,U91),2)) | F91: =IF($C91="","",ROUND($C91-$E91,2)) | G91: =IF(OR($C91="",$C91=0),"",$E91/$C91) | H91: =IF($C91="","",IF($E91=0,"A receber",IF(ROUND($F91,2)=0,"Quitado",IF($F91<0,"Recebido a mais","Parcial")))) | X91: =IF($C91="","",$F91) | Y91: =IF($C91="","",$C91)
A93: Outubro | C93: =SUM(C94:C96) | E93: =SUM(E94:E96) | F93: =SUM(F94:F96) | G93: =IF(OR(C93="",C93=0),"",E93/C93) | H93: =COUNT(C94:C96)&" projeto(s)"
E94: =IF($C94="","",ROUND(SUM(I94,L94,O94,R94,U94),2)) | F94: =IF($C94="","",ROUND($C94-$E94,2)) | G94: =IF(OR($C94="",$C94=0),"",$E94/$C94) | H94: =IF($C94="","",IF($E94=0,"A receber",IF(ROUND($F94,2)=0,"Quitado",IF($F94<0,"Recebido a mais","Parcial")))) | X94: =IF($C94="","",$F94) | Y94: =IF($C94="","",$C94)
E95: =IF($C95="","",ROUND(SUM(I95,L95,O95,R95,U95),2)) | F95: =IF($C95="","",ROUND($C95-$E95,2)) | G95: =IF(OR($C95="",$C95=0),"",$E95/$C95) | H95: =IF($C95="","",IF($E95=0,"A receber",IF(ROUND($F95,2)=0,"Quitado",IF($F95<0,"Recebido a mais","Parcial")))) | X95: =IF($C95="","",$F95) | Y95: =IF($C95="","",$C95)
E96: =IF($C96="","",ROUND(SUM(I96,L96,O96,R96,U96),2)) | F96: =IF($C96="","",ROUND($C96-$E96,2)) | G96: =IF(OR($C96="",$C96=0),"",$E96/$C96) | H96: =IF($C96="","",IF($E96=0,"A receber",IF(ROUND($F96,2)=0,"Quitado",IF($F96<0,"Recebido a mais","Parcial")))) | X96: =IF($C96="","",$F96) | Y96: =IF($C96="","",$C96)
A98: Novembro | C98: =SUM(C99:C101) | E98: =SUM(E99:E101) | F98: =SUM(F99:F101) | G98: =IF(OR(C98="",C98=0),"",E98/C98) | H98: =COUNT(C99:C101)&" projeto(s)"
E99: =IF($C99="","",ROUND(SUM(I99,L99,O99,R99,U99),2)) | F99: =IF($C99="","",ROUND($C99-$E99,2)) | G99: =IF(OR($C99="",$C99=0),"",$E99/$C99) | H99: =IF($C99="","",IF($E99=0,"A receber",IF(ROUND($F99,2)=0,"Quitado",IF($F99<0,"Recebido a mais","Parcial")))) | X99: =IF($C99="","",$F99) | Y99: =IF($C99="","",$C99)
E100: =IF($C100="","",ROUND(SUM(I100,L100,O100,R100,U100),2)) | F100: =IF($C100="","",ROUND($C100-$E100,2)) | G100: =IF(OR($C100="",$C100=0),"",$E100/$C100) | H100: =IF($C100="","",IF($E100=0,"A receber",IF(ROUND($F100,2)=0,"Quitado",IF($F100<0,"Recebido a mais","Parcial")))) | X100: =IF($C100="","",$F100) | Y100: =IF($C100="","",$C100)
E101: =IF($C101="","",ROUND(SUM(I101,L101,O101,R101,U101),2)) | F101: =IF($C101="","",ROUND($C101-$E101,2)) | G101: =IF(OR($C101="",$C101=0),"",$E101/$C101) | H101: =IF($C101="","",IF($E101=0,"A receber",IF(ROUND($F101,2)=0,"Quitado",IF($F101<0,"Recebido a mais","Parcial")))) | X101: =IF($C101="","",$F101) | Y101: =IF($C101="","",$C101)
A103: Dezembro | C103: =SUM(C104:C106) | E103: =SUM(E104:E106) | F103: =SUM(F104:F106) | G103: =IF(OR(C103="",C103=0),"",E103/C103) | H103: =COUNT(C104:C106)&" projeto(s)"
E104: =IF($C104="","",ROUND(SUM(I104,L104,O104,R104,U104),2)) | F104: =IF($C104="","",ROUND($C104-$E104,2)) | G104: =IF(OR($C104="",$C104=0),"",$E104/$C104) | H104: =IF($C104="","",IF($E104=0,"A receber",IF(ROUND($F104,2)=0,"Quitado",IF($F104<0,"Recebido a mais","Parcial")))) | X104: =IF($C104="","",$F104) | Y104: =IF($C104="","",$C104)
E105: =IF($C105="","",ROUND(SUM(I105,L105,O105,R105,U105),2)) | F105: =IF($C105="","",ROUND($C105-$E105,2)) | G105: =IF(OR($C105="",$C105=0),"",$E105/$C105) | H105: =IF($C105="","",IF($E105=0,"A receber",IF(ROUND($F105,2)=0,"Quitado",IF($F105<0,"Recebido a mais","Parcial")))) | X105: =IF($C105="","",$F105) | Y105: =IF($C105="","",$C105)
E106: =IF($C106="","",ROUND(SUM(I106,L106,O106,R106,U106),2)) | F106: =IF($C106="","",ROUND($C106-$E106,2)) | G106: =IF(OR($C106="",$C106=0),"",$E106/$C106) | H106: =IF($C106="","",IF($E106=0,"A receber",IF(ROUND($F106,2)=0,"Quitado",IF($F106<0,"Recebido a mais","Parcial")))) | X106: =IF($C106="","",$F106) | Y106: =IF($C106="","",$C106)

Sheet 2025
A1: VALVIC MARCENARIA
A2: Vargas Decor Ltda · CNPJ 17.269.304/0001-51 · Belo Horizonte / MG
A3: CONTROLE DE PAGAMENTOS · 2025
A4: Uma linha por projeto · fundo creme = você preenche · fundo cinza = calculado · Recebido, Saldo, % e Situação saem sozinhos
A6: VENDIDO NO ANO | D6: RECEBIDO | F6: A RECEBER | H6: % RECEBIDO | I6: META DO ANO | L6: % DA META | O6: FALTA PARA A META | R6: CONFERÊNCIA
A7: =ROUND(SUMPRODUCT((COUNTIF(Listas!$A$2:$A$15,$A$10:$A$111)=0)*$C$10:$C$111),2) | D7: =ROUND(SUM($I$10:$I$111,$L$10:$L$111,$O$10:$O$111,$R$10:$R$111,$U$10:$U$111),2) | F7: =ROUND($A$7-$D$7,2) | H7: =IF($A$7=0,"",$D$7/$A$7) | I7: 2000000 | L7: =IF(OR($I$7="",$I$7=0),"",$A$7/$I$7) | O7: =IF(OR($I$7="",$I$7=0),"",MAX(0,$I$7-$A$7)) | R7: =IF(ROUND(($C$10+$C$20+$C$29+$C$40+$C$51+$C$58+$C$69+$C$78+$C$83+$C$95+$C$100+$C$106)-$A$7,2)=0,"OK · os meses somam igual às linhas","DIVERGE em "&TEXT(($C$10+$C$20+$C$29+$C$40+$C$51+$C$58+$C$69+$C$78+$C$83+$C$95+$C$100+$C$106)-$A$7,"R$ #,##0.00")& " — confira se alguma linha ficou fora de um bloco de mês")
A9: Cliente | B9: Projeto | C9: Investimento | D9: Forma de pagamento | E9: Recebido | F9: Saldo a receber | G9: % recebido | H9: Situação | I9: 1º Pagt. (R$) | J9: Data | K9: Descrição | L9: 2º Pagt. (R$) | M9: Data | N9: Descrição | O9: 3º Pagt. (R$) | P9: Data | Q9: Descrição | R9: 4º Pagt. (R$) | S9: Data | T9: Descrição | U9: 5º Pagt. (R$) | V9: Data | W9: Descrição | X9: aux | Y9: aux2
A10: Janeiro | C10: =SUM(C11:C18) | E10: =SUM(E11:E18) | F10: =SUM(F11:F18) | G10: =IF(OR(C10="",C10=0),"",E10/C10) | H10: =COUNT(C11:C18)&" projeto(s)"
A11: Sirlei | B11: Closet | C11: 37800 | E11: =IF($C11="","",ROUND(SUM(I11,L11,O11,R11,U11),2)) | F11: =IF($C11="","",ROUND($C11-$E11,2)) | G11: =IF(OR($C11="",$C11=0),"",$E11/$C11) | H11: =IF($C11="","",IF($E11=0,"A receber",IF(ROUND($F11,2)=0,"Quitado",IF($F11<0,"Recebido a mais","Parcial")))) | I11: 20000 | L11: 17800 | X11: =IF($C11="","",$F11) | Y11: =IF($C11="","",$C11)
A12: Tiago Matias | B12: Quarto filha | C12: 15000 | E12: =IF($C12="","",ROUND(SUM(I12,L12,O12,R12,U12),2)) | F12: =IF($C12="","",ROUND($C12-$E12,2)) | G12: =IF(OR($C12="",$C12=0),"",$E12/$C12) | H12: =IF($C12="","",IF($E12=0,"A receber",IF(ROUND($F12,2)=0,"Quitado",IF($F12<0,"Recebido a mais","Parcial")))) | I12: 7500 | L12: 7500 | X12: =IF($C12="","",$F12) | Y12: =IF($C12="","",$C12)
A13: Adriano | B13: roupeiro e cozinha | C13: 11126 | E13: =IF($C13="","",ROUND(SUM(I13,L13,O13,R13,U13),2)) | F13: =IF($C13="","",ROUND($C13-$E13,2)) | G13: =IF(OR($C13="",$C13=0),"",$E13/$C13) | H13: =IF($C13="","",IF($E13=0,"A receber",IF(ROUND($F13,2)=0,"Quitado",IF($F13<0,"Recebido a mais","Parcial")))) | I13: 11126 | X13: =IF($C13="","",$F13) | Y13: =IF($C13="","",$C13)
A14: Eduardo | B14: roupeiro | C14: 5800 | E14: =IF($C14="","",ROUND(SUM(I14,L14,O14,R14,U14),2)) | F14: =IF($C14="","",ROUND($C14-$E14,2)) | G14: =IF(OR($C14="",$C14=0),"",$E14/$C14) | H14: =IF($C14="","",IF($E14=0,"A receber",IF(ROUND($F14,2)=0,"Quitado",IF($F14<0,"Recebido a mais","Parcial")))) | I14: 5800 | X14: =IF($C14="","",$F14) | Y14: =IF($C14="","",$C14)
A15: Shelf | B15: Loja completa | C15: 57000 | E15: =IF($C15="","",ROUND(SUM(I15,L15,O15,R15,U15),2)) | F15: =IF($C15="","",ROUND($C15-$E15,2)) | G15: =IF(OR($C15="",$C15=0),"",$E15/$C15) | H15: =IF($C15="","",IF($E15=0,"A receber",IF(ROUND($F15,2)=0,"Quitado",IF($F15<0,"Recebido a mais","Parcial")))) | I15: 28500 | L15: 28500 | X15: =IF($C15="","",$F15) | Y15: =IF($C15="","",$C15)
A16: Matheus e Hanna | B16: Armario bancada | C16: 4600 | E16: =IF($C16="","",ROUND(SUM(I16,L16,O16,R16,U16),2)) | F16: =IF($C16="","",ROUND($C16-$E16,2)) | G16: =IF(OR($C16="",$C16=0),"",$E16/$C16) | H16: =IF($C16="","",IF($E16=0,"A receber",IF(ROUND($F16,2)=0,"Quitado",IF($F16<0,"Recebido a mais","Parcial")))) | I16: 4600 | N16: pix | X16: =IF($C16="","",$F16) | Y16: =IF($C16="","",$C16)
E17: =IF($C17="","",ROUND(SUM(I17,L17,O17,R17,U17),2)) | F17: =IF($C17="","",ROUND($C17-$E17,2)) | G17: =IF(OR($C17="",$C17=0),"",$E17/$C17) | H17: =IF($C17="","",IF($E17=0,"A receber",IF(ROUND($F17,2)=0,"Quitado",IF($F17<0,"Recebido a mais","Parcial")))) | X17: =IF($C17="","",$F17) | Y17: =IF($C17="","",$C17)
E18: =IF($C18="","",ROUND(SUM(I18,L18,O18,R18,U18),2)) | F18: =IF($C18="","",ROUND($C18-$E18,2)) | G18: =IF(OR($C18="",$C18=0),"",$E18/$C18) | H18: =IF($C18="","",IF($E18=0,"A receber",IF(ROUND($F18,2)=0,"Quitado",IF($F18<0,"Recebido a mais","Parcial")))) | X18: =IF($C18="","",$F18) | Y18: =IF($C18="","",$C18)
A20: Fevereiro | C20: =SUM(C21:C27) | E20: =SUM(E21:E27) | F20: =SUM(F21:F27) | G20: =IF(OR(C20="",C20=0),"",E20/C20) | H20: =COUNT(C21:C27)&" projeto(s)"
A21: Jessica Sollero | B21: Quarto filha | C21: 6200 | E21: =IF($C21="","",ROUND(SUM(I21,L21,O21,R21,U21),2)) | F21: =IF($C21="","",ROUND($C21-$E21,2)) | G21: =IF(OR($C21="",$C21=0),"",$E21/$C21) | H21: =IF($C21="","",IF($E21=0,"A receber",IF(ROUND($F21,2)=0,"Quitado",IF($F21<0,"Recebido a mais","Parcial")))) | I21: 6200 | X21: =IF($C21="","",$F21) | Y21: =IF($C21="","",$C21)
A22: Patricia | B22: Mesa lateral lamina | C22: 4850 | E22: =IF($C22="","",ROUND(SUM(I22,L22,O22,R22,U22),2)) | F22: =IF($C22="","",ROUND($C22-$E22,2)) | G22: =IF(OR($C22="",$C22=0),"",$E22/$C22) | H22: =IF($C22="","",IF($E22=0,"A receber",IF(ROUND($F22,2)=0,"Quitado",IF($F22<0,"Recebido a mais","Parcial")))) | I22: 2425 | L22: 2425 | X22: =IF($C22="","",$F22) | Y22: =IF($C22="","",$C22)
A23: Vania | B23: Czinha | C23: 9170 | E23: =IF($C23="","",ROUND(SUM(I23,L23,O23,R23,U23),2)) | F23: =IF($C23="","",ROUND($C23-$E23,2)) | G23: =IF(OR($C23="",$C23=0),"",$E23/$C23) | H23: =IF($C23="","",IF($E23=0,"A receber",IF(ROUND($F23,2)=0,"Quitado",IF($F23<0,"Recebido a mais","Parcial")))) | I23: 9170 | X23: =IF($C23="","",$F23) | Y23: =IF($C23="","",$C23)
A24: Sirlei | B24: quartos e banheiros | C24: 22500 | E24: =IF($C24="","",ROUND(SUM(I24,L24,O24,R24,U24),2)) | F24: =IF($C24="","",ROUND($C24-$E24,2)) | G24: =IF(OR($C24="",$C24=0),"",$E24/$C24) | H24: =IF($C24="","",IF($E24=0,"A receber",IF(ROUND($F24,2)=0,"Quitado",IF($F24<0,"Recebido a mais","Parcial")))) | I24: 11250 | L24: 11250 | X24: =IF($C24="","",$F24) | Y24: =IF($C24="","",$C24)
A25: Seal | B25: Bancada | C25: 3500 | E25: =IF($C25="","",ROUND(SUM(I25,L25,O25,R25,U25),2)) | F25: =IF($C25="","",ROUND($C25-$E25,2)) | G25: =IF(OR($C25="",$C25=0),"",$E25/$C25) | H25: =IF($C25="","",IF($E25=0,"A receber",IF(ROUND($F25,2)=0,"Quitado",IF($F25<0,"Recebido a mais","Parcial")))) | I25: 3500 | X25: =IF($C25="","",$F25) | Y25: =IF($C25="","",$C25)
E26: =IF($C26="","",ROUND(SUM(I26,L26,O26,R26,U26),2)) | F26: =IF($C26="","",ROUND($C26-$E26,2)) | G26: =IF(OR($C26="",$C26=0),"",$E26/$C26) | H26: =IF($C26="","",IF($E26=0,"A receber",IF(ROUND($F26,2)=0,"Quitado",IF($F26<0,"Recebido a mais","Parcial")))) | X26: =IF($C26="","",$F26) | Y26: =IF($C26="","",$C26)
E27: =IF($C27="","",ROUND(SUM(I27,L27,O27,R27,U27),2)) | F27: =IF($C27="","",ROUND($C27-$E27,2)) | G27: =IF(OR($C27="",$C27=0),"",$E27/$C27) | H27: =IF($C27="","",IF($E27=0,"A receber",IF(ROUND($F27,2)=0,"Quitado",IF($F27<0,"Recebido a mais","Parcial")))) | X27: =IF($C27="","",$F27) | Y27: =IF($C27="","",$C27)
A29: Março | C29: =SUM(C30:C38) | E29: =SUM(E30:E38) | F29: =SUM(F30:F38) | G29: =IF(OR(C29="",C29=0),"",E29/C29) | H29: =COUNT(C30:C38)&" projeto(s)"
A30: Valeska | B30: quarto bebe, hospede e cab | C30: 20000 | E30: =IF($C30="","",ROUND(SUM(I30,L30,O30,R30,U30),2)) | F30: =IF($C30="","",ROUND($C30-$E30,2)) | G30: =IF(OR($C30="",$C30=0),"",$E30/$C30) | H30: =IF($C30="","",IF($E30=0,"A receber",IF(ROUND($F30,2)=0,"Quitado",IF($F30<0,"Recebido a mais","Parcial")))) | I30: 20000 | K30: cartao e pix | X30: =IF($C30="","",$F30) | Y30: =IF($C30="","",$C30)
A31: Ana maria | B31: buffet | C31: 3150 | E31: =IF($C31="","",ROUND(SUM(I31,L31,O31,R31,U31),2)) | F31: =IF($C31="","",ROUND($C31-$E31,2)) | G31: =IF(OR($C31="",$C31=0),"",$E31/$C31) | H31: =IF($C31="","",IF($E31=0,"A receber",IF(ROUND($F31,2)=0,"Quitado",IF($F31<0,"Recebido a mais","Parcial")))) | I31: 485 | L31: 1300 | O31: 1365 | X31: =IF($C31="","",$F31) | Y31: =IF($C31="","",$C31)
A32: Ducarmo | B32: Cozinha e roupeiro | C32: 7800 | E32: =IF($C32="","",ROUND(SUM(I32,L32,O32,R32,U32),2)) | F32: =IF($C32="","",ROUND($C32-$E32,2)) | G32: =IF(OR($C32="",$C32=0),"",$E32/$C32) | H32: =IF($C32="","",IF($E32=0,"A receber",IF(ROUND($F32,2)=0,"Quitado",IF($F32<0,"Recebido a mais","Parcial")))) | I32: 3900 | L32: 3900 | X32: =IF($C32="","",$F32) | Y32: =IF($C32="","",$C32)
A33: Sirlei | B33: Cabeceiras | C33: 16000 | E33: =IF($C33="","",ROUND(SUM(I33,L33,O33,R33,U33),2)) | F33: =IF($C33="","",ROUND($C33-$E33,2)) | G33: =IF(OR($C33="",$C33=0),"",$E33/$C33) | H33: =IF($C33="","",IF($E33=0,"A receber",IF(ROUND($F33,2)=0,"Quitado",IF($F33<0,"Recebido a mais","Parcial")))) | I33: 6000 | L33: 10000 | X33: =IF($C33="","",$F33) | Y33: =IF($C33="","",$C33)
A34: Janaina | B34: bancadas e painel | C34: 4000 | E34: =IF($C34="","",ROUND(SUM(I34,L34,O34,R34,U34),2)) | F34: =IF($C34="","",ROUND($C34-$E34,2)) | G34: =IF(OR($C34="",$C34=0),"",$E34/$C34) | H34: =IF($C34="","",IF($E34=0,"A receber",IF(ROUND($F34,2)=0,"Quitado",IF($F34<0,"Recebido a mais","Parcial")))) | I34: 4000 | X34: =IF($C34="","",$F34) | Y34: =IF($C34="","",$C34)
A35: Sirlei | B35: Gourmet + paineis | C35: 31000 | E35: =IF($C35="","",ROUND(SUM(I35,L35,O35,R35,U35),2)) | F35: =IF($C35="","",ROUND($C35-$E35,2)) | G35: =IF(OR($C35="",$C35=0),"",$E35/$C35) | H35: =IF($C35="","",IF($E35=0,"A receber",IF(ROUND($F35,2)=0,"Quitado",IF($F35<0,"Recebido a mais","Parcial")))) | I35: 15500 | L35: 15500 | X35: =IF($C35="","",$F35) | Y35: =IF($C35="","",$C35)
A36: Mirela | B36: Reforma | C36: 30000 | E36: =IF($C36="","",ROUND(SUM(I36,L36,O36,R36,U36),2)) | F36: =IF($C36="","",ROUND($C36-$E36,2)) | G36: =IF(OR($C36="",$C36=0),"",$E36/$C36) | H36: =IF($C36="","",IF($E36=0,"A receber",IF(ROUND($F36,2)=0,"Quitado",IF($F36<0,"Recebido a mais","Parcial")))) | I36: 15000 | L36: 10000 | M36: 45861 | N36: pix | O36: 5000 | Q36: pix | X36: =IF($C36="","",$F36) | Y36: =IF($C36="","",$C36)
E37: =IF($C37="","",ROUND(SUM(I37,L37,O37,R37,U37),2)) | F37: =IF($C37="","",ROUND($C37-$E37,2)) | G37: =IF(OR($C37="",$C37=0),"",$E37/$C37) | H37: =IF($C37="","",IF($E37=0,"A receber",IF(ROUND($F37,2)=0,"Quitado",IF($F37<0,"Recebido a mais","Parcial")))) | X37: =IF($C37="","",$F37) | Y37: =IF($C37="","",$C37)
E38: =IF($C38="","",ROUND(SUM(I38,L38,O38,R38,U38),2)) | F38: =IF($C38="","",ROUND($C38-$E38,2)) | G38: =IF(OR($C38="",$C38=0),"",$E38/$C38) | H38: =IF($C38="","",IF($E38=0,"A receber",IF(ROUND($F38,2)=0,"Quitado",IF($F38<0,"Recebido a mais","Parcial")))) | X38: =IF($C38="","",$F38) | Y38: =IF($C38="","",$C38)
A40: Abril | C40: =SUM(C41:C49) | E40: =SUM(E41:E49) | F40: =SUM(F41:F49) | G40: =IF(OR(C40="",C40=0),"",E40/C40) | H40: =COUNT(C41:C49)&" projeto(s)"
A41: Seal | B41: Painel | C41: 12250 | D41: 30 dias apos a nota | E41: =IF($C41="","",ROUND(SUM(I41,L41,O41,R41,U41),2)) | F41: =IF($C41="","",ROUND($C41-$E41,2)) | G41: =IF(OR($C41="",$C41=0),"",$E41/$C41) | H41: =IF($C41="","",IF($E41=0,"A receber",IF(ROUND($F41,2)=0,"Quitado",IF($F41<0,"Recebido a mais","Parcial")))) | I41: 12250 | J41: 45791 | K41: pix | X41: =IF($C41="","",$F41) | Y41: =IF($C41="","",$C41)
A42: Savio | B42: Casa nova | C42: 64320 | D42: entrada + 20% + final no cartao | E42: =IF($C42="","",ROUND(SUM(I42,L42,O42,R42,U42),2)) | F42: =IF($C42="","",ROUND($C42-$E42,2)) | G42: =IF(OR($C42="",$C42=0),"",$E42/$C42) | H42: =IF($C42="","",IF($E42=0,"A receber",IF(ROUND($F42,2)=0,"Quitado",IF($F42<0,"Recebido a mais","Parcial")))) | I42: 25700 | J42: 45769 | K42: pix | L42: 12800 | M42: 45817 | N42: pix | O42: 25820 | P42: 45832 | Q42: cartao | X42: =IF($C42="","",$F42) | Y42: =IF($C42="","",$C42)
A43: Lucas Campara | B43: casa completa | C43: 45000 | D43: Entrada + final no cartao | E43: =IF($C43="","",ROUND(SUM(I43,L43,O43,R43,U43),2)) | F43: =IF($C43="","",ROUND($C43-$E43,2)) | G43: =IF(OR($C43="",$C43=0),"",$E43/$C43) | H43: =IF($C43="","",IF($E43=0,"A receber",IF(ROUND($F43,2)=0,"Quitado",IF($F43<0,"Recebido a mais","Parcial")))) | I43: 22500 | J43: 45764 | K43: pix | L43: 11250 | M43: 45814 | N43: cartao | O43: 11250 | Q43: pix | X43: =IF($C43="","",$F43) | Y43: =IF($C43="","",$C43)
A44: Fabyola | B44: Loja | C44: 20250 | D44: Entrada + Cartao | E44: =IF($C44="","",ROUND(SUM(I44,L44,O44,R44,U44),2)) | F44: =IF($C44="","",ROUND($C44-$E44,2)) | G44: =IF(OR($C44="",$C44=0),"",$E44/$C44) | H44: =IF($C44="","",IF($E44=0,"A receber",IF(ROUND($F44,2)=0,"Quitado",IF($F44<0,"Recebido a mais","Parcial")))) | I44: 12000 | K44: cartao | L44: 8250 | M44: 45763 | N44: pix | X44: =IF($C44="","",$F44) | Y44: =IF($C44="","",$C44)
A45: Theo | B45: Estante | C45: 3500 | D45: permuta | E45: =IF($C45="","",ROUND(SUM(I45,L45,O45,R45,U45),2)) | F45: =IF($C45="","",ROUND($C45-$E45,2)) | G45: =IF(OR($C45="",$C45=0),"",$E45/$C45) | H45: =IF($C45="","",IF($E45=0,"A receber",IF(ROUND($F45,2)=0,"Quitado",IF($F45<0,"Recebido a mais","Parcial")))) | I45: 3500 | K45: permuta | X45: =IF($C45="","",$F45) | Y45: =IF($C45="","",$C45)
A46: Graciane | B46: Escritorio | C46: 13800 | D46: a vista | E46: =IF($C46="","",ROUND(SUM(I46,L46,O46,R46,U46),2)) | F46: =IF($C46="","",ROUND($C46-$E46,2)) | G46: =IF(OR($C46="",$C46=0),"",$E46/$C46) | H46: =IF($C46="","",IF($E46=0,"A receber",IF(ROUND($F46,2)=0,"Quitado",IF($F46<0,"Recebido a mais","Parcial")))) | I46: 13800 | J46: 45771 | K46: pix | X46: =IF($C46="","",$F46) | Y46: =IF($C46="","",$C46)
A47: Reinaldo | B47: Loja | C47: 20100 | D47: Parcelado | E47: =IF($C47="","",ROUND(SUM(I47,L47,O47,R47,U47),2)) | F47: =IF($C47="","",ROUND($C47-$E47,2)) | G47: =IF(OR($C47="",$C47=0),"",$E47/$C47) | H47: =IF($C47="","",IF($E47=0,"A receber",IF(ROUND($F47,2)=0,"Quitado",IF($F47<0,"Recebido a mais","Parcial")))) | I47: 1000 | X47: =IF($C47="","",$F47) | Y47: =IF($C47="","",$C47)
E48: =IF($C48="","",ROUND(SUM(I48,L48,O48,R48,U48),2)) | F48: =IF($C48="","",ROUND($C48-$E48,2)) | G48: =IF(OR($C48="",$C48=0),"",$E48/$C48) | H48: =IF($C48="","",IF($E48=0,"A receber",IF(ROUND($F48,2)=0,"Quitado",IF($F48<0,"Recebido a mais","Parcial")))) | X48: =IF($C48="","",$F48) | Y48: =IF($C48="","",$C48)
E49: =IF($C49="","",ROUND(SUM(I49,L49,O49,R49,U49),2)) | F49: =IF($C49="","",ROUND($C49-$E49,2)) | G49: =IF(OR($C49="",$C49=0),"",$E49/$C49) | H49: =IF($C49="","",IF($E49=0,"A receber",IF(ROUND($F49,2)=0,"Quitado",IF($F49<0,"Recebido a mais","Parcial")))) | X49: =IF($C49="","",$F49) | Y49: =IF($C49="","",$C49)
A51: Maio | C51: =SUM(C52:C56) | E51: =SUM(E52:E56) | F51: =SUM(F52:F56) | G51: =IF(OR(C51="",C51=0),"",E51/C51) | H51: =COUNT(C52:C56)&" projeto(s)"
A52: Sirley | B52: Lavanderia | C52: 2600 | E52: =IF($C52="","",ROUND(SUM(I52,L52,O52,R52,U52),2)) | F52: =IF($C52="","",ROUND($C52-$E52,2)) | G52: =IF(OR($C52="",$C52=0),"",$E52/$C52) | H52: =IF($C52="","",IF($E52=0,"A receber",IF(ROUND($F52,2)=0,"Quitado",IF($F52<0,"Recebido a mais","Parcial")))) | I52: 2600 | X52: =IF($C52="","",$F52) | Y52: =IF($C52="","",$C52)
A53: Leonidia | B53: Quarto filhos | C53: 8500 | D53: Entrada + restante no final | E53: =IF($C53="","",ROUND(SUM(I53,L53,O53,R53,U53),2)) | F53: =IF($C53="","",ROUND($C53-$E53,2)) | G53: =IF(OR($C53="",$C53=0),"",$E53/$C53) | H53: =IF($C53="","",IF($E53=0,"A receber",IF(ROUND($F53,2)=0,"Quitado",IF($F53<0,"Recebido a mais","Parcial")))) | I53: 4500 | J53: 45786 | K53: pix | L53: 1000 | N53: pix | O53: 1000 | P53: 45807 | Q53: pix | R53: 1000 | S53: 45821 | T53: pix | U53: 1000 | X53: =IF($C53="","",$F53) | Y53: =IF($C53="","",$C53)
A54: Alexandrina | B54: Complemento painel + bancada | C54: 2250 | D54: A vista | E54: =IF($C54="","",ROUND(SUM(I54,L54,O54,R54,U54),2)) | F54: =IF($C54="","",ROUND($C54-$E54,2)) | G54: =IF(OR($C54="",$C54=0),"",$E54/$C54) | H54: =IF($C54="","",IF($E54=0,"A receber",IF(ROUND($F54,2)=0,"Quitado",IF($F54<0,"Recebido a mais","Parcial")))) | I54: 1100 | J54: 45786 | K54: dinheiro | L54: 1150 | M54: 45833 | N54: dinheiro | X54: =IF($C54="","",$F54) | Y54: =IF($C54="","",$C54)
E55: =IF($C55="","",ROUND(SUM(I55,L55,O55,R55,U55),2)) | F55: =IF($C55="","",ROUND($C55-$E55,2)) | G55: =IF(OR($C55="",$C55=0),"",$E55/$C55) | H55: =IF($C55="","",IF($E55=0,"A receber",IF(ROUND($F55,2)=0,"Quitado",IF($F55<0,"Recebido a mais","Parcial")))) | X55: =IF($C55="","",$F55) | Y55: =IF($C55="","",$C55)
E56: =IF($C56="","",ROUND(SUM(I56,L56,O56,R56,U56),2)) | F56: =IF($C56="","",ROUND($C56-$E56,2)) | G56: =IF(OR($C56="",$C56=0),"",$E56/$C56) | H56: =IF($C56="","",IF($E56=0,"A receber",IF(ROUND($F56,2)=0,"Quitado",IF($F56<0,"Recebido a mais","Parcial")))) | X56: =IF($C56="","",$F56) | Y56: =IF($C56="","",$C56)
A58: Junho | C58: =SUM(C59:C67) | E58: =SUM(E59:E67) | F58: =SUM(F59:F67) | G58: =IF(OR(C58="",C58=0),"",E58/C58) | H58: =COUNT(C59:C67)&" projeto(s)"
A59: Regina | B59: Area gourmet e lavanderia | C59: 26055 | E59: =IF($C59="","",ROUND(SUM(I59,L59,O59,R59,U59),2)) | F59: =IF($C59="","",ROUND($C59-$E59,2)) | G59: =IF(OR($C59="",$C59=0),"",$E59/$C59) | H59: =IF($C59="","",IF($E59=0,"A receber",IF(ROUND($F59,2)=0,"Quitado",IF($F59<0,"Recebido a mais","Parcial")))) | I59: 10422 | J59: 45812 | K59: PIX | L59: 15633 | M59: 45880 | N59: pix | X59: =IF($C59="","",$F59) | Y59: =IF($C59="","",$C59)
A60: Graciene | B60: Area de convivencia | C60: 44000 | E60: =IF($C60="","",ROUND(SUM(I60,L60,O60,R60,U60),2)) | F60: =IF($C60="","",ROUND($C60-$E60,2)) | G60: =IF(OR($C60="",$C60=0),"",$E60/$C60) | H60: =IF($C60="","",IF($E60=0,"A receber",IF(ROUND($F60,2)=0,"Quitado",IF($F60<0,"Recebido a mais","Parcial")))) | I60: 22000 | J60: 45839 | K60: pix | L60: 22000 | M60: 45898 | N60: pix | X60: =IF($C60="","",$F60) | Y60: =IF($C60="","",$C60)
A61: Consuelo | B61: rampa | C61: 1800 | E61: =IF($C61="","",ROUND(SUM(I61,L61,O61,R61,U61),2)) | F61: =IF($C61="","",ROUND($C61-$E61,2)) | G61: =IF(OR($C61="",$C61=0),"",$E61/$C61) | H61: =IF($C61="","",IF($E61=0,"A receber",IF(ROUND($F61,2)=0,"Quitado",IF($F61<0,"Recebido a mais","Parcial")))) | I61: 1800 | J61: 45840 | K61: pix | X61: =IF($C61="","",$F61) | Y61: =IF($C61="","",$C61)
A62: Irving | B62: Apt | C62: 27150 | E62: =IF($C62="","",ROUND(SUM(I62,L62,O62,R62,U62),2)) | F62: =IF($C62="","",ROUND($C62-$E62,2)) | G62: =IF(OR($C62="",$C62=0),"",$E62/$C62) | H62: =IF($C62="","",IF($E62=0,"A receber",IF(ROUND($F62,2)=0,"Quitado",IF($F62<0,"Recebido a mais","Parcial")))) | I62: 10800 | J62: 45825 | K62: pix | L62: 4905 | M62: 45911 | N62: pix | O62: 11445 | X62: =IF($C62="","",$F62) | Y62: =IF($C62="","",$C62)
A63: Valeska | B63: Adicionais | C63: 1850 | E63: =IF($C63="","",ROUND(SUM(I63,L63,O63,R63,U63),2)) | F63: =IF($C63="","",ROUND($C63-$E63,2)) | G63: =IF(OR($C63="",$C63=0),"",$E63/$C63) | H63: =IF($C63="","",IF($E63=0,"A receber",IF(ROUND($F63,2)=0,"Quitado",IF($F63<0,"Recebido a mais","Parcial")))) | I63: 1850 | X63: =IF($C63="","",$F63) | Y63: =IF($C63="","",$C63)
A64: Netinho | B64: Cozinha | C64: 4700 | E64: =IF($C64="","",ROUND(SUM(I64,L64,O64,R64,U64),2)) | F64: =IF($C64="","",ROUND($C64-$E64,2)) | G64: =IF(OR($C64="",$C64=0),"",$E64/$C64) | H64: =IF($C64="","",IF($E64=0,"A receber",IF(ROUND($F64,2)=0,"Quitado",IF($F64<0,"Recebido a mais","Parcial")))) | I64: 1900 | K64: Carretos | L64: 1500 | O64: 1300 | X64: =IF($C64="","",$F64) | Y64: =IF($C64="","",$C64)
A65: Claudia - Dubal arq. | B65: Lavanderia + diversos | C65: 18540 | E65: =IF($C65="","",ROUND(SUM(I65,L65,O65,R65,U65),2)) | F65: =IF($C65="","",ROUND($C65-$E65,2)) | G65: =IF(OR($C65="",$C65=0),"",$E65/$C65) | H65: =IF($C65="","",IF($E65=0,"A receber",IF(ROUND($F65,2)=0,"Quitado",IF($F65<0,"Recebido a mais","Parcial")))) | I65: 9270 | J65: 45826 | K65: pix | L65: 9270 | X65: =IF($C65="","",$F65) | Y65: =IF($C65="","",$C65)
E66: =IF($C66="","",ROUND(SUM(I66,L66,O66,R66,U66),2)) | F66: =IF($C66="","",ROUND($C66-$E66,2)) | G66: =IF(OR($C66="",$C66=0),"",$E66/$C66) | H66: =IF($C66="","",IF($E66=0,"A receber",IF(ROUND($F66,2)=0,"Quitado",IF($F66<0,"Recebido a mais","Parcial")))) | X66: =IF($C66="","",$F66) | Y66: =IF($C66="","",$C66)
E67: =IF($C67="","",ROUND(SUM(I67,L67,O67,R67,U67),2)) | F67: =IF($C67="","",ROUND($C67-$E67,2)) | G67: =IF(OR($C67="",$C67=0),"",$E67/$C67) | H67: =IF($C67="","",IF($E67=0,"A receber",IF(ROUND($F67,2)=0,"Quitado",IF($F67<0,"Recebido a mais","Parcial")))) | X67: =IF($C67="","",$F67) | Y67: =IF($C67="","",$C67)
A69: Julho | C69: =SUM(C70:C76) | E69: =SUM(E70:E76) | F69: =SUM(F70:F76) | G69: =IF(OR(C69="",C69=0),"",E69/C69) | H69: =COUNT(C70:C76)&" projeto(s)"
A70: Tom Souto | B70: Stand oiapoque | C70: 8750 | D70: 50% + 50% | E70: =IF($C70="","",ROUND(SUM(I70,L70,O70,R70,U70),2)) | F70: =IF($C70="","",ROUND($C70-$E70,2)) | G70: =IF(OR($C70="",$C70=0),"",$E70/$C70) | H70: =IF($C70="","",IF($E70=0,"A receber",IF(ROUND($F70,2)=0,"Quitado",IF($F70<0,"Recebido a mais","Parcial")))) | I70: 4050 | J70: 45835 | K70: pix | L70: 4700 | M70: 45863 | N70: pix | X70: =IF($C70="","",$F70) | Y70: =IF($C70="","",$C70)
A71: Debora | B71: Reforma apt | C71: 26350 | D71: 50% + cartao ate 10 vezes | E71: =IF($C71="","",ROUND(SUM(I71,L71,O71,R71,U71),2)) | F71: =IF($C71="","",ROUND($C71-$E71,2)) | G71: =IF(OR($C71="",$C71=0),"",$E71/$C71) | H71: =IF($C71="","",IF($E71=0,"A receber",IF(ROUND($F71,2)=0,"Quitado",IF($F71<0,"Recebido a mais","Parcial")))) | I71: 13175 | J71: 45862 | K71: pix | L71: 13175 | N71: pix | X71: =IF($C71="","",$F71) | Y71: =IF($C71="","",$C71)
A72: Vanual | B72: Casa completa | C72: 138580 | D72: Permuta + parcelas | E72: =IF($C72="","",ROUND(SUM(I72,L72,O72,R72,U72),2)) | F72: =IF($C72="","",ROUND($C72-$E72,2)) | G72: =IF(OR($C72="",$C72=0),"",$E72/$C72) | H72: =IF($C72="","",IF($E72=0,"A receber",IF(ROUND($F72,2)=0,"Quitado",IF($F72<0,"Recebido a mais","Parcial")))) | I72: 41600 | J72: 45859 | K72: permuta | L72: 38000 | M72: 45859 | N72: pix | O72: 19660 | P72: 45952 | R72: 39320 | T72: pix | X72: =IF($C72="","",$F72) | Y72: =IF($C72="","",$C72)
A73: Sirley | B73: Escritorio | C73: 7250 | D73: 50%+50% | E73: =IF($C73="","",ROUND(SUM(I73,L73,O73,R73,U73),2)) | F73: =IF($C73="","",ROUND($C73-$E73,2)) | G73: =IF(OR($C73="",$C73=0),"",$E73/$C73) | H73: =IF($C73="","",IF($E73=0,"A receber",IF(ROUND($F73,2)=0,"Quitado",IF($F73<0,"Recebido a mais","Parcial")))) | I73: 3750 | L73: 3500 | M73: 45896 | N73: pix | X73: =IF($C73="","",$F73) | Y73: =IF($C73="","",$C73)
A74: Cristina | B74: Banho Casa | C74: 1450 | D74: 50% + 50% | E74: =IF($C74="","",ROUND(SUM(I74,L74,O74,R74,U74),2)) | F74: =IF($C74="","",ROUND($C74-$E74,2)) | G74: =IF(OR($C74="",$C74=0),"",$E74/$C74) | H74: =IF($C74="","",IF($E74=0,"A receber",IF(ROUND($F74,2)=0,"Quitado",IF($F74<0,"Recebido a mais","Parcial")))) | I74: 725 | J74: 45852 | K74: pix | L74: 725 | X74: =IF($C74="","",$F74) | Y74: =IF($C74="","",$C74)
E75: =IF($C75="","",ROUND(SUM(I75,L75,O75,R75,U75),2)) | F75: =IF($C75="","",ROUND($C75-$E75,2)) | G75: =IF(OR($C75="",$C75=0),"",$E75/$C75) | H75: =IF($C75="","",IF($E75=0,"A receber",IF(ROUND($F75,2)=0,"Quitado",IF($F75<0,"Recebido a mais","Parcial")))) | X75: =IF($C75="","",$F75) | Y75: =IF($C75="","",$C75)
E76: =IF($C76="","",ROUND(SUM(I76,L76,O76,R76,U76),2)) | F76: =IF($C76="","",ROUND($C76-$E76,2)) | G76: =IF(OR($C76="",$C76=0),"",$E76/$C76) | H76: =IF($C76="","",IF($E76=0,"A receber",IF(ROUND($F76,2)=0,"Quitado",IF($F76<0,"Recebido a mais","Parcial")))) | X76: =IF($C76="","",$F76) | Y76: =IF($C76="","",$C76)
A78: Agosto | C78: =SUM(C79:C81) | E78: =SUM(E79:E81) | F78: =SUM(F79:F81) | G78: =IF(OR(C78="",C78=0),"",E78/C78) | H78: =COUNT(C79:C81)&" projeto(s)"
A79: Reginaldo Sigma | B79: Area Gourmet e Lavanderia | C79: 15250 | D79: 60% + 40% | E79: =IF($C79="","",ROUND(SUM(I79,L79,O79,R79,U79),2)) | F79: =IF($C79="","",ROUND($C79-$E79,2)) | G79: =IF(OR($C79="",$C79=0),"",$E79/$C79) | H79: =IF($C79="","",IF($E79=0,"A receber",IF(ROUND($F79,2)=0,"Quitado",IF($F79<0,"Recebido a mais","Parcial")))) | I79: 9150 | J79: 45895 | K79: Cartao | L79: 6100 | M79: 45945 | X79: =IF($C79="","",$F79) | Y79: =IF($C79="","",$C79)
E80: =IF($C80="","",ROUND(SUM(I80,L80,O80,R80,U80),2)) | F80: =IF($C80="","",ROUND($C80-$E80,2)) | G80: =IF(OR($C80="",$C80=0),"",$E80/$C80) | H80: =IF($C80="","",IF($E80=0,"A receber",IF(ROUND($F80,2)=0,"Quitado",IF($F80<0,"Recebido a mais","Parcial")))) | X80: =IF($C80="","",$F80) | Y80: =IF($C80="","",$C80)
E81: =IF($C81="","",ROUND(SUM(I81,L81,O81,R81,U81),2)) | F81: =IF($C81="","",ROUND($C81-$E81,2)) | G81: =IF(OR($C81="",$C81=0),"",$E81/$C81) | H81: =IF($C81="","",IF($E81=0,"A receber",IF(ROUND($F81,2)=0,"Quitado",IF($F81<0,"Recebido a mais","Parcial")))) | X81: =IF($C81="","",$F81) | Y81: =IF($C81="","",$C81)
A83: Setembro | C83: =SUM(C84:C93) | E83: =SUM(E84:E93) | F83: =SUM(F84:F93) | G83: =IF(OR(C83="",C83=0),"",E83/C83) | H83: =COUNT(C84:C93)&" projeto(s)"
A84: Rafael Monte Negro | B84: Valor fechado (60 mil) | C84: 240000 | D84: ficou pendente 13.000 | E84: =IF($C84="","",ROUND(SUM(I84,L84,O84,R84,U84),2)) | F84: =IF($C84="","",ROUND($C84-$E84,2)) | G84: =IF(OR($C84="",$C84=0),"",$E84/$C84) | H84: =IF($C84="","",IF($E84=0,"A receber",IF(ROUND($F84,2)=0,"Quitado",IF($F84<0,"Recebido a mais","Parcial")))) | I84: 180000 | L84: 10000 | M84: 45961 | N84: pix | O84: 10000 | R84: 5000 | U84: 10000 | X84: =IF($C84="","",$F84) | Y84: =IF($C84="","",$C84)
A85: Reginaldo Sigma | B85: Cozinha e sala | C85: 31500 | E85: =IF($C85="","",ROUND(SUM(I85,L85,O85,R85,U85),2)) | F85: =IF($C85="","",ROUND($C85-$E85,2)) | G85: =IF(OR($C85="",$C85=0),"",$E85/$C85) | H85: =IF($C85="","",IF($E85=0,"A receber",IF(ROUND($F85,2)=0,"Quitado",IF($F85<0,"Recebido a mais","Parcial")))) | I85: 16500 | K85: cartao | L85: 10000 | N85: cartao | O85: 5000 | P85: 46034 | Q85: cartao | X85: =IF($C85="","",$F85) | Y85: =IF($C85="","",$C85)
A86: Wallace | B86: Casa completa | C86: 167000 | E86: =IF($C86="","",ROUND(SUM(I86,L86,O86,R86,U86),2)) | F86: =IF($C86="","",ROUND($C86-$E86,2)) | G86: =IF(OR($C86="",$C86=0),"",$E86/$C86) | H86: =IF($C86="","",IF($E86=0,"A receber",IF(ROUND($F86,2)=0,"Quitado",IF($F86<0,"Recebido a mais","Parcial")))) | I86: 70000 | J86: 45918 | K86: Carro | L86: 24000 | M86: 45917 | N86: pix | O86: 24000 | P86: 45954 | Q86: pix | R86: 29000 | T86: pix · 2025-07-11 00:00:00 | U86: 20000 | X86: =IF($C86="","",$F86) | Y86: =IF($C86="","",$C86)
A87: Barbara | B87: Escritorio | C87: 18700 | E87: =IF($C87="","",ROUND(SUM(I87,L87,O87,R87,U87),2)) | F87: =IF($C87="","",ROUND($C87-$E87,2)) | G87: =IF(OR($C87="",$C87=0),"",$E87/$C87) | H87: =IF($C87="","",IF($E87=0,"A receber",IF(ROUND($F87,2)=0,"Quitado",IF($F87<0,"Recebido a mais","Parcial")))) | I87: 9350 | J87: 45913 | K87: cartao | L87: 3000 | M87: 45965 | N87: PIX | O87: 6350 | P87: 45942 | X87: =IF($C87="","",$F87) | Y87: =IF($C87="","",$C87)
A88: Lucas campara | B88: Banheiros | C88: 2500 | E88: =IF($C88="","",ROUND(SUM(I88,L88,O88,R88,U88),2)) | F88: =IF($C88="","",ROUND($C88-$E88,2)) | G88: =IF(OR($C88="",$C88=0),"",$E88/$C88) | H88: =IF($C88="","",IF($E88=0,"A receber",IF(ROUND($F88,2)=0,"Quitado",IF($F88<0,"Recebido a mais","Parcial")))) | I88: 2500 | J88: 45918 | K88: pix | X88: =IF($C88="","",$F88) | Y88: =IF($C88="","",$C88)
A89: Claudia Salum | B89: Area de servico,banho, paineis | C89: 8450 | E89: =IF($C89="","",ROUND(SUM(I89,L89,O89,R89,U89),2)) | F89: =IF($C89="","",ROUND($C89-$E89,2)) | G89: =IF(OR($C89="",$C89=0),"",$E89/$C89) | H89: =IF($C89="","",IF($E89=0,"A receber",IF(ROUND($F89,2)=0,"Quitado",IF($F89<0,"Recebido a mais","Parcial")))) | I89: 4225 | J89: 45924 | K89: pix | L89: 4225 | M89: 45939 | N89: pix | X89: =IF($C89="","",$F89) | Y89: =IF($C89="","",$C89)
A90: Isaias | B90: Painel social e cozinha | C90: 23700 | E90: =IF($C90="","",ROUND(SUM(I90,L90,O90,R90,U90),2)) | F90: =IF($C90="","",ROUND($C90-$E90,2)) | G90: =IF(OR($C90="",$C90=0),"",$E90/$C90) | H90: =IF($C90="","",IF($E90=0,"A receber",IF(ROUND($F90,2)=0,"Quitado",IF($F90<0,"Recebido a mais","Parcial")))) | I90: 10000 | J90: 45947 | K90: transferencia | L90: 5000 | M90: 45985 | N90: transferencia | O90: 8700 | P90: 45707 | Q90: pix | X90: =IF($C90="","",$F90) | Y90: =IF($C90="","",$C90)
A91: Isabela | B91: Casa completa | C91: 81000 | E91: =IF($C91="","",ROUND(SUM(I91,L91,O91,R91,U91),2)) | F91: =IF($C91="","",ROUND($C91-$E91,2)) | G91: =IF(OR($C91="",$C91=0),"",$E91/$C91) | H91: =IF($C91="","",IF($E91=0,"A receber",IF(ROUND($F91,2)=0,"Quitado",IF($F91<0,"Recebido a mais","Parcial")))) | I91: 56700 | J91: 45937 | K91: pix | L91: 24300 | M91: 46071 | N91: pix | X91: =IF($C91="","",$F91) | Y91: =IF($C91="","",$C91)
E92: =IF($C92="","",ROUND(SUM(I92,L92,O92,R92,U92),2)) | F92: =IF($C92="","",ROUND($C92-$E92,2)) | G92: =IF(OR($C92="",$C92=0),"",$E92/$C92) | H92: =IF($C92="","",IF($E92=0,"A receber",IF(ROUND($F92,2)=0,"Quitado",IF($F92<0,"Recebido a mais","Parcial")))) | X92: =IF($C92="","",$F92) | Y92: =IF($C92="","",$C92)
E93: =IF($C93="","",ROUND(SUM(I93,L93,O93,R93,U93),2)) | F93: =IF($C93="","",ROUND($C93-$E93,2)) | G93: =IF(OR($C93="",$C93=0),"",$E93/$C93) | H93: =IF($C93="","",IF($E93=0,"A receber",IF(ROUND($F93,2)=0,"Quitado",IF($F93<0,"Recebido a mais","Parcial")))) | X93: =IF($C93="","",$F93) | Y93: =IF($C93="","",$C93)
A95: Outubro | C95: =SUM(C96:C98) | E95: =SUM(E96:E98) | F95: =SUM(F96:F98) | G95: =IF(OR(C95="",C95=0),"",E95/C95) | H95: =COUNT(C96:C98)&" projeto(s)"
A96: Cibele | B96: Quarto casal, solteiro e banhos | C96: 50000 | E96: =IF($C96="","",ROUND(SUM(I96,L96,O96,R96,U96),2)) | F96: =IF($C96="","",ROUND($C96-$E96,2)) | G96: =IF(OR($C96="",$C96=0),"",$E96/$C96) | H96: =IF($C96="","",IF($E96=0,"A receber",IF(ROUND($F96,2)=0,"Quitado",IF($F96<0,"Recebido a mais","Parcial")))) | I96: 25000 | J96: 45947 | K96: pix | L96: 12500 | M96: 46007 | N96: pix | O96: 12500 | P96: 46064 | Q96: pix | X96: =IF($C96="","",$F96) | Y96: =IF($C96="","",$C96)
E97: =IF($C97="","",ROUND(SUM(I97,L97,O97,R97,U97),2)) | F97: =IF($C97="","",ROUND($C97-$E97,2)) | G97: =IF(OR($C97="",$C97=0),"",$E97/$C97) | H97: =IF($C97="","",IF($E97=0,"A receber",IF(ROUND($F97,2)=0,"Quitado",IF($F97<0,"Recebido a mais","Parcial")))) | X97: =IF($C97="","",$F97) | Y97: =IF($C97="","",$C97)
E98: =IF($C98="","",ROUND(SUM(I98,L98,O98,R98,U98),2)) | F98: =IF($C98="","",ROUND($C98-$E98,2)) | G98: =IF(OR($C98="",$C98=0),"",$E98/$C98) | H98: =IF($C98="","",IF($E98=0,"A receber",IF(ROUND($F98,2)=0,"Quitado",IF($F98<0,"Recebido a mais","Parcial")))) | X98: =IF($C98="","",$F98) | Y98: =IF($C98="","",$C98)
A100: Novembro | C100: =SUM(C101:C104) | E100: =SUM(E101:E104) | F100: =SUM(F101:F104) | G100: =IF(OR(C100="",C100=0),"",E100/C100) | H100: =COUNT(C101:C104)&" projeto(s)"
A101: United airlines | C101: 100500 | E101: =IF($C101="","",ROUND(SUM(I101,L101,O101,R101,U101),2)) | F101: =IF($C101="","",ROUND($C101-$E101,2)) | G101: =IF(OR($C101="",$C101=0),"",$E101/$C101) | H101: =IF($C101="","",IF($E101=0,"A receber",IF(ROUND($F101,2)=0,"Quitado",IF($F101<0,"Recebido a mais","Parcial")))) | I101: 50000 | K101: Boleto | L101: 20000 | M101: 46093 | N101: boleto | O101: 30500 | P101: 46087 | Q101: boleto | X101: =IF($C101="","",$F101) | Y101: =IF($C101="","",$C101)
A102: Jessica Sollero | C102: 9500 | E102: =IF($C102="","",ROUND(SUM(I102,L102,O102,R102,U102),2)) | F102: =IF($C102="","",ROUND($C102-$E102,2)) | G102: =IF(OR($C102="",$C102=0),"",$E102/$C102) | H102: =IF($C102="","",IF($E102=0,"A receber",IF(ROUND($F102,2)=0,"Quitado",IF($F102<0,"Recebido a mais","Parcial")))) | I102: 9500 | X102: =IF($C102="","",$F102) | Y102: =IF($C102="","",$C102)
E103: =IF($C103="","",ROUND(SUM(I103,L103,O103,R103,U103),2)) | F103: =IF($C103="","",ROUND($C103-$E103,2)) | G103: =IF(OR($C103="",$C103=0),"",$E103/$C103) | H103: =IF($C103="","",IF($E103=0,"A receber",IF(ROUND($F103,2)=0,"Quitado",IF($F103<0,"Recebido a mais","Parcial")))) | X103: =IF($C103="","",$F103) | Y103: =IF($C103="","",$C103)
E104: =IF($C104="","",ROUND(SUM(I104,L104,O104,R104,U104),2)) | F104: =IF($C104="","",ROUND($C104-$E104,2)) | G104: =IF(OR($C104="",$C104=0),"",$E104/$C104) | H104: =IF($C104="","",IF($E104=0,"A receber",IF(ROUND($F104,2)=0,"Quitado",IF($F104<0,"Recebido a mais","Parcial")))) | X104: =IF($C104="","",$F104) | Y104: =IF($C104="","",$C104)
A106: Dezembro | C106: =SUM(C107:C111) | E106: =SUM(E107:E111) | F106: =SUM(F107:F111) | G106: =IF(OR(C106="",C106=0),"",E106/C106) | H106: =COUNT(C107:C111)&" projeto(s)"
A107: Evandro | C107: 12000 | E107: =IF($C107="","",ROUND(SUM(I107,L107,O107,R107,U107),2)) | F107: =IF($C107="","",ROUND($C107-$E107,2)) | G107: =IF(OR($C107="",$C107=0),"",$E107/$C107) | H107: =IF($C107="","",IF($E107=0,"A receber",IF(ROUND($F107,2)=0,"Quitado",IF($F107<0,"Recebido a mais","Parcial")))) | I107: 6500 | J107: 45992 | K107: pix | L107: 5500 | M107: 45685 | N107: pix | X107: =IF($C107="","",$F107) | Y107: =IF($C107="","",$C107)
A108: Debora | C108: 13000 | E108: =IF($C108="","",ROUND(SUM(I108,L108,O108,R108,U108),2)) | F108: =IF($C108="","",ROUND($C108-$E108,2)) | G108: =IF(OR($C108="",$C108=0),"",$E108/$C108) | H108: =IF($C108="","",IF($E108=0,"A receber",IF(ROUND($F108,2)=0,"Quitado",IF($F108<0,"Recebido a mais","Parcial")))) | I108: 6500 | J108: 46001 | K108: pix | L108: 6500 | M108: 45686 | N108: pix | X108: =IF($C108="","",$F108) | Y108: =IF($C108="","",$C108)
A109: Netinho | C109: 4850 | E109: =IF($C109="","",ROUND(SUM(I109,L109,O109,R109,U109),2)) | F109: =IF($C109="","",ROUND($C109-$E109,2)) | G109: =IF(OR($C109="",$C109=0),"",$E109/$C109) | H109: =IF($C109="","",IF($E109=0,"A receber",IF(ROUND($F109,2)=0,"Quitado",IF($F109<0,"Recebido a mais","Parcial")))) | I109: 4000 | K109: permuta | L109: 850 | N109: permuta | X109: =IF($C109="","",$F109) | Y109: =IF($C109="","",$C109)
E110: =IF($C110="","",ROUND(SUM(I110,L110,O110,R110,U110),2)) | F110: =IF($C110="","",ROUND($C110-$E110,2)) | G110: =IF(OR($C110="",$C110=0),"",$E110/$C110) | H110: =IF($C110="","",IF($E110=0,"A receber",IF(ROUND($F110,2)=0,"Quitado",IF($F110<0,"Recebido a mais","Parcial")))) | X110: =IF($C110="","",$F110) | Y110: =IF($C110="","",$C110)
E111: =IF($C111="","",ROUND(SUM(I111,L111,O111,R111,U111),2)) | F111: =IF($C111="","",ROUND($C111-$E111,2)) | G111: =IF(OR($C111="",$C111=0),"",$E111/$C111) | H111: =IF($C111="","",IF($E111=0,"A receber",IF(ROUND($F111,2)=0,"Quitado",IF($F111<0,"Recebido a mais","Parcial")))) | X111: =IF($C111="","",$F111) | Y111: =IF($C111="","",$C111)

Sheet 2024
A1: VALVIC MARCENARIA
A2: Vargas Decor Ltda · CNPJ 17.269.304/0001-51 · Belo Horizonte / MG
A3: CONTROLE DE PAGAMENTOS · 2024
A4: Uma linha por projeto · fundo creme = você preenche · fundo cinza = calculado · Recebido, Saldo, % e Situação saem sozinhos
A6: VENDIDO NO ANO | D6: RECEBIDO | F6: A RECEBER | H6: % RECEBIDO | I6: META DO ANO | L6: % DA META | O6: FALTA PARA A META | R6: CONFERÊNCIA
A7: =ROUND(SUMPRODUCT((COUNTIF(Listas!$A$2:$A$15,$A$10:$A$107)=0)*$C$10:$C$107),2) | D7: =ROUND(SUM($I$10:$I$107,$L$10:$L$107,$O$10:$O$107,$R$10:$R$107,$U$10:$U$107),2) | F7: =ROUND($A$7-$D$7,2) | H7: =IF($A$7=0,"",$D$7/$A$7) | L7: =IF(OR($I$7="",$I$7=0),"",$A$7/$I$7) | O7: =IF(OR($I$7="",$I$7=0),"",MAX(0,$I$7-$A$7)) | R7: =IF(ROUND(($C$10+$C$21+$C$35+$C$43+$C$49+$C$57+$C$63+$C$69+$C$76+$C$84+$C$91+$C$99)-$A$7,2)=0,"OK · os meses somam igual às linhas","DIVERGE em "&TEXT(($C$10+$C$21+$C$35+$C$43+$C$49+$C$57+$C$63+$C$69+$C$76+$C$84+$C$91+$C$99)-$A$7,"R$ #,##0.00")& " — confira se alguma linha ficou fora de um bloco de mês")
A9: Cliente | B9: Projeto | C9: Investimento | D9: Forma de pagamento | E9: Recebido | F9: Saldo a receber | G9: % recebido | H9: Situação | I9: 1º Pagt. (R$) | J9: Data | K9: Descrição | L9: 2º Pagt. (R$) | M9: Data | N9: Descrição | O9: 3º Pagt. (R$) | P9: Data | Q9: Descrição | R9: 4º Pagt. (R$) | S9: Data | T9: Descrição | U9: 5º Pagt. (R$) | V9: Data | W9: Descrição | X9: aux | Y9: aux2
A10: Janeiro | C10: =SUM(C11:C19) | E10: =SUM(E11:E19) | F10: =SUM(F11:F19) | G10: =IF(OR(C10="",C10=0),"",E10/C10) | H10: =COUNT(C11:C19)&" projeto(s)"
A11: Alexandre Rissio | B11: Painel (Monte Negro) | C11: 13000 | E11: =IF($C11="","",ROUND(SUM(I11,L11,O11,R11,U11),2)) | F11: =IF($C11="","",ROUND($C11-$E11,2)) | G11: =IF(OR($C11="",$C11=0),"",$E11/$C11) | H11: =IF($C11="","",IF($E11=0,"A receber",IF(ROUND($F11,2)=0,"Quitado",IF($F11<0,"Recebido a mais","Parcial")))) | I11: 5000 | J11: 45345 | K11: pix | L11: 8000 | M11: 45388 | N11: pix | X11: =IF($C11="","",$F11) | Y11: =IF($C11="","",$C11)
