Workbook

Sheet Comissões
A1: VALVIC MARCENARIA · COMISSÕES · LUCAS
A2: A comissão incide sobre o valor líquido — o contrato menos os custos de venda. Preencha as colunas claras; as azuis se calculam sozinhas.
A3: Mês | B3: Cliente | C3: Ambiente / projeto | D3: Valor do contrato | E3: RT | F3: Taxa de máquina | G3: Nota fiscal | H3: Comissão do vendedor | I3: Outros custos | J3: Total de custos | K3: Valor líquido | L3: % | M3: Comissão a receber | N3: Status | O3: Pagamento em | P3: Referência | Q3: Conferir
J4: =IF($D4="","",SUM($E4:$I4)) | K4: =IF($D4="","",$D4-$J4) | L4: =IF($D4="","",0.01) | M4: =IF($D4="","",ROUND($K4*$L4,2)) | Q4: =IF($D4="","",IF($J4>$D4,"custos maiores que o contrato",IF(AND($N4="Pago",$O4=""),"marcado como pago, sem a data",IF($A4="","falta o mês",""))))
J5: =IF($D5="","",SUM($E5:$I5)) | K5: =IF($D5="","",$D5-$J5) | L5: =IF($D5="","",0.01) | M5: =IF($D5="","",ROUND($K5*$L5,2)) | Q5: =IF($D5="","",IF($J5>$D5,"custos maiores que o contrato",IF(AND($N5="Pago",$O5=""),"marcado como pago, sem a data",IF($A5="","falta o mês",""))))
J6: =IF($D6="","",SUM($E6:$I6)) | K6: =IF($D6="","",$D6-$J6) | L6: =IF($D6="","",0.01) | M6: =IF($D6="","",ROUND($K6*$L6,2)) | Q6: =IF($D6="","",IF($J6>$D6,"custos maiores que o contrato",IF(AND($N6="Pago",$O6=""),"marcado como pago, sem a data",IF($A6="","falta o mês",""))))
J7: =IF($D7="","",SUM($E7:$I7)) | K7: =IF($D7="","",$D7-$J7) | L7: =IF($D7="","",0.01) | M7: =IF($D7="","",ROUND($K7*$L7,2)) | Q7: =IF($D7="","",IF($J7>$D7,"custos maiores que o contrato",IF(AND($N7="Pago",$O7=""),"marcado como pago, sem a data",IF($A7="","falta o mês",""))))
J8: =IF($D8="","",SUM($E8:$I8)) | K8: =IF($D8="","",$D8-$J8) | L8: =IF($D8="","",0.01) | M8: =IF($D8="","",ROUND($K8*$L8,2)) | Q8: =IF($D8="","",IF($J8>$D8,"custos maiores que o contrato",IF(AND($N8="Pago",$O8=""),"marcado como pago, sem a data",IF($A8="","falta o mês",""))))
J9: =IF($D9="","",SUM($E9:$I9)) | K9: =IF($D9="","",$D9-$J9) | L9: =IF($D9="","",0.01) | M9: =IF($D9="","",ROUND($K9*$L9,2)) | Q9: =IF($D9="","",IF($J9>$D9,"custos maiores que o contrato",IF(AND($N9="Pago",$O9=""),"marcado como pago, sem a data",IF($A9="","falta o mês",""))))
J10: =IF($D10="","",SUM($E10:$I10)) | K10: =IF($D10="","",$D10-$J10) | L10: =IF($D10="","",0.01) | M10: =IF($D10="","",ROUND($K10*$L10,2)) | Q10: =IF($D10="","",IF($J10>$D10,"custos maiores que o contrato",IF(AND($N10="Pago",$O10=""),"marcado como pago, sem a data",IF($A10="","falta o mês",""))))
J11: =IF($D11="","",SUM($E11:$I11)) | K11: =IF($D11="","",$D11-$J11) | L11: =IF($D11="","",0.01) | M11: =IF($D11="","",ROUND($K11*$L11,2)) | Q11: =IF($D11="","",IF($J11>$D11,"custos maiores que o contrato",IF(AND($N11="Pago",$O11=""),"marcado como pago, sem a data",IF($A11="","falta o mês",""))))
J12: =IF($D12="","",SUM($E12:$I12)) | K12: =IF($D12="","",$D12-$J12) | L12: =IF($D12="","",0.01) | M12: =IF($D12="","",ROUND($K12*$L12,2)) | Q12: =IF($D12="","",IF($J12>$D12,"custos maiores que o contrato",IF(AND($N12="Pago",$O12=""),"marcado como pago, sem a data",IF($A12="","falta o mês",""))))
J13: =IF($D13="","",SUM($E13:$I13)) | K13: =IF($D13="","",$D13-$J13) | L13: =IF($D13="","",0.01) | M13: =IF($D13="","",ROUND($K13*$L13,2)) | Q13: =IF($D13="","",IF($J13>$D13,"custos maiores que o contrato",IF(AND($N13="Pago",$O13=""),"marcado como pago, sem a data",IF($A13="","falta o mês",""))))
J14: =IF($D14="","",SUM($E14:$I14)) | K14: =IF($D14="","",$D14-$J14) | L14: =IF($D14="","",0.01) | M14: =IF($D14="","",ROUND($K14*$L14,2)) | Q14: =IF($D14="","",IF($J14>$D14,"custos maiores que o contrato",IF(AND($N14="Pago",$O14=""),"marcado como pago, sem a data",IF($A14="","falta o mês",""))))
J15: =IF($D15="","",SUM($E15:$I15)) | K15: =IF($D15="","",$D15-$J15) | L15: =IF($D15="","",0.01) | M15: =IF($D15="","",ROUND($K15*$L15,2)) | Q15: =IF($D15="","",IF($J15>$D15,"custos maiores que o contrato",IF(AND($N15="Pago",$O15=""),"marcado como pago, sem a data",IF($A15="","falta o mês",""))))
... J123: =IF($D123="","",SUM($E123:$I123)) | K123: =IF($D123="","",$D123-$J123) | L123: =IF($D123="","",0.01) | M123: =IF($D123="","",ROUND($K123*$L123,2)) | Q123: =IF($D123="","",IF($J123>$D123,"custos maiores que o contrato",IF(AND($N123="Pago",$O123=""),"marcado como pago, sem a data",IF($A123="","falta o mês",""))))

Sheet Painel
A1: PAINEL · LUCAS
A2: Tudo se calcula a partir da aba Comissões. Nada se digita aqui.
B4: NO ANO
B5: Projetos lançados | D5: Valor de contrato | F5: Custos de venda | H5: Valor líquido
B6: =COUNTIF('Comissões'!$D:$D,">0") | D6: =SUM('Comissões'!$D:$D) | F6: =SUM('Comissões'!$J:$J) | H6: =SUM('Comissões'!$K:$K)
B8: Comissão total | D8: Já paga | F8: Em aberto | H8: Prevista
B9: =SUM('Comissões'!$M:$M) | D9: =SUMIF('Comissões'!$N:$N,"Pago",'Comissões'!$M:$M) | F9: =SUMIF('Comissões'!$N:$N,"Em aberto",'Comissões'!$M:$M) | H9: =SUMIF('Comissões'!$N:$N,"Previsto",'Comissões'!$M:$M)
B11: MÊS A MÊS
B12: Mês | C12: Projetos | D12: Contrato | E12: Líquido | F12: Comissão | G12: Paga | H12: Em aberto
B13: Janeiro | C13: =COUNTIFS('Comissões'!$A:$A,"Jan",'Comissões'!$D:$D,">0") | D13: =SUMIF('Comissões'!$A:$A,"Jan",'Comissões'!$D:$D) | E13: =SUMIF('Comissões'!$A:$A,"Jan",'Comissões'!$K:$K) | F13: =SUMIF('Comissões'!$A:$A,"Jan",'Comissões'!$M:$M) | G13: =SUMIFS('Comissões'!$M:$M,'Comissões'!$A:$A,"Jan",'Comissões'!$N:$N,"Pago") | H13: =SUMIFS('Comissões'!$M:$M,'Comissões'!$A:$A,"Jan",'Comissões'!$N:$N,"Em aberto")
B14: Fevereiro | C14: =COUNTIFS('Comissões'!$A:$A,"Fev",'Comissões'!$D:$D,">0") | D14: =SUMIF('Comissões'!$A:$A,"Fev",'Comissões'!$D:$D) | E14: =SUMIF('Comissões'!$A:$A,"Fev",'Comissões'!$K:$K) | F14: =SUMIF('Comissões'!$A:$A,"Fev",'Comissões'!$M:$M) | G14: =SUMIFS('Comissões'!$M:$M,'Comissões'!$A:$A,"Fev",'Comissões'!$N:$N,"Pago") | H14: =SUMIFS('Comissões'!$M:$M,'Comissões'!$A:$A,"Fev",'Comissões'!$N:$N,"Em aberto")
B15: Março | C15: =COUNTIFS('Comissões'!$A:$A,"Mar",'Comissões'!$D:$D,">0") | D15: =SUMIF('Comissões'!$A:$A,"Mar",'Comissões'!$D:$D) | E15: =SUMIF('Comissões'!$A:$A,"Mar",'Comissões'!$K:$K) | F15: =SUMIF('Comissões'!$A:$A,"Mar",'Comissões'!$M:$M) | G15: =SUMIFS('Comissões'!$M:$M,'Comissões'!$A:$A,"Mar",'Comissões'!$N:$N,"Pago") | H15: =SUMIFS('Comissões'!$M:$M,'Comissões'!$A:$A,"Mar",'Comissões'!$N:$N,"Em aberto")
B16: Abril | C16: =COUNTIFS('Comissões'!$A:$A,"Abr",'Comissões'!$D:$D,">0") | D16: =SUMIF('Comissões'!$A:$A,"Abr",'Comissões'!$D:$D) | E16: =SUMIF('Comissões'!$A:$A,"Abr",'Comissões'!$K:$K) | F16: =SUMIF('Comissões'!$A:$A,"Abr",'Comissões'!$M:$M) | G16: =SUMIFS('Comissões'!$M:$M,'Comissões'!$A:$A,"Abr",'Comissões'!$N:$N,"Pago") | H16: =SUMIFS('Comissões'!$M:$M,'Comissões'!$A:$A,"Abr",'Comissões'!$N:$N,"Em aberto")
B17: Maio | C17: =COUNTIFS('Comissões'!$A:$A,"Mai",'Comissões'!$D:$D,">0") | D17: =SUMIF('Comissões'!$A:$A,"Mai",'Comissões'!$D:$D) | E17: =SUMIF('Comissões'!$A:$A,"Mai",'Comissões'!$K:$K) | F17: =SUMIF('Comissões'!$A:$A,"Mai",'Comissões'!$M:$M) | G17: =SUMIFS('Comissões'!$M:$M,'Comissões'!$A:$A,"Mai",'Comissões'!$N:$N,"Pago") | H17: =SUMIFS('Comissões'!$M:$M,'Comissões'!$A:$A,"Mai",'Comissões'!$N:$N,"Em aberto")
B18: Junho | C18: =COUNTIFS('Comissões'!$A:$A,"Jun",'Comissões'!$D:$D,">0") | D18: =SUMIF('Comissões'!$A:$A,"Jun",'Comissões'!$D:$D) | E18: =SUMIF('Comissões'!$A:$A,"Jun",'Comissões'!$K:$K) | F18: =SUMIF('Comissões'!$A:$A,"Jun",'Comissões'!$M:$M) | G18: =SUMIFS('Comissões'!$M:$M,'Comissões'!$A:$A,"Jun",'Comissões'!$N:$N,"Pago") | H18: =SUMIFS('Comissões'!$M:$M,'Comissões'!$A:$A,"Jun",'Comissões'!$N:$N,"Em aberto")
B19: Julho | C19: =COUNTIFS('Comissões'!$A:$A,"Jul",'Comissões'!$D:$D,">0") | D19: =SUMIF('Comissões'!$A:$A,"Jul",'Comissões'!$D:$D) | E19: =SUMIF('Comissões'!$A:$A,"Jul",'Comissões'!$K:$K) | F19: =SUMIF('Comissões'!$A:$A,"Jul",'Comissões'!$M:$M) | G19: =SUMIFS('Comissões'!$M:$M,'Comissões'!$A:$A,"Jul",'Comissões'!$N:$N,"Pago") | H19: =SUMIFS('Comissões'!$M:$M,'Comissões'!$A:$A,"Jul",'Comissões'!$N:$N,"Em aberto")
B20: Agosto | C20: =COUNTIFS('Comissões'!$A:$A,"Ago",'Comissões'!$D:$D,">0") | D20: =SUMIF('Comissões'!$A:$A,"Ago",'Comissões'!$D:$D) | E20: =SUMIF('Comissões'!$A:$A,"Ago",'Comissões'!$K:$K) | F20: =SUMIF('Comissões'!$A:$A,"Ago",'Comissões'!$M:$M) | G20: =SUMIFS('Comissões'!$M:$M,'Comissões'!$A:$A,"Ago",'Comissões'!$N:$N,"Pago") | H20: =SUMIFS('Comissões'!$M:$M,'Comissões'!$A:$A,"Ago",'Comissões'!$N:$N,"Em aberto")
B21: Setembro | C21: =COUNTIFS('Comissões'!$A:$A,"Set",'Comissões'!$D:$D,">0") | D21: =SUMIF('Comissões'!$A:$A,"Set",'Comissões'!$D:$D) | E21: =SUMIF('Comissões'!$A:$A,"Set",'Comissões'!$K:$K) | F21: =SUMIF('Comissões'!$A:$A,"Set",'Comissões'!$M:$M) | G21: =SUMIFS('Comissões'!$M:$M,'Comissões'!$A:$A,"Set",'Comissões'!$N:$N,"Pago") | H21: =SUMIFS('Comissões'!$M:$M,'Comissões'!$A:$A,"Set",'Comissões'!$N:$N,"Em aberto")
B22: Outubro | C22: =COUNTIFS('Comissões'!$A:$A,"Out",'Comissões'!$D:$D,">0") | D22: =SUMIF('Comissões'!$A:$A,"Out",'Comissões'!$D:$D) | E22: =SUMIF('Comissões'!$A:$A,"Out",'Comissões'!$K:$K) | F22: =SUMIF('Comissões'!$A:$A,"Out",'Comissões'!$M:$M) | G22: =SUMIFS('Comissões'!$M:$M,'Comissões'!$A:$A,"Out",'Comissões'!$N:$N,"Pago") | H22: =SUMIFS('Comissões'!$M:$M,'Comissões'!$A:$A,"Out",'Comissões'!$N:$N,"Em aberto")
B23: Novembro | C23: =COUNTIFS('Comissões'!$A:$A,"Nov",'Comissões'!$D:$D,">0") | D23: =SUMIF('Comissões'!$A:$A,"Nov",'Comissões'!$D:$D) | E23: =SUMIF('Comissões'!$A:$A,"Nov",'Comissões'!$K:$K) | F23: =SUMIF('Comissões'!$A:$A,"Nov",'Comissões'!$M:$M) | G23: =SUMIFS('Comissões'!$M:$M,'Comissões'!$A:$A,"Nov",'Comissões'!$N:$N,"Pago") | H23: =SUMIFS('Comissões'!$M:$M,'Comissões'!$A:$A,"Nov",'Comissões'!$N:$N,"Em aberto")
B24: Dezembro | C24: =COUNTIFS('Comissões'!$A:$A,"Dez",'Comissões'!$D:$D,">0") | D24: =SUMIF('Comissões'!$A:$A,"Dez",'Comissões'!$D:$D) | E24: =SUMIF('Comissões'!$A:$A,"Dez",'Comissões'!$K:$K) | F24: =SUMIF('Comissões'!$A:$A,"Dez",'Comissões'!$M:$M) | G24: =SUMIFS('Comissões'!$M:$M,'Comissões'!$A:$A,"Dez",'Comissões'!$N:$N,"Pago") | H24: =SUMIFS('Comissões'!$M:$M,'Comissões'!$A:$A,"Dez",'Comissões'!$N:$N,"Em aberto")
B25: Total do ano | C25: =SUM(C13:C24) | D25: =SUM(D13:D24) | E25: =SUM(E13:E24) | F25: =SUM(F13:F24) | G25: =SUM(G13:G24) | H25: =SUM(H13:H24)

Sheet Como funciona
A1: COMO A COMISSÃO É CALCULADA
A2: A mesma regra para todos os projetos. Qualquer dúvida se resolve olhando esta aba.
B4: A conta | C4: A comissão incide sobre o VALOR LÍQUIDO do projeto, nunca sobre o valor de contrato. Líquido = contrato − RT − taxa de máquina − nota fiscal − comissão do vendedor − outros custos de venda.
B5: O percentual | C5: 1% sobre o líquido. A coluna "%" existe em cada linha porque um projeto pode ter percentual diferente — quando houver, o combinado é anotado ali antes do lançamento.
B6: Custos de venda | C6: São os custos que a venda carrega e que não ficam com a empresa: RT da arquiteta ou decoradora, taxa da máquina de cartão, imposto da nota fiscal, a comissão do vendedor e eventuais outros. Cada um tem a sua coluna, para ficar à vista de onde saiu.
B7: Status | C7: PREVISTO — o projeto está lançado mas a comissão ainda não entrou na fila de pagamento. EM ABERTO — está na fila, a pagar. PAGO — pago, com data e referência preenchidas.
B8: Quem preenche | C8: A Valvic lança e atualiza. A planilha é compartilhada com o projetista para acompanhamento — conferir é bem-vindo; qualquer divergência se fala antes do pagamento.
B9: A coluna Conferir | C9: Acende sozinha quando falta o mês, quando o projeto está marcado como pago sem data, ou quando os custos de venda somam mais que o contrato. É uma rede contra erro de digitação.
